package com.vvt.temporalcontrol.normal;

import android.content.BroadcastReceiver;

public class NormalTaskScheduler$TaskScheduledReceiver
  extends BroadcastReceiver
{
  public NormalTaskScheduler$TaskScheduledReceiver(NormalTaskScheduler paramNormalTaskScheduler) {}
  
  /* Error */
  public void onReceive(android.content.Context paramContext, android.content.Intent paramIntent)
  {
    // Byte code:
    //   0: aload_0
    //   1: monitorenter
    //   2: invokestatic 18	com/vvt/temporalcontrol/normal/NormalTaskScheduler:e	()Z
    //   5: istore_3
    //   6: iload_3
    //   7: ifeq +3 -> 10
    //   10: ldc 20
    //   12: astore 4
    //   14: iconst_m1
    //   15: istore 5
    //   17: aload_2
    //   18: aload 4
    //   20: iload 5
    //   22: invokevirtual 26	android/content/Intent:getIntExtra	(Ljava/lang/String;I)I
    //   25: pop
    //   26: ldc 28
    //   28: astore 4
    //   30: lconst_0
    //   31: lstore 6
    //   33: aload_2
    //   34: aload 4
    //   36: lload 6
    //   38: invokevirtual 32	android/content/Intent:getLongExtra	(Ljava/lang/String;J)J
    //   41: lstore 6
    //   43: ldc 34
    //   45: astore 4
    //   47: aload_2
    //   48: aload 4
    //   50: invokevirtual 38	android/content/Intent:getSerializableExtra	(Ljava/lang/String;)Ljava/io/Serializable;
    //   53: astore 4
    //   55: aload 4
    //   57: checkcast 40	com/vvt/preference/PrefTemporalControl$TemporalControlInfo
    //   60: astore 4
    //   62: aload 4
    //   64: ifnull +83 -> 147
    //   67: aload 4
    //   69: invokevirtual 44	com/vvt/preference/PrefTemporalControl$TemporalControlInfo:getTimeBegin	()Ljava/lang/String;
    //   72: pop
    //   73: aload 4
    //   75: invokevirtual 47	com/vvt/preference/PrefTemporalControl$TemporalControlInfo:getTimeEnd	()Ljava/lang/String;
    //   78: pop
    //   79: aload 4
    //   81: invokevirtual 51	com/vvt/preference/PrefTemporalControl$TemporalControlInfo:getAction	()I
    //   84: istore_3
    //   85: invokestatic 54	com/vvt/temporalcontrol/normal/NormalTaskScheduler:f	()Z
    //   88: istore 8
    //   90: iload 8
    //   92: ifeq +3 -> 95
    //   95: aload_0
    //   96: getfield 8	com/vvt/temporalcontrol/normal/NormalTaskScheduler$TaskScheduledReceiver:a	Lcom/vvt/temporalcontrol/normal/NormalTaskScheduler;
    //   99: astore 9
    //   101: aload 9
    //   103: invokestatic 57	com/vvt/temporalcontrol/normal/NormalTaskScheduler:e	(Lcom/vvt/temporalcontrol/normal/NormalTaskScheduler;)Lcom/vvt/temporalcontrol/MyUncaughtExceptionHandler;
    //   106: astore 9
    //   108: aload 9
    //   110: ifnull +26 -> 136
    //   113: aload_0
    //   114: getfield 8	com/vvt/temporalcontrol/normal/NormalTaskScheduler$TaskScheduledReceiver:a	Lcom/vvt/temporalcontrol/normal/NormalTaskScheduler;
    //   117: astore 9
    //   119: aload 9
    //   121: invokestatic 57	com/vvt/temporalcontrol/normal/NormalTaskScheduler:e	(Lcom/vvt/temporalcontrol/normal/NormalTaskScheduler;)Lcom/vvt/temporalcontrol/MyUncaughtExceptionHandler;
    //   124: astore 9
    //   126: aload 9
    //   128: iload_3
    //   129: lload 6
    //   131: invokeinterface 62 4 0
    //   136: invokestatic 18	com/vvt/temporalcontrol/normal/NormalTaskScheduler:e	()Z
    //   139: istore_3
    //   140: iload_3
    //   141: ifeq +3 -> 144
    //   144: aload_0
    //   145: monitorexit
    //   146: return
    //   147: invokestatic 65	com/vvt/temporalcontrol/normal/NormalTaskScheduler:FxFileObserverWorker	()Z
    //   150: istore_3
    //   151: iload_3
    //   152: ifeq -16 -> 136
    //   155: goto -19 -> 136
    //   158: astore 4
    //   160: aload_0
    //   161: monitorexit
    //   162: aload 4
    //   164: athrow
    // Local variable table:
    //   start	length	slot	name	signature
    //   0	165	0	this	TaskScheduledReceiver
    //   0	165	1	paramContext	android.content.Context
    //   0	165	2	paramIntent	android.content.Intent
    //   5	2	3	bool1	boolean
    //   84	45	3	i	int
    //   139	13	3	bool2	boolean
    //   12	68	4	localObject1	Object
    //   158	5	4	localObject2	Object
    //   15	6	5	j	int
    //   31	99	6	l	long
    //   88	3	8	bool3	boolean
    //   99	28	9	localObject3	Object
    // Exception table:
    //   from	to	target	type
    //   2	5	158	finally
    //   20	26	158	finally
    //   36	41	158	finally
    //   48	53	158	finally
    //   55	60	158	finally
    //   67	73	158	finally
    //   73	79	158	finally
    //   79	84	158	finally
    //   85	88	158	finally
    //   95	99	158	finally
    //   101	106	158	finally
    //   113	117	158	finally
    //   119	124	158	finally
    //   129	136	158	finally
    //   136	139	158	finally
    //   147	150	158	finally
  }
}


/* Location:              /Volumes/D1/codebase/android/POC/assets/product/maind/classes-enjarify.jar!/com/vvt/temporalcontrol/normal/NormalTaskScheduler$TaskScheduledReceiver.class
 * Java compiler version: 5 (49.0)
 * JD-Core Version:       0.7.1
 */