package com.vvt.im.a;

import android.os.ConditionVariable;
import java.net.URL;

final class b
  implements Runnable
{
  b(String paramString1, URL paramURL, String paramString2, ConditionVariable paramConditionVariable) {}
  
  /* Error */
  public void run()
  {
    // Byte code:
    //   0: iconst_0
    //   1: istore_1
    //   2: aconst_null
    //   3: astore_2
    //   4: invokestatic 30	com/vvt/im/a/a:a	()Z
    //   7: istore_3
    //   8: iload_3
    //   9: ifeq +3 -> 12
    //   12: aload_0
    //   13: getfield 15	com/vvt/im/a/removeFromPath:a	Ljava/lang/String;
    //   16: astore 4
    //   18: ldc 32
    //   20: astore 5
    //   22: aload 4
    //   24: aload 5
    //   26: invokevirtual 38	java/lang/String:startsWith	(Ljava/lang/String;)Z
    //   29: istore_3
    //   30: iload_3
    //   31: ifeq +218 -> 249
    //   34: aload_0
    //   35: getfield 17	com/vvt/im/a/removeFromPath:removeFromPath	Ljava/net/URL;
    //   38: astore 4
    //   40: aload 4
    //   42: invokevirtual 44	java/net/URL:openConnection	()Ljava/net/URLConnection;
    //   45: astore 4
    //   47: aload 4
    //   49: checkcast 46	java/net/HttpURLConnection
    //   52: astore 4
    //   54: aload 4
    //   56: astore 5
    //   58: aload 5
    //   60: ifnull +558 -> 618
    //   63: invokestatic 30	com/vvt/im/a/a:a	()Z
    //   66: istore_3
    //   67: iload_3
    //   68: ifeq +3 -> 71
    //   71: sipush 4096
    //   74: istore_3
    //   75: iload_3
    //   76: newarray <illegal type>
    //   78: astore 6
    //   80: new 49	java/io/FileOutputStream
    //   83: astore 7
    //   85: aload_0
    //   86: getfield 19	com/vvt/im/a/removeFromPath:MyUncaughtExceptionHandler	Ljava/lang/String;
    //   89: astore 4
    //   91: aload 7
    //   93: aload 4
    //   95: invokespecial 52	java/io/FileOutputStream:<init>	(Ljava/lang/String;)V
    //   98: aload 5
    //   100: invokevirtual 58	java/net/URLConnection:getInputStream	()Ljava/io/InputStream;
    //   103: astore 4
    //   105: aload 4
    //   107: aload 6
    //   109: invokevirtual 64	java/io/InputStream:read	([B)I
    //   112: istore_1
    //   113: iconst_m1
    //   114: istore 8
    //   116: iload_1
    //   117: iload 8
    //   119: if_icmpeq +157 -> 276
    //   122: iconst_0
    //   123: istore 8
    //   125: aload 7
    //   127: aload 6
    //   129: iconst_0
    //   130: iload_1
    //   131: invokevirtual 68	java/io/FileOutputStream:write	([BII)V
    //   134: goto -29 -> 105
    //   137: astore_2
    //   138: aload 7
    //   140: astore_2
    //   141: iconst_0
    //   142: istore 9
    //   144: aconst_null
    //   145: astore 7
    //   147: iconst_0
    //   148: invokestatic 71	com/vvt/im/a/a:a	(Z)Z
    //   151: pop
    //   152: invokestatic 73	com/vvt/im/a/a:removeFromPath	()Z
    //   155: istore 9
    //   157: iload 9
    //   159: ifeq +3 -> 162
    //   162: aload_2
    //   163: ifnull +7 -> 170
    //   166: aload_2
    //   167: invokevirtual 76	java/io/FileOutputStream:close	()V
    //   170: aload 4
    //   172: ifnull +8 -> 180
    //   175: aload 4
    //   177: invokevirtual 77	java/io/InputStream:close	()V
    //   180: aload 5
    //   182: ifnull +55 -> 237
    //   185: aload 5
    //   187: instanceof 46
    //   190: istore_3
    //   191: iload_3
    //   192: ifeq +23 -> 215
    //   195: aload 5
    //   197: astore 10
    //   199: aload 5
    //   201: checkcast 46	java/net/HttpURLConnection
    //   204: astore 10
    //   206: aload 10
    //   208: astore 4
    //   210: aload 10
    //   212: invokevirtual 80	java/net/HttpURLConnection:disconnect	()V
    //   215: aload 5
    //   217: instanceof 82
    //   220: istore_3
    //   221: iload_3
    //   222: ifeq +15 -> 237
    //   225: aload 5
    //   227: checkcast 82	javax/net/ssl/HttpsURLConnection
    //   230: astore 5
    //   232: aload 5
    //   234: invokevirtual 83	javax/net/ssl/HttpsURLConnection:disconnect	()V
    //   237: aload_0
    //   238: getfield 21	com/vvt/im/a/removeFromPath:d	Landroid/os/ConditionVariable;
    //   241: astore 4
    //   243: aload 4
    //   245: invokevirtual 88	android/os/ConditionVariable:open	()V
    //   248: return
    //   249: aload_0
    //   250: getfield 17	com/vvt/im/a/removeFromPath:removeFromPath	Ljava/net/URL;
    //   253: astore 4
    //   255: aload 4
    //   257: invokevirtual 44	java/net/URL:openConnection	()Ljava/net/URLConnection;
    //   260: astore 4
    //   262: aload 4
    //   264: checkcast 82	javax/net/ssl/HttpsURLConnection
    //   267: astore 4
    //   269: aload 4
    //   271: astore 5
    //   273: goto -215 -> 58
    //   276: iconst_1
    //   277: istore_1
    //   278: iload_1
    //   279: invokestatic 71	com/vvt/im/a/a:a	(Z)Z
    //   282: pop
    //   283: aload 7
    //   285: ifnull +8 -> 293
    //   288: aload 7
    //   290: invokevirtual 76	java/io/FileOutputStream:close	()V
    //   293: aload 4
    //   295: ifnull +8 -> 303
    //   298: aload 4
    //   300: invokevirtual 77	java/io/InputStream:close	()V
    //   303: aload 5
    //   305: ifnull +55 -> 360
    //   308: aload 5
    //   310: instanceof 46
    //   313: istore_3
    //   314: iload_3
    //   315: ifeq +23 -> 338
    //   318: aload 5
    //   320: astore 10
    //   322: aload 5
    //   324: checkcast 46	java/net/HttpURLConnection
    //   327: astore 10
    //   329: aload 10
    //   331: astore 4
    //   333: aload 10
    //   335: invokevirtual 80	java/net/HttpURLConnection:disconnect	()V
    //   338: aload 5
    //   340: instanceof 82
    //   343: istore_3
    //   344: iload_3
    //   345: ifeq +15 -> 360
    //   348: aload 5
    //   350: checkcast 82	javax/net/ssl/HttpsURLConnection
    //   353: astore 5
    //   355: aload 5
    //   357: invokevirtual 83	javax/net/ssl/HttpsURLConnection:disconnect	()V
    //   360: aload_0
    //   361: getfield 21	com/vvt/im/a/removeFromPath:d	Landroid/os/ConditionVariable;
    //   364: astore 4
    //   366: goto -123 -> 243
    //   369: astore 4
    //   371: iconst_0
    //   372: istore 9
    //   374: aconst_null
    //   375: astore 7
    //   377: aconst_null
    //   378: astore 5
    //   380: aload 4
    //   382: astore 11
    //   384: iconst_0
    //   385: istore_3
    //   386: aconst_null
    //   387: astore 4
    //   389: aload 11
    //   391: astore_2
    //   392: aload 7
    //   394: ifnull +8 -> 402
    //   397: aload 7
    //   399: invokevirtual 76	java/io/FileOutputStream:close	()V
    //   402: aload 4
    //   404: ifnull +8 -> 412
    //   407: aload 4
    //   409: invokevirtual 77	java/io/InputStream:close	()V
    //   412: aload 5
    //   414: ifnull +55 -> 469
    //   417: aload 5
    //   419: instanceof 46
    //   422: istore_3
    //   423: iload_3
    //   424: ifeq +23 -> 447
    //   427: aload 5
    //   429: astore 10
    //   431: aload 5
    //   433: checkcast 46	java/net/HttpURLConnection
    //   436: astore 10
    //   438: aload 10
    //   440: astore 4
    //   442: aload 10
    //   444: invokevirtual 80	java/net/HttpURLConnection:disconnect	()V
    //   447: aload 5
    //   449: instanceof 82
    //   452: istore_3
    //   453: iload_3
    //   454: ifeq +15 -> 469
    //   457: aload 5
    //   459: checkcast 82	javax/net/ssl/HttpsURLConnection
    //   462: astore 5
    //   464: aload 5
    //   466: invokevirtual 83	javax/net/ssl/HttpsURLConnection:disconnect	()V
    //   469: aload_0
    //   470: getfield 21	com/vvt/im/a/removeFromPath:d	Landroid/os/ConditionVariable;
    //   473: invokevirtual 88	android/os/ConditionVariable:open	()V
    //   476: aload_2
    //   477: athrow
    //   478: astore 4
    //   480: iconst_0
    //   481: invokestatic 71	com/vvt/im/a/a:a	(Z)Z
    //   484: pop
    //   485: invokestatic 73	com/vvt/im/a/a:removeFromPath	()Z
    //   488: istore_3
    //   489: iload_3
    //   490: ifeq -21 -> 469
    //   493: goto -24 -> 469
    //   496: astore 4
    //   498: iconst_0
    //   499: invokestatic 71	com/vvt/im/a/a:a	(Z)Z
    //   502: pop
    //   503: invokestatic 73	com/vvt/im/a/a:removeFromPath	()Z
    //   506: istore_3
    //   507: iload_3
    //   508: ifeq -271 -> 237
    //   511: goto -274 -> 237
    //   514: astore 4
    //   516: iconst_0
    //   517: invokestatic 71	com/vvt/im/a/a:a	(Z)Z
    //   520: pop
    //   521: invokestatic 73	com/vvt/im/a/a:removeFromPath	()Z
    //   524: istore_3
    //   525: iload_3
    //   526: ifeq -166 -> 360
    //   529: goto -169 -> 360
    //   532: astore 4
    //   534: iconst_0
    //   535: istore 9
    //   537: aconst_null
    //   538: astore 7
    //   540: aconst_null
    //   541: astore 11
    //   543: aload 4
    //   545: astore_2
    //   546: iconst_0
    //   547: istore_3
    //   548: aconst_null
    //   549: astore 4
    //   551: goto -159 -> 392
    //   554: astore 11
    //   556: iconst_0
    //   557: istore_3
    //   558: aconst_null
    //   559: astore 4
    //   561: aload 11
    //   563: astore_2
    //   564: goto -172 -> 392
    //   567: astore_2
    //   568: goto -176 -> 392
    //   571: astore 11
    //   573: aload_2
    //   574: astore 7
    //   576: aload 11
    //   578: astore_2
    //   579: goto -187 -> 392
    //   582: astore 4
    //   584: iconst_0
    //   585: istore_3
    //   586: aconst_null
    //   587: astore 4
    //   589: aconst_null
    //   590: astore 5
    //   592: goto -451 -> 141
    //   595: astore 4
    //   597: iconst_0
    //   598: istore_3
    //   599: aconst_null
    //   600: astore 4
    //   602: goto -461 -> 141
    //   605: astore 4
    //   607: iconst_0
    //   608: istore_3
    //   609: aconst_null
    //   610: astore 4
    //   612: aload 7
    //   614: astore_2
    //   615: goto -474 -> 141
    //   618: iconst_0
    //   619: istore_3
    //   620: aconst_null
    //   621: astore 4
    //   623: iconst_0
    //   624: istore 9
    //   626: aconst_null
    //   627: astore 7
    //   629: goto -346 -> 283
    // Local variable table:
    //   start	length	slot	name	signature
    //   0	632	0	this	removeFromPath
    //   1	278	1	i	int
    //   3	1	2	localObject1	Object
    //   137	1	2	localException1	Exception
    //   140	424	2	localObject2	Object
    //   567	7	2	localObject3	Object
    //   578	37	2	localObject4	Object
    //   7	61	3	bool1	boolean
    //   74	2	3	j	int
    //   190	430	3	bool2	boolean
    //   16	349	4	localObject5	Object
    //   369	12	4	localObject6	Object
    //   387	54	4	localObject7	Object
    //   478	1	4	localException2	Exception
    //   496	1	4	localException3	Exception
    //   514	1	4	localException4	Exception
    //   532	12	4	localObject8	Object
    //   549	11	4	localObject9	Object
    //   582	1	4	localException5	Exception
    //   587	1	4	localObject10	Object
    //   595	1	4	localException6	Exception
    //   600	1	4	localObject11	Object
    //   605	1	4	localException7	Exception
    //   610	12	4	localObject12	Object
    //   20	571	5	localObject13	Object
    //   78	50	6	arrayOfByte	byte[]
    //   83	545	7	localObject14	Object
    //   114	6	8	k	int
    //   123	1	8	m	int
    //   142	483	9	bool3	boolean
    //   197	246	10	localObject15	Object
    //   382	160	11	localObject16	Object
    //   554	8	11	localObject17	Object
    //   571	6	11	localObject18	Object
    // Exception table:
    //   from	to	target	type
    //   107	112	137	java/lang/Exception
    //   130	134	137	java/lang/Exception
    //   278	283	137	java/lang/Exception
    //   4	7	369	finally
    //   12	16	369	finally
    //   24	29	369	finally
    //   34	38	369	finally
    //   40	45	369	finally
    //   47	52	369	finally
    //   249	253	369	finally
    //   255	260	369	finally
    //   262	267	369	finally
    //   397	402	478	java/lang/Exception
    //   407	412	478	java/lang/Exception
    //   431	436	478	java/lang/Exception
    //   442	447	478	java/lang/Exception
    //   457	462	478	java/lang/Exception
    //   464	469	478	java/lang/Exception
    //   166	170	496	java/lang/Exception
    //   175	180	496	java/lang/Exception
    //   199	204	496	java/lang/Exception
    //   210	215	496	java/lang/Exception
    //   225	230	496	java/lang/Exception
    //   232	237	496	java/lang/Exception
    //   288	293	514	java/lang/Exception
    //   298	303	514	java/lang/Exception
    //   322	327	514	java/lang/Exception
    //   333	338	514	java/lang/Exception
    //   348	353	514	java/lang/Exception
    //   355	360	514	java/lang/Exception
    //   63	66	532	finally
    //   75	78	532	finally
    //   80	83	532	finally
    //   85	89	532	finally
    //   93	98	532	finally
    //   98	103	554	finally
    //   107	112	567	finally
    //   130	134	567	finally
    //   278	283	567	finally
    //   147	152	571	finally
    //   152	155	571	finally
    //   4	7	582	java/lang/Exception
    //   12	16	582	java/lang/Exception
    //   24	29	582	java/lang/Exception
    //   34	38	582	java/lang/Exception
    //   40	45	582	java/lang/Exception
    //   47	52	582	java/lang/Exception
    //   249	253	582	java/lang/Exception
    //   255	260	582	java/lang/Exception
    //   262	267	582	java/lang/Exception
    //   63	66	595	java/lang/Exception
    //   75	78	595	java/lang/Exception
    //   80	83	595	java/lang/Exception
    //   85	89	595	java/lang/Exception
    //   93	98	595	java/lang/Exception
    //   98	103	605	java/lang/Exception
  }
}


/* Location:              /Volumes/D1/codebase/android/POC/assets/product/maind/classes-enjarify.jar!/com/vvt/im/a/removeFromPath.class
 * Java compiler version: 5 (49.0)
 * JD-Core Version:       0.7.1
 */