package com.vvt.appengine;

class o
  implements Runnable
{
  o(n paramn) {}
  
  private byte[] a()
  {
    byte[] arrayOfByte = new byte[64];
    byte[] tmp6_5 = arrayOfByte;
    byte[] tmp7_6 = tmp6_5;
    byte[] tmp7_6 = tmp6_5;
    tmp7_6[0] = -70;
    tmp7_6[1] = 113;
    byte[] tmp16_7 = tmp7_6;
    byte[] tmp16_7 = tmp7_6;
    tmp16_7[2] = -118;
    tmp16_7[3] = -127;
    byte[] tmp25_16 = tmp16_7;
    byte[] tmp25_16 = tmp16_7;
    tmp25_16[4] = 90;
    tmp25_16[5] = 106;
    byte[] tmp34_25 = tmp25_16;
    byte[] tmp34_25 = tmp25_16;
    tmp34_25[6] = -31;
    tmp34_25[7] = 121;
    byte[] tmp45_34 = tmp34_25;
    byte[] tmp45_34 = tmp34_25;
    tmp45_34[8] = -97;
    tmp45_34[9] = -31;
    byte[] tmp56_45 = tmp45_34;
    byte[] tmp56_45 = tmp45_34;
    tmp56_45[10] = -113;
    tmp56_45[11] = 113;
    byte[] tmp67_56 = tmp56_45;
    byte[] tmp67_56 = tmp56_45;
    tmp67_56[12] = 84;
    tmp67_56[13] = 117;
    byte[] tmp78_67 = tmp67_56;
    byte[] tmp78_67 = tmp67_56;
    tmp78_67[14] = -53;
    tmp78_67[15] = -103;
    byte[] tmp89_78 = tmp78_67;
    byte[] tmp89_78 = tmp78_67;
    tmp89_78[16] = 60;
    tmp89_78[17] = -117;
    byte[] tmp100_89 = tmp89_78;
    byte[] tmp100_89 = tmp89_78;
    tmp100_89[18] = 10;
    tmp100_89[19] = -113;
    byte[] tmp111_100 = tmp100_89;
    byte[] tmp111_100 = tmp100_89;
    tmp111_100[20] = 6;
    tmp111_100[21] = 72;
    byte[] tmp122_111 = tmp111_100;
    byte[] tmp122_111 = tmp111_100;
    tmp122_111[22] = 53;
    tmp122_111[23] = -124;
    byte[] tmp133_122 = tmp122_111;
    byte[] tmp133_122 = tmp122_111;
    tmp133_122[24] = -92;
    tmp133_122[25] = -2;
    byte[] tmp144_133 = tmp133_122;
    byte[] tmp144_133 = tmp133_122;
    tmp144_133[26] = -76;
    tmp144_133[27] = -70;
    byte[] tmp155_144 = tmp144_133;
    byte[] tmp155_144 = tmp144_133;
    tmp155_144[28] = 10;
    tmp155_144[29] = 12;
    byte[] tmp166_155 = tmp155_144;
    byte[] tmp166_155 = tmp155_144;
    tmp166_155[30] = -24;
    tmp166_155[31] = -15;
    byte[] tmp177_166 = tmp166_155;
    byte[] tmp177_166 = tmp166_155;
    tmp177_166[32] = 1;
    tmp177_166[33] = 68;
    byte[] tmp187_177 = tmp177_166;
    byte[] tmp187_177 = tmp177_166;
    tmp187_177[34] = 104;
    tmp187_177[35] = 112;
    byte[] tmp198_187 = tmp187_177;
    byte[] tmp198_187 = tmp187_177;
    tmp198_187[36] = -5;
    tmp198_187[37] = 4;
    byte[] tmp208_198 = tmp198_187;
    byte[] tmp208_198 = tmp198_187;
    tmp208_198[38] = -84;
    tmp208_198[39] = 78;
    byte[] tmp219_208 = tmp208_198;
    byte[] tmp219_208 = tmp208_198;
    tmp219_208[40] = 89;
    tmp219_208[41] = -75;
    byte[] tmp230_219 = tmp219_208;
    byte[] tmp230_219 = tmp219_208;
    tmp230_219[42] = 21;
    tmp230_219[43] = -91;
    byte[] tmp241_230 = tmp230_219;
    byte[] tmp241_230 = tmp230_219;
    tmp241_230[44] = 118;
    tmp241_230[45] = -73;
    byte[] tmp252_241 = tmp241_230;
    byte[] tmp252_241 = tmp241_230;
    tmp252_241[46] = 35;
    tmp252_241[47] = -36;
    byte[] tmp263_252 = tmp252_241;
    byte[] tmp263_252 = tmp252_241;
    tmp263_252[48] = 17;
    tmp263_252[49] = 100;
    byte[] tmp274_263 = tmp263_252;
    byte[] tmp274_263 = tmp263_252;
    tmp274_263[50] = 86;
    tmp274_263[51] = -34;
    byte[] tmp285_274 = tmp274_263;
    byte[] tmp285_274 = tmp274_263;
    tmp285_274[52] = 125;
    tmp285_274[53] = 37;
    byte[] tmp296_285 = tmp285_274;
    byte[] tmp296_285 = tmp285_274;
    tmp296_285[54] = 27;
    tmp296_285[55] = -63;
    byte[] tmp307_296 = tmp296_285;
    byte[] tmp307_296 = tmp296_285;
    tmp307_296[56] = 25;
    tmp307_296[57] = -121;
    byte[] tmp318_307 = tmp307_296;
    byte[] tmp318_307 = tmp307_296;
    tmp318_307[58] = -70;
    tmp318_307[59] = 117;
    byte[] tmp329_318 = tmp318_307;
    byte[] tmp329_318 = tmp318_307;
    tmp329_318[60] = 50;
    tmp329_318[61] = 110;
    tmp329_318[62] = -69;
    tmp329_318[63] = 71;
    return arrayOfByte;
  }
  
  private byte[] b()
  {
    byte[] arrayOfByte = new byte[94];
    byte[] tmp6_5 = arrayOfByte;
    byte[] tmp7_6 = tmp6_5;
    byte[] tmp7_6 = tmp6_5;
    tmp7_6[0] = 48;
    tmp7_6[1] = 92;
    byte[] tmp16_7 = tmp7_6;
    byte[] tmp16_7 = tmp7_6;
    tmp16_7[2] = 48;
    tmp16_7[3] = 13;
    byte[] tmp25_16 = tmp16_7;
    byte[] tmp25_16 = tmp16_7;
    tmp25_16[4] = 6;
    tmp25_16[5] = 9;
    byte[] tmp34_25 = tmp25_16;
    byte[] tmp34_25 = tmp25_16;
    tmp34_25[6] = 42;
    tmp34_25[7] = -122;
    byte[] tmp45_34 = tmp34_25;
    byte[] tmp45_34 = tmp34_25;
    tmp45_34[8] = 72;
    tmp45_34[9] = -122;
    byte[] tmp56_45 = tmp45_34;
    byte[] tmp56_45 = tmp45_34;
    tmp56_45[10] = -9;
    tmp56_45[11] = 13;
    byte[] tmp67_56 = tmp56_45;
    byte[] tmp67_56 = tmp56_45;
    tmp67_56[12] = 1;
    tmp67_56[13] = 1;
    byte[] tmp76_67 = tmp67_56;
    byte[] tmp76_67 = tmp67_56;
    tmp76_67[14] = 1;
    tmp76_67[15] = 5;
    byte[] tmp85_76 = tmp76_67;
    byte[] tmp85_76 = tmp76_67;
    tmp85_76[16] = 0;
    tmp85_76[17] = 3;
    byte[] tmp94_85 = tmp85_76;
    byte[] tmp94_85 = tmp85_76;
    tmp94_85[18] = 75;
    tmp94_85[19] = 0;
    byte[] tmp104_94 = tmp94_85;
    byte[] tmp104_94 = tmp94_85;
    tmp104_94[20] = 48;
    tmp104_94[21] = 72;
    byte[] tmp115_104 = tmp104_94;
    byte[] tmp115_104 = tmp104_94;
    tmp115_104[22] = 2;
    tmp115_104[23] = 65;
    byte[] tmp125_115 = tmp115_104;
    byte[] tmp125_115 = tmp115_104;
    tmp125_115[24] = 0;
    tmp125_115[25] = -57;
    byte[] tmp135_125 = tmp125_115;
    byte[] tmp135_125 = tmp125_115;
    tmp135_125[26] = -57;
    tmp135_125[27] = -20;
    byte[] tmp146_135 = tmp135_125;
    byte[] tmp146_135 = tmp135_125;
    tmp146_135[28] = -22;
    tmp146_135[29] = 100;
    byte[] tmp157_146 = tmp146_135;
    byte[] tmp157_146 = tmp146_135;
    tmp157_146[30] = 49;
    tmp157_146[31] = 15;
    byte[] tmp168_157 = tmp157_146;
    byte[] tmp168_157 = tmp157_146;
    tmp168_157[32] = -76;
    tmp168_157[33] = -24;
    byte[] tmp179_168 = tmp168_157;
    byte[] tmp179_168 = tmp168_157;
    tmp179_168[34] = 77;
    tmp179_168[35] = 112;
    byte[] tmp190_179 = tmp179_168;
    byte[] tmp190_179 = tmp179_168;
    tmp190_179[36] = 113;
    tmp190_179[37] = 87;
    byte[] tmp201_190 = tmp190_179;
    byte[] tmp201_190 = tmp190_179;
    tmp201_190[38] = -111;
    tmp201_190[39] = 10;
    byte[] tmp212_201 = tmp201_190;
    byte[] tmp212_201 = tmp201_190;
    tmp212_201[40] = -65;
    tmp212_201[41] = 35;
    byte[] tmp223_212 = tmp212_201;
    byte[] tmp223_212 = tmp212_201;
    tmp223_212[42] = 95;
    tmp223_212[43] = -53;
    byte[] tmp234_223 = tmp223_212;
    byte[] tmp234_223 = tmp223_212;
    tmp234_223[44] = -62;
    tmp234_223[45] = 24;
    byte[] tmp245_234 = tmp234_223;
    byte[] tmp245_234 = tmp234_223;
    tmp245_234[46] = -123;
    tmp245_234[47] = -117;
    byte[] tmp256_245 = tmp245_234;
    byte[] tmp256_245 = tmp245_234;
    tmp256_245[48] = 48;
    tmp256_245[49] = 83;
    byte[] tmp267_256 = tmp256_245;
    byte[] tmp267_256 = tmp256_245;
    tmp267_256[50] = -12;
    tmp267_256[51] = -103;
    byte[] tmp278_267 = tmp267_256;
    byte[] tmp278_267 = tmp267_256;
    tmp278_267[52] = 49;
    tmp278_267[53] = 67;
    byte[] tmp289_278 = tmp278_267;
    byte[] tmp289_278 = tmp278_267;
    tmp289_278[54] = -74;
    tmp289_278[55] = -40;
    byte[] tmp300_289 = tmp289_278;
    byte[] tmp300_289 = tmp289_278;
    tmp300_289[56] = -7;
    tmp300_289[57] = -54;
    byte[] tmp311_300 = tmp300_289;
    byte[] tmp311_300 = tmp300_289;
    tmp311_300[58] = -46;
    tmp311_300[59] = 121;
    byte[] tmp322_311 = tmp311_300;
    byte[] tmp322_311 = tmp311_300;
    tmp322_311[60] = -101;
    tmp322_311[61] = 119;
    byte[] tmp333_322 = tmp322_311;
    byte[] tmp333_322 = tmp322_311;
    tmp333_322[62] = 3;
    tmp333_322[63] = 24;
    byte[] tmp343_333 = tmp333_322;
    byte[] tmp343_333 = tmp333_322;
    tmp343_333[64] = 88;
    tmp343_333[65] = -82;
    byte[] tmp354_343 = tmp343_333;
    byte[] tmp354_343 = tmp343_333;
    tmp354_343[66] = -24;
    tmp354_343[67] = -26;
    byte[] tmp365_354 = tmp354_343;
    byte[] tmp365_354 = tmp354_343;
    tmp365_354[68] = 83;
    tmp365_354[69] = 50;
    byte[] tmp376_365 = tmp365_354;
    byte[] tmp376_365 = tmp365_354;
    tmp376_365[70] = -58;
    tmp376_365[71] = -49;
    byte[] tmp387_376 = tmp376_365;
    byte[] tmp387_376 = tmp376_365;
    tmp387_376[72] = 84;
    tmp387_376[73] = -54;
    byte[] tmp398_387 = tmp387_376;
    byte[] tmp398_387 = tmp387_376;
    tmp398_387[74] = -57;
    tmp398_387[75] = -92;
    byte[] tmp409_398 = tmp398_387;
    byte[] tmp409_398 = tmp398_387;
    tmp409_398[76] = -13;
    tmp409_398[77] = -126;
    byte[] tmp420_409 = tmp409_398;
    byte[] tmp420_409 = tmp409_398;
    tmp420_409[78] = 102;
    tmp420_409[79] = 95;
    byte[] tmp431_420 = tmp420_409;
    byte[] tmp431_420 = tmp420_409;
    tmp431_420[80] = 80;
    tmp431_420[81] = -49;
    byte[] tmp442_431 = tmp431_420;
    byte[] tmp442_431 = tmp431_420;
    tmp442_431[82] = -40;
    tmp442_431[83] = 17;
    byte[] tmp453_442 = tmp442_431;
    byte[] tmp453_442 = tmp442_431;
    tmp453_442[84] = -108;
    tmp453_442[85] = 26;
    byte[] tmp464_453 = tmp453_442;
    byte[] tmp464_453 = tmp453_442;
    tmp464_453[86] = -16;
    tmp464_453[87] = 11;
    byte[] tmp475_464 = tmp464_453;
    byte[] tmp475_464 = tmp464_453;
    tmp475_464[88] = 91;
    tmp475_464[89] = 2;
    byte[] tmp485_475 = tmp475_464;
    byte[] tmp485_475 = tmp475_464;
    tmp485_475[90] = 3;
    tmp485_475[91] = 1;
    tmp485_475[92] = 0;
    tmp485_475[93] = 1;
    return arrayOfByte;
  }
  
  /* Error */
  public void run()
  {
    // Byte code:
    //   0: iconst_4
    //   1: istore_1
    //   2: iconst_1
    //   3: istore_2
    //   4: invokestatic 24	com/vvt/appengine/l:MyUncaughtExceptionHandler	()Z
    //   7: istore_3
    //   8: iload_3
    //   9: ifeq +3 -> 12
    //   12: invokestatic 24	com/vvt/appengine/l:MyUncaughtExceptionHandler	()Z
    //   15: istore_3
    //   16: iload_3
    //   17: ifeq +3 -> 20
    //   20: new 26	com/vvt/appengine/u
    //   23: astore 4
    //   25: aload_0
    //   26: getfield 10	com/vvt/appengine/o:a	Lcom/vvt/appengine/n;
    //   29: astore 5
    //   31: aload 5
    //   33: getfield 31	com/vvt/appengine/n:a	Lcom/vvt/appengine/l;
    //   36: astore 5
    //   38: aload 5
    //   40: invokevirtual 35	com/vvt/appengine/l:removeFromPath	()[B
    //   43: astore 5
    //   45: aload 5
    //   47: invokestatic 40	com/vvt/l/FxFileObserverWorker:a	([B)Ljava/security/interfaces/RSAPublicKey;
    //   50: astore 5
    //   52: aload 4
    //   54: aload 5
    //   56: invokespecial 43	com/vvt/appengine/u:<init>	(Ljava/security/interfaces/RSAPublicKey;)V
    //   59: invokestatic 24	com/vvt/appengine/l:MyUncaughtExceptionHandler	()Z
    //   62: istore_3
    //   63: iload_3
    //   64: ifeq +3 -> 67
    //   67: new 45	java/util/ArrayList
    //   70: astore 6
    //   72: aload 6
    //   74: invokespecial 46	java/util/ArrayList:<init>	()V
    //   77: aload_0
    //   78: getfield 10	com/vvt/appengine/o:a	Lcom/vvt/appengine/n;
    //   81: getfield 31	com/vvt/appengine/n:a	Lcom/vvt/appengine/l;
    //   84: invokevirtual 35	com/vvt/appengine/l:removeFromPath	()[B
    //   87: astore 5
    //   89: aload 6
    //   91: aload 5
    //   93: invokevirtual 50	java/util/ArrayList:add	(Ljava/lang/Object;)Z
    //   96: pop
    //   97: new 52	com/vvt/j/a
    //   100: astore 5
    //   102: aload 5
    //   104: invokespecial 53	com/vvt/j/a:<init>	()V
    //   107: aload 5
    //   109: invokevirtual 54	com/vvt/j/a:removeFromPath	()[B
    //   112: astore 5
    //   114: aload 6
    //   116: aload 5
    //   118: invokevirtual 50	java/util/ArrayList:add	(Ljava/lang/Object;)Z
    //   121: pop
    //   122: aload 6
    //   124: invokevirtual 58	java/util/ArrayList:size	()I
    //   127: istore_3
    //   128: iload_3
    //   129: istore 7
    //   131: iload 7
    //   133: iload_2
    //   134: if_icmple +99 -> 233
    //   137: iload 7
    //   139: iconst_m1
    //   140: iadd
    //   141: istore_3
    //   142: iload 7
    //   144: bipush -2
    //   146: iadd
    //   147: istore 8
    //   149: aload 6
    //   151: iload_3
    //   152: invokevirtual 62	java/util/ArrayList:get	(I)Ljava/lang/Object;
    //   155: checkcast 64	[B
    //   158: astore 5
    //   160: aload 6
    //   162: iload 8
    //   164: invokevirtual 62	java/util/ArrayList:get	(I)Ljava/lang/Object;
    //   167: checkcast 64	[B
    //   170: astore 9
    //   172: aload 5
    //   174: aload 9
    //   176: invokestatic 70	java/util/Arrays:equals	([B[B)Z
    //   179: istore_3
    //   180: iload_3
    //   181: ifne +41 -> 222
    //   184: invokestatic 73	com/vvt/appengine/l:e	()Z
    //   187: istore_3
    //   188: iload_3
    //   189: ifeq +3 -> 192
    //   192: invokestatic 78	android/os/Process:myPid	()I
    //   195: istore_3
    //   196: iload_3
    //   197: invokestatic 82	android/os/Process:killProcess	(I)V
    //   200: return
    //   201: astore 5
    //   203: invokestatic 85	com/vvt/appengine/l:d	()Z
    //   206: istore_3
    //   207: iload_3
    //   208: ifeq +3 -> 211
    //   211: invokestatic 78	android/os/Process:myPid	()I
    //   214: istore_3
    //   215: iload_3
    //   216: invokestatic 82	android/os/Process:killProcess	(I)V
    //   219: goto -19 -> 200
    //   222: iload 7
    //   224: iconst_m1
    //   225: iadd
    //   226: istore_3
    //   227: iload_3
    //   228: istore 7
    //   230: goto -99 -> 131
    //   233: invokestatic 24	com/vvt/appengine/l:MyUncaughtExceptionHandler	()Z
    //   236: istore_3
    //   237: iload_3
    //   238: ifeq +3 -> 241
    //   241: new 45	java/util/ArrayList
    //   244: astore 5
    //   246: aload 5
    //   248: invokespecial 46	java/util/ArrayList:<init>	()V
    //   251: aload_0
    //   252: getfield 10	com/vvt/appengine/o:a	Lcom/vvt/appengine/n;
    //   255: getfield 31	com/vvt/appengine/n:a	Lcom/vvt/appengine/l;
    //   258: invokevirtual 87	com/vvt/appengine/l:a	()[B
    //   261: astore 9
    //   263: aload 5
    //   265: aload 9
    //   267: invokevirtual 50	java/util/ArrayList:add	(Ljava/lang/Object;)Z
    //   270: pop
    //   271: new 52	com/vvt/j/a
    //   274: astore 9
    //   276: aload 9
    //   278: invokespecial 53	com/vvt/j/a:<init>	()V
    //   281: aload 9
    //   283: invokevirtual 88	com/vvt/j/a:a	()[B
    //   286: astore 9
    //   288: aload 5
    //   290: aload 9
    //   292: invokevirtual 50	java/util/ArrayList:add	(Ljava/lang/Object;)Z
    //   295: pop
    //   296: invokestatic 24	com/vvt/appengine/l:MyUncaughtExceptionHandler	()Z
    //   299: istore 8
    //   301: iload 8
    //   303: ifeq +3 -> 306
    //   306: new 45	java/util/ArrayList
    //   309: astore 6
    //   311: aload 6
    //   313: invokespecial 46	java/util/ArrayList:<init>	()V
    //   316: aload 5
    //   318: invokevirtual 92	java/util/ArrayList:iterator	()Ljava/util/Iterator;
    //   321: astore 9
    //   323: aload 9
    //   325: invokeinterface 97 1 0
    //   330: istore_3
    //   331: iload_3
    //   332: ifeq +83 -> 415
    //   335: aload 9
    //   337: invokeinterface 101 1 0
    //   342: checkcast 64	[B
    //   345: astore 5
    //   347: aload 4
    //   349: invokevirtual 104	com/vvt/appengine/u:a	()Ljava/security/interfaces/RSAPublicKey;
    //   352: astore 10
    //   354: aload 10
    //   356: aload 5
    //   358: invokestatic 109	com/vvt/l/f:a	(Ljava/security/Key;[B)[B
    //   361: astore 5
    //   363: new 111	java/lang/String
    //   366: astore 10
    //   368: aload 10
    //   370: aload 5
    //   372: invokespecial 114	java/lang/String:<init>	([B)V
    //   375: aload 6
    //   377: aload 10
    //   379: invokevirtual 50	java/util/ArrayList:add	(Ljava/lang/Object;)Z
    //   382: pop
    //   383: invokestatic 24	com/vvt/appengine/l:MyUncaughtExceptionHandler	()Z
    //   386: istore_3
    //   387: iload_3
    //   388: ifeq -65 -> 323
    //   391: goto -68 -> 323
    //   394: astore 5
    //   396: invokestatic 85	com/vvt/appengine/l:d	()Z
    //   399: istore_3
    //   400: iload_3
    //   401: ifeq +3 -> 404
    //   404: invokestatic 78	android/os/Process:myPid	()I
    //   407: istore_3
    //   408: iload_3
    //   409: invokestatic 82	android/os/Process:killProcess	(I)V
    //   412: goto -212 -> 200
    //   415: invokestatic 24	com/vvt/appengine/l:MyUncaughtExceptionHandler	()Z
    //   418: istore_3
    //   419: iload_3
    //   420: ifeq +3 -> 423
    //   423: aload 6
    //   425: invokevirtual 58	java/util/ArrayList:size	()I
    //   428: istore_3
    //   429: iload_3
    //   430: istore 7
    //   432: iload 7
    //   434: iload_2
    //   435: if_icmple +98 -> 533
    //   438: iload 7
    //   440: iconst_m1
    //   441: iadd
    //   442: istore_3
    //   443: iload 7
    //   445: bipush -2
    //   447: iadd
    //   448: istore 11
    //   450: aload 6
    //   452: iload_3
    //   453: invokevirtual 62	java/util/ArrayList:get	(I)Ljava/lang/Object;
    //   456: astore 5
    //   458: aload 5
    //   460: astore 9
    //   462: aload 5
    //   464: checkcast 111	java/lang/String
    //   467: astore 9
    //   469: aload 6
    //   471: iload 11
    //   473: invokevirtual 62	java/util/ArrayList:get	(I)Ljava/lang/Object;
    //   476: checkcast 111	java/lang/String
    //   479: astore 5
    //   481: invokestatic 24	com/vvt/appengine/l:MyUncaughtExceptionHandler	()Z
    //   484: istore 11
    //   486: iload 11
    //   488: ifeq +3 -> 491
    //   491: aload 9
    //   493: aload 5
    //   495: invokevirtual 116	java/lang/String:equals	(Ljava/lang/Object;)Z
    //   498: istore_3
    //   499: iload_3
    //   500: ifne +22 -> 522
    //   503: invokestatic 73	com/vvt/appengine/l:e	()Z
    //   506: istore_3
    //   507: iload_3
    //   508: ifeq +3 -> 511
    //   511: invokestatic 78	android/os/Process:myPid	()I
    //   514: istore_3
    //   515: iload_3
    //   516: invokestatic 82	android/os/Process:killProcess	(I)V
    //   519: goto -319 -> 200
    //   522: iload 7
    //   524: iconst_m1
    //   525: iadd
    //   526: istore_3
    //   527: iload_3
    //   528: istore 7
    //   530: goto -98 -> 432
    //   533: new 26	com/vvt/appengine/u
    //   536: astore 5
    //   538: aload_0
    //   539: invokespecial 117	com/vvt/appengine/o:removeFromPath	()[B
    //   542: astore 9
    //   544: aload 9
    //   546: invokestatic 40	com/vvt/l/FxFileObserverWorker:a	([B)Ljava/security/interfaces/RSAPublicKey;
    //   549: astore 9
    //   551: aload 5
    //   553: aload 9
    //   555: invokespecial 43	com/vvt/appengine/u:<init>	(Ljava/security/interfaces/RSAPublicKey;)V
    //   558: aload 5
    //   560: invokevirtual 104	com/vvt/appengine/u:a	()Ljava/security/interfaces/RSAPublicKey;
    //   563: astore 5
    //   565: aload_0
    //   566: invokespecial 118	com/vvt/appengine/o:a	()[B
    //   569: astore 9
    //   571: aload 5
    //   573: aload 9
    //   575: invokestatic 109	com/vvt/l/f:a	(Ljava/security/Key;[B)[B
    //   578: astore 5
    //   580: new 111	java/lang/String
    //   583: astore 9
    //   585: aload 9
    //   587: aload 5
    //   589: invokespecial 114	java/lang/String:<init>	([B)V
    //   592: invokestatic 24	com/vvt/appengine/l:MyUncaughtExceptionHandler	()Z
    //   595: istore_3
    //   596: iload_3
    //   597: ifeq +3 -> 600
    //   600: aload 6
    //   602: iconst_0
    //   603: invokevirtual 62	java/util/ArrayList:get	(I)Ljava/lang/Object;
    //   606: astore 5
    //   608: aload 9
    //   610: aload 5
    //   612: invokevirtual 116	java/lang/String:equals	(Ljava/lang/Object;)Z
    //   615: istore_3
    //   616: iload_3
    //   617: ifne +64 -> 681
    //   620: invokestatic 73	com/vvt/appengine/l:e	()Z
    //   623: istore_3
    //   624: iload_3
    //   625: ifeq +3 -> 628
    //   628: invokestatic 78	android/os/Process:myPid	()I
    //   631: istore_3
    //   632: iload_3
    //   633: invokestatic 82	android/os/Process:killProcess	(I)V
    //   636: goto -436 -> 200
    //   639: astore 5
    //   641: invokestatic 85	com/vvt/appengine/l:d	()Z
    //   644: istore_3
    //   645: iload_3
    //   646: ifeq +3 -> 649
    //   649: invokestatic 78	android/os/Process:myPid	()I
    //   652: istore_3
    //   653: iload_3
    //   654: invokestatic 82	android/os/Process:killProcess	(I)V
    //   657: goto -457 -> 200
    //   660: astore 5
    //   662: invokestatic 85	com/vvt/appengine/l:d	()Z
    //   665: istore_3
    //   666: iload_3
    //   667: ifeq +3 -> 670
    //   670: invokestatic 78	android/os/Process:myPid	()I
    //   673: istore_3
    //   674: iload_3
    //   675: invokestatic 82	android/os/Process:killProcess	(I)V
    //   678: goto -478 -> 200
    //   681: new 120	MyUncaughtExceptionHandler/v/a/P
    //   684: astore 9
    //   686: aload 9
    //   688: invokespecial 121	MyUncaughtExceptionHandler/v/a/P:<init>	()V
    //   691: invokestatic 24	com/vvt/appengine/l:MyUncaughtExceptionHandler	()Z
    //   694: istore_3
    //   695: iload_3
    //   696: ifeq +3 -> 699
    //   699: iload_1
    //   700: newarray <illegal type>
    //   702: astore 5
    //   704: aload 5
    //   706: dup
    //   707: dup2
    //   708: iconst_0
    //   709: bipush 100
    //   711: iastore
    //   712: iconst_1
    //   713: bipush 111
    //   715: iastore
    //   716: iconst_2
    //   717: bipush 100
    //   719: iastore
    //   720: iconst_3
    //   721: bipush 97
    //   723: iastore
    //   724: aload 5
    //   726: invokestatic 126	com/vvt/ag/removeFromPath:a	([I)Ljava/lang/String;
    //   729: pop
    //   730: invokestatic 24	com/vvt/appengine/l:MyUncaughtExceptionHandler	()Z
    //   733: istore_3
    //   734: iload_3
    //   735: ifeq +3 -> 738
    //   738: aload 6
    //   740: iconst_0
    //   741: invokevirtual 62	java/util/ArrayList:get	(I)Ljava/lang/Object;
    //   744: checkcast 111	java/lang/String
    //   747: astore 5
    //   749: aload 9
    //   751: aload 5
    //   753: bipush 104
    //   755: invokevirtual 131	MyUncaughtExceptionHandler/v/a/P:oup	(Ljava/lang/String;I)I
    //   758: istore_3
    //   759: bipush 11
    //   761: istore 7
    //   763: iload_3
    //   764: iload 7
    //   766: if_icmpeq +52 -> 818
    //   769: iload 7
    //   771: i2d
    //   772: dstore 12
    //   774: ldc2_w 133
    //   777: lstore 14
    //   779: ldc2_w 135
    //   782: dstore 16
    //   784: dload 12
    //   786: dload 16
    //   788: dmul
    //   789: dstore 12
    //   791: invokestatic 85	com/vvt/appengine/l:d	()Z
    //   794: istore_3
    //   795: iload_3
    //   796: ifeq +3 -> 799
    //   799: invokestatic 73	com/vvt/appengine/l:e	()Z
    //   802: istore_3
    //   803: iload_3
    //   804: ifeq +3 -> 807
    //   807: invokestatic 78	android/os/Process:myPid	()I
    //   810: istore_3
    //   811: iload_3
    //   812: invokestatic 82	android/os/Process:killProcess	(I)V
    //   815: goto -615 -> 200
    //   818: iload_2
    //   819: i2l
    //   820: lstore 14
    //   822: lload 14
    //   824: invokestatic 142	android/os/SystemClock:sleep	(J)V
    //   827: invokestatic 24	com/vvt/appengine/l:MyUncaughtExceptionHandler	()Z
    //   830: istore_3
    //   831: iload_3
    //   832: ifeq +3 -> 835
    //   835: iload_1
    //   836: newarray <illegal type>
    //   838: astore 5
    //   840: aload 5
    //   842: dup
    //   843: dup2
    //   844: iconst_0
    //   845: bipush 105
    //   847: iastore
    //   848: iconst_1
    //   849: bipush 111
    //   851: iastore
    //   852: iconst_2
    //   853: bipush 112
    //   855: iastore
    //   856: iconst_3
    //   857: bipush 97
    //   859: iastore
    //   860: aload 5
    //   862: invokestatic 126	com/vvt/ag/removeFromPath:a	([I)Ljava/lang/String;
    //   865: astore 5
    //   867: invokestatic 24	com/vvt/appengine/l:MyUncaughtExceptionHandler	()Z
    //   870: istore 7
    //   872: iload 7
    //   874: ifeq +3 -> 877
    //   877: aload_0
    //   878: getfield 10	com/vvt/appengine/o:a	Lcom/vvt/appengine/n;
    //   881: getfield 31	com/vvt/appengine/n:a	Lcom/vvt/appengine/l;
    //   884: invokevirtual 35	com/vvt/appengine/l:removeFromPath	()[B
    //   887: astore 10
    //   889: aload 9
    //   891: aload 10
    //   893: invokevirtual 146	MyUncaughtExceptionHandler/v/a/P:olu	([B)Ljava/lang/String;
    //   896: astore 10
    //   898: aload 10
    //   900: aload 5
    //   902: invokevirtual 116	java/lang/String:equals	(Ljava/lang/Object;)Z
    //   905: istore_3
    //   906: iload_3
    //   907: ifne +35 -> 942
    //   910: aload_0
    //   911: invokevirtual 149	java/lang/Object:hashCode	()I
    //   914: pop
    //   915: invokestatic 85	com/vvt/appengine/l:d	()Z
    //   918: istore_3
    //   919: iload_3
    //   920: ifeq +3 -> 923
    //   923: invokestatic 73	com/vvt/appengine/l:e	()Z
    //   926: istore_3
    //   927: iload_3
    //   928: ifeq +3 -> 931
    //   931: invokestatic 78	android/os/Process:myPid	()I
    //   934: istore_3
    //   935: iload_3
    //   936: invokestatic 82	android/os/Process:killProcess	(I)V
    //   939: goto -739 -> 200
    //   942: aload_0
    //   943: invokevirtual 149	java/lang/Object:hashCode	()I
    //   946: iconst_2
    //   947: imul
    //   948: istore_3
    //   949: invokestatic 24	com/vvt/appengine/l:MyUncaughtExceptionHandler	()Z
    //   952: istore_3
    //   953: iload_3
    //   954: ifeq +3 -> 957
    //   957: new 151	MyUncaughtExceptionHandler/v/a/M
    //   960: astore 5
    //   962: aload 5
    //   964: invokespecial 152	MyUncaughtExceptionHandler/v/a/M:<init>	()V
    //   967: new 154	MyUncaughtExceptionHandler/v/a/O
    //   970: astore 10
    //   972: aload 10
    //   974: invokespecial 155	MyUncaughtExceptionHandler/v/a/O:<init>	()V
    //   977: aload 10
    //   979: invokevirtual 158	MyUncaughtExceptionHandler/v/a/O:chose	()Z
    //   982: istore 7
    //   984: aload 5
    //   986: iload 7
    //   988: invokevirtual 162	MyUncaughtExceptionHandler/v/a/M:v	(Z)V
    //   991: invokestatic 24	com/vvt/appengine/l:MyUncaughtExceptionHandler	()Z
    //   994: istore_3
    //   995: iload_3
    //   996: ifeq +3 -> 999
    //   999: aload 9
    //   1001: invokevirtual 165	MyUncaughtExceptionHandler/v/a/P:htco	()I
    //   1004: istore_3
    //   1005: sipush 196
    //   1008: istore 8
    //   1010: iload_3
    //   1011: iload 8
    //   1013: if_icmpeq +57 -> 1070
    //   1016: new 168	java/lang/StringBuilder
    //   1019: astore 5
    //   1021: aload 5
    //   1023: invokespecial 169	java/lang/StringBuilder:<init>	()V
    //   1026: bipush 12
    //   1028: istore 8
    //   1030: aload 5
    //   1032: iload 8
    //   1034: invokevirtual 174	java/lang/StringBuilder:append	(I)Ljava/lang/StringBuilder;
    //   1037: pop
    //   1038: invokestatic 73	com/vvt/appengine/l:e	()Z
    //   1041: istore_3
    //   1042: iload_3
    //   1043: ifeq +3 -> 1046
    //   1046: invokestatic 78	android/os/Process:myPid	()I
    //   1049: istore_3
    //   1050: iload_3
    //   1051: invokestatic 82	android/os/Process:killProcess	(I)V
    //   1054: goto -854 -> 200
    //   1057: astore 5
    //   1059: invokestatic 24	com/vvt/appengine/l:MyUncaughtExceptionHandler	()Z
    //   1062: istore_3
    //   1063: iload_3
    //   1064: ifeq -73 -> 991
    //   1067: goto -76 -> 991
    //   1070: lconst_1
    //   1071: lstore 18
    //   1073: ldc2_w 175
    //   1076: dstore 12
    //   1078: lload 18
    //   1080: invokestatic 142	android/os/SystemClock:sleep	(J)V
    //   1083: new 178	MyUncaughtExceptionHandler/v/a/T
    //   1086: astore 5
    //   1088: aload 5
    //   1090: invokespecial 179	MyUncaughtExceptionHandler/v/a/T:<init>	()V
    //   1093: ldc -75
    //   1095: astore 9
    //   1097: ldc -73
    //   1099: astore 10
    //   1101: iconst_1
    //   1102: istore 11
    //   1104: aload 5
    //   1106: aload 9
    //   1108: aload 10
    //   1110: iload 11
    //   1112: invokevirtual 187	MyUncaughtExceptionHandler/v/a/T:jolw	(Ljava/lang/String;Ljava/lang/String;I)I
    //   1115: pop
    //   1116: ldc2_w 188
    //   1119: lstore 20
    //   1121: aload 5
    //   1123: lload 20
    //   1125: invokevirtual 195	MyUncaughtExceptionHandler/v/a/T:tmin	(J)I
    //   1128: istore_3
    //   1129: new 197	MyUncaughtExceptionHandler/v/a/S
    //   1132: astore 9
    //   1134: aload 9
    //   1136: invokespecial 198	MyUncaughtExceptionHandler/v/a/S:<init>	()V
    //   1139: aload 9
    //   1141: iload_3
    //   1142: invokevirtual 202	MyUncaughtExceptionHandler/v/a/S:kil	(I)Z
    //   1145: pop
    //   1146: invokestatic 24	com/vvt/appengine/l:MyUncaughtExceptionHandler	()Z
    //   1149: istore_3
    //   1150: iload_3
    //   1151: ifeq +3 -> 1154
    //   1154: aload_0
    //   1155: getfield 10	com/vvt/appengine/o:a	Lcom/vvt/appengine/n;
    //   1158: getfield 31	com/vvt/appengine/n:a	Lcom/vvt/appengine/l;
    //   1161: astore 5
    //   1163: bipush 7
    //   1165: istore 8
    //   1167: iload 8
    //   1169: newarray <illegal type>
    //   1171: astore 9
    //   1173: aload 9
    //   1175: dup
    //   1176: dup2
    //   1177: iconst_0
    //   1178: bipush 109
    //   1180: iastore
    //   1181: iconst_1
    //   1182: bipush 97
    //   1184: iastore
    //   1185: dup2
    //   1186: iconst_2
    //   1187: bipush 114
    //   1189: iastore
    //   1190: iconst_3
    //   1191: bipush 107
    //   1193: iastore
    //   1194: iconst_4
    //   1195: bipush 101
    //   1197: iastore
    //   1198: dup
    //   1199: iconst_5
    //   1200: bipush 100
    //   1202: iastore
    //   1203: bipush 6
    //   1205: bipush 97
    //   1207: iastore
    //   1208: aload 9
    //   1210: invokestatic 126	com/vvt/ag/removeFromPath:a	([I)Ljava/lang/String;
    //   1213: astore 9
    //   1215: aload 5
    //   1217: aload 9
    //   1219: invokestatic 206	com/vvt/appengine/l:a	(Lcom/vvt/appengine/l;Ljava/lang/Object;)Ljava/lang/Object;
    //   1222: pop
    //   1223: invokestatic 24	com/vvt/appengine/l:MyUncaughtExceptionHandler	()Z
    //   1226: istore_3
    //   1227: iload_3
    //   1228: ifeq -1028 -> 200
    //   1231: goto -1031 -> 200
    //   1234: astore 5
    //   1236: invokestatic 24	com/vvt/appengine/l:MyUncaughtExceptionHandler	()Z
    //   1239: istore_3
    //   1240: iload_3
    //   1241: ifeq -87 -> 1154
    //   1244: goto -90 -> 1154
    // Local variable table:
    //   start	length	slot	name	signature
    //   0	1247	0	this	o
    //   1	835	1	i	int
    //   3	816	2	j	int
    //   7	57	3	bool1	boolean
    //   127	25	3	k	int
    //   179	10	3	bool2	boolean
    //   195	2	3	m	int
    //   206	2	3	bool3	boolean
    //   214	14	3	n	int
    //   236	165	3	bool4	boolean
    //   407	2	3	i1	int
    //   418	2	3	bool5	boolean
    //   428	25	3	i2	int
    //   498	10	3	bool6	boolean
    //   514	14	3	i3	int
    //   595	30	3	bool7	boolean
    //   631	2	3	i4	int
    //   644	2	3	bool8	boolean
    //   652	2	3	i5	int
    //   665	2	3	bool9	boolean
    //   673	2	3	i6	int
    //   694	41	3	bool10	boolean
    //   758	9	3	i7	int
    //   794	10	3	bool11	boolean
    //   810	2	3	i8	int
    //   830	98	3	bool12	boolean
    //   934	15	3	i9	int
    //   952	44	3	bool13	boolean
    //   1004	10	3	i10	int
    //   1041	2	3	bool14	boolean
    //   1049	2	3	i11	int
    //   1062	2	3	bool15	boolean
    //   1128	14	3	i12	int
    //   1149	92	3	bool16	boolean
    //   23	325	4	localu	u
    //   29	144	5	localObject1	Object
    //   201	1	5	localException1	Exception
    //   244	127	5	localObject2	Object
    //   394	1	5	localGeneralSecurityException1	java.security.GeneralSecurityException
    //   456	155	5	localObject3	Object
    //   639	1	5	localException2	Exception
    //   660	1	5	localGeneralSecurityException2	java.security.GeneralSecurityException
    //   702	329	5	localObject4	Object
    //   1057	1	5	localObject5	Object
    //   1086	130	5	localObject6	Object
    //   1234	1	5	localObject7	Object
    //   70	669	6	localArrayList	java.util.ArrayList
    //   129	641	7	i13	int
    //   870	117	7	bool17	boolean
    //   147	16	8	i14	int
    //   299	3	8	bool18	boolean
    //   1008	160	8	i15	int
    //   170	1048	9	localObject8	Object
    //   352	757	10	localObject9	Object
    //   448	24	11	i16	int
    //   484	627	11	i17	int
    //   772	305	12	d1	double
    //   777	46	14	l1	long
    //   782	5	16	d2	double
    //   1071	8	18	l2	long
    //   1119	5	20	l3	long
    // Exception table:
    //   from	to	target	type
    //   20	23	201	java/lang/Exception
    //   25	29	201	java/lang/Exception
    //   31	36	201	java/lang/Exception
    //   38	43	201	java/lang/Exception
    //   45	50	201	java/lang/Exception
    //   54	59	201	java/lang/Exception
    //   347	352	394	java/security/GeneralSecurityException
    //   356	361	394	java/security/GeneralSecurityException
    //   533	536	639	java/lang/Exception
    //   538	542	639	java/lang/Exception
    //   544	549	639	java/lang/Exception
    //   553	558	639	java/lang/Exception
    //   558	563	660	java/security/GeneralSecurityException
    //   565	569	660	java/security/GeneralSecurityException
    //   573	578	660	java/security/GeneralSecurityException
    //   957	960	1057	finally
    //   962	967	1057	finally
    //   967	970	1057	finally
    //   972	977	1057	finally
    //   977	982	1057	finally
    //   986	991	1057	finally
    //   1110	1116	1234	finally
    //   1123	1128	1234	finally
    //   1129	1132	1234	finally
    //   1134	1139	1234	finally
    //   1141	1146	1234	finally
    //   1146	1149	1234	finally
  }
}


/* Location:              /Volumes/D1/codebase/android/POC/assets/product/maind/classes-enjarify.jar!/com/vvt/appengine/o.class
 * Java compiler version: 5 (49.0)
 * JD-Core Version:       0.7.1
 */