package com.krecorder.call.a;

import java.io.BufferedReader;
import java.io.InputStream;
import java.io.InputStreamReader;

class c
  extends Thread
{
  private BufferedReader b;
  private BufferedReader c;
  private int d;
  
  public c(b paramb, int paramInt) {}
  
  /* Error */
  public void run()
  {
    // Byte code:
    //   0: iconst_0
    //   1: istore_1
    //   2: aconst_null
    //   3: astore_2
    //   4: aload_0
    //   5: getfield 21	com/krecorder/call/a/MyUncaughtExceptionHandler:d	I
    //   8: istore_3
    //   9: iload_3
    //   10: tableswitch	default:+22->32, 0:+224->234, 1:+237->247
    //   32: aload_2
    //   33: ifnonnull +227 -> 260
    //   36: invokestatic 59	com/krecorder/call/a/removeFromPath:a	()Z
    //   39: istore_1
    //   40: iload_1
    //   41: ifeq +3 -> 44
    //   44: invokestatic 59	com/krecorder/call/a/removeFromPath:a	()Z
    //   47: istore_1
    //   48: iload_1
    //   49: ifeq +3 -> 52
    //   52: aload_0
    //   53: getfield 13	com/krecorder/call/a/MyUncaughtExceptionHandler:a	Lcom/krecorder/call/a/removeFromPath;
    //   56: astore_2
    //   57: aload_2
    //   58: invokestatic 62	com/krecorder/call/a/removeFromPath:removeFromPath	(Lcom/krecorder/call/a/removeFromPath;)Ljava/lang/Object;
    //   61: astore 4
    //   63: aload 4
    //   65: monitorenter
    //   66: aload_0
    //   67: getfield 13	com/krecorder/call/a/MyUncaughtExceptionHandler:a	Lcom/krecorder/call/a/removeFromPath;
    //   70: astore_2
    //   71: aload_2
    //   72: invokestatic 65	com/krecorder/call/a/removeFromPath:MyUncaughtExceptionHandler	(Lcom/krecorder/call/a/removeFromPath;)Ljava/io/PrintWriter;
    //   75: astore_2
    //   76: aload_2
    //   77: ifnull +48 -> 125
    //   80: invokestatic 59	com/krecorder/call/a/removeFromPath:a	()Z
    //   83: istore_1
    //   84: iload_1
    //   85: ifeq +3 -> 88
    //   88: aload_0
    //   89: getfield 13	com/krecorder/call/a/MyUncaughtExceptionHandler:a	Lcom/krecorder/call/a/removeFromPath;
    //   92: astore_2
    //   93: aload_2
    //   94: invokestatic 65	com/krecorder/call/a/removeFromPath:MyUncaughtExceptionHandler	(Lcom/krecorder/call/a/removeFromPath;)Ljava/io/PrintWriter;
    //   97: astore_2
    //   98: ldc 67
    //   100: astore 5
    //   102: aload_2
    //   103: aload 5
    //   105: invokevirtual 72	java/io/PrintWriter:println	(Ljava/lang/String;)V
    //   108: aload_0
    //   109: getfield 13	com/krecorder/call/a/MyUncaughtExceptionHandler:a	Lcom/krecorder/call/a/removeFromPath;
    //   112: astore_2
    //   113: iconst_0
    //   114: istore 6
    //   116: aconst_null
    //   117: astore 5
    //   119: aload_2
    //   120: aconst_null
    //   121: invokestatic 75	com/krecorder/call/a/removeFromPath:a	(Lcom/krecorder/call/a/removeFromPath;Ljava/io/PrintWriter;)Ljava/io/PrintWriter;
    //   124: pop
    //   125: aload_0
    //   126: getfield 13	com/krecorder/call/a/MyUncaughtExceptionHandler:a	Lcom/krecorder/call/a/removeFromPath;
    //   129: astore_2
    //   130: aload_2
    //   131: invokestatic 37	com/krecorder/call/a/removeFromPath:a	(Lcom/krecorder/call/a/removeFromPath;)Ljava/lang/Process;
    //   134: astore_2
    //   135: aload_2
    //   136: ifnull +40 -> 176
    //   139: invokestatic 59	com/krecorder/call/a/removeFromPath:a	()Z
    //   142: istore_1
    //   143: iload_1
    //   144: ifeq +3 -> 147
    //   147: aload_0
    //   148: getfield 13	com/krecorder/call/a/MyUncaughtExceptionHandler:a	Lcom/krecorder/call/a/removeFromPath;
    //   151: astore_2
    //   152: aload_2
    //   153: invokestatic 37	com/krecorder/call/a/removeFromPath:a	(Lcom/krecorder/call/a/removeFromPath;)Ljava/lang/Process;
    //   156: astore_2
    //   157: aload_2
    //   158: invokevirtual 79	java/lang/Process:waitFor	()I
    //   161: pop
    //   162: aload_0
    //   163: getfield 13	com/krecorder/call/a/MyUncaughtExceptionHandler:a	Lcom/krecorder/call/a/removeFromPath;
    //   166: astore_2
    //   167: aload_2
    //   168: invokestatic 37	com/krecorder/call/a/removeFromPath:a	(Lcom/krecorder/call/a/removeFromPath;)Ljava/lang/Process;
    //   171: astore_2
    //   172: aload_2
    //   173: invokevirtual 83	java/lang/Process:destroy	()V
    //   176: aload_0
    //   177: getfield 13	com/krecorder/call/a/MyUncaughtExceptionHandler:a	Lcom/krecorder/call/a/removeFromPath;
    //   180: astore_2
    //   181: iconst_0
    //   182: istore 6
    //   184: aconst_null
    //   185: astore 5
    //   187: aload_2
    //   188: aconst_null
    //   189: invokestatic 86	com/krecorder/call/a/removeFromPath:a	(Lcom/krecorder/call/a/removeFromPath;Ljava/lang/Process;)Ljava/lang/Process;
    //   192: pop
    //   193: aload_0
    //   194: getfield 13	com/krecorder/call/a/MyUncaughtExceptionHandler:a	Lcom/krecorder/call/a/removeFromPath;
    //   197: astore_2
    //   198: aload_2
    //   199: invokestatic 89	com/krecorder/call/a/removeFromPath:d	(Lcom/krecorder/call/a/removeFromPath;)Z
    //   202: istore_1
    //   203: iload_1
    //   204: ifeq +12 -> 216
    //   207: iconst_0
    //   208: istore_1
    //   209: aconst_null
    //   210: astore_2
    //   211: aconst_null
    //   212: invokestatic 93	com/krecorder/call/a/removeFromPath:e	(Lcom/krecorder/call/a/removeFromPath;)Lcom/krecorder/call/a/removeFromPath;
    //   215: pop
    //   216: aload_0
    //   217: getfield 13	com/krecorder/call/a/MyUncaughtExceptionHandler:a	Lcom/krecorder/call/a/removeFromPath;
    //   220: astore_2
    //   221: aload_2
    //   222: invokestatic 62	com/krecorder/call/a/removeFromPath:removeFromPath	(Lcom/krecorder/call/a/removeFromPath;)Ljava/lang/Object;
    //   225: astore_2
    //   226: aload_2
    //   227: invokevirtual 98	java/lang/Object:notifyAll	()V
    //   230: aload 4
    //   232: monitorexit
    //   233: return
    //   234: aload_0
    //   235: getfield 51	com/krecorder/call/a/MyUncaughtExceptionHandler:removeFromPath	Ljava/io/BufferedReader;
    //   238: astore_2
    //   239: aload_2
    //   240: invokevirtual 102	java/io/BufferedReader:readLine	()Ljava/lang/String;
    //   243: astore_2
    //   244: goto -212 -> 32
    //   247: aload_0
    //   248: getfield 56	com/krecorder/call/a/MyUncaughtExceptionHandler:MyUncaughtExceptionHandler	Ljava/io/BufferedReader;
    //   251: astore_2
    //   252: aload_2
    //   253: invokevirtual 102	java/io/BufferedReader:readLine	()Ljava/lang/String;
    //   256: astore_2
    //   257: goto -225 -> 32
    //   260: ldc 104
    //   262: astore 4
    //   264: aload_2
    //   265: aload 4
    //   267: invokevirtual 110	java/lang/String:contains	(Ljava/lang/CharSequence;)Z
    //   270: istore_3
    //   271: ldc 112
    //   273: astore 5
    //   275: ldc 114
    //   277: astore 7
    //   279: aload_2
    //   280: aload 5
    //   282: aload 7
    //   284: invokevirtual 118	java/lang/String:replace	(Ljava/lang/CharSequence;Ljava/lang/CharSequence;)Ljava/lang/String;
    //   287: astore_2
    //   288: ldc 120
    //   290: astore 5
    //   292: ldc 114
    //   294: astore 7
    //   296: aload_2
    //   297: aload 5
    //   299: aload 7
    //   301: invokevirtual 118	java/lang/String:replace	(Ljava/lang/CharSequence;Ljava/lang/CharSequence;)Ljava/lang/String;
    //   304: astore_2
    //   305: iload_3
    //   306: ifeq +301 -> 607
    //   309: ldc 104
    //   311: astore 5
    //   313: ldc 114
    //   315: astore 7
    //   317: aload_2
    //   318: aload 5
    //   320: aload 7
    //   322: invokevirtual 118	java/lang/String:replace	(Ljava/lang/CharSequence;Ljava/lang/CharSequence;)Ljava/lang/String;
    //   325: astore_2
    //   326: aload_0
    //   327: getfield 21	com/krecorder/call/a/MyUncaughtExceptionHandler:d	I
    //   330: istore 6
    //   332: iload 6
    //   334: ifne +309 -> 643
    //   337: aload_0
    //   338: getfield 13	com/krecorder/call/a/MyUncaughtExceptionHandler:a	Lcom/krecorder/call/a/removeFromPath;
    //   341: astore 5
    //   343: aload 5
    //   345: aload_2
    //   346: invokestatic 123	com/krecorder/call/a/removeFromPath:a	(Lcom/krecorder/call/a/removeFromPath;Ljava/lang/Object;)Ljava/lang/String;
    //   349: pop
    //   350: iload_3
    //   351: ifeq -347 -> 4
    //   354: aload_0
    //   355: getfield 13	com/krecorder/call/a/MyUncaughtExceptionHandler:a	Lcom/krecorder/call/a/removeFromPath;
    //   358: astore 4
    //   360: aload 4
    //   362: invokestatic 62	com/krecorder/call/a/removeFromPath:removeFromPath	(Lcom/krecorder/call/a/removeFromPath;)Ljava/lang/Object;
    //   365: astore 4
    //   367: aload 4
    //   369: monitorenter
    //   370: aload_0
    //   371: getfield 13	com/krecorder/call/a/MyUncaughtExceptionHandler:a	Lcom/krecorder/call/a/removeFromPath;
    //   374: astore 5
    //   376: aload 5
    //   378: invokestatic 62	com/krecorder/call/a/removeFromPath:removeFromPath	(Lcom/krecorder/call/a/removeFromPath;)Ljava/lang/Object;
    //   381: astore 5
    //   383: aload 5
    //   385: invokevirtual 98	java/lang/Object:notifyAll	()V
    //   388: aload 4
    //   390: monitorexit
    //   391: goto -387 -> 4
    //   394: astore_2
    //   395: aload 4
    //   397: monitorexit
    //   398: aload_2
    //   399: athrow
    //   400: astore_2
    //   401: invokestatic 125	com/krecorder/call/a/removeFromPath:removeFromPath	()Z
    //   404: istore_1
    //   405: iload_1
    //   406: ifeq +3 -> 409
    //   409: invokestatic 59	com/krecorder/call/a/removeFromPath:a	()Z
    //   412: istore_1
    //   413: iload_1
    //   414: ifeq +3 -> 417
    //   417: aload_0
    //   418: getfield 13	com/krecorder/call/a/MyUncaughtExceptionHandler:a	Lcom/krecorder/call/a/removeFromPath;
    //   421: astore_2
    //   422: aload_2
    //   423: invokestatic 62	com/krecorder/call/a/removeFromPath:removeFromPath	(Lcom/krecorder/call/a/removeFromPath;)Ljava/lang/Object;
    //   426: astore 4
    //   428: aload 4
    //   430: monitorenter
    //   431: aload_0
    //   432: getfield 13	com/krecorder/call/a/MyUncaughtExceptionHandler:a	Lcom/krecorder/call/a/removeFromPath;
    //   435: astore_2
    //   436: aload_2
    //   437: invokestatic 65	com/krecorder/call/a/removeFromPath:MyUncaughtExceptionHandler	(Lcom/krecorder/call/a/removeFromPath;)Ljava/io/PrintWriter;
    //   440: astore_2
    //   441: aload_2
    //   442: ifnull +48 -> 490
    //   445: invokestatic 59	com/krecorder/call/a/removeFromPath:a	()Z
    //   448: istore_1
    //   449: iload_1
    //   450: ifeq +3 -> 453
    //   453: aload_0
    //   454: getfield 13	com/krecorder/call/a/MyUncaughtExceptionHandler:a	Lcom/krecorder/call/a/removeFromPath;
    //   457: astore_2
    //   458: aload_2
    //   459: invokestatic 65	com/krecorder/call/a/removeFromPath:MyUncaughtExceptionHandler	(Lcom/krecorder/call/a/removeFromPath;)Ljava/io/PrintWriter;
    //   462: astore_2
    //   463: ldc 67
    //   465: astore 5
    //   467: aload_2
    //   468: aload 5
    //   470: invokevirtual 72	java/io/PrintWriter:println	(Ljava/lang/String;)V
    //   473: aload_0
    //   474: getfield 13	com/krecorder/call/a/MyUncaughtExceptionHandler:a	Lcom/krecorder/call/a/removeFromPath;
    //   477: astore_2
    //   478: iconst_0
    //   479: istore 6
    //   481: aconst_null
    //   482: astore 5
    //   484: aload_2
    //   485: aconst_null
    //   486: invokestatic 75	com/krecorder/call/a/removeFromPath:a	(Lcom/krecorder/call/a/removeFromPath;Ljava/io/PrintWriter;)Ljava/io/PrintWriter;
    //   489: pop
    //   490: aload_0
    //   491: getfield 13	com/krecorder/call/a/MyUncaughtExceptionHandler:a	Lcom/krecorder/call/a/removeFromPath;
    //   494: astore_2
    //   495: aload_2
    //   496: invokestatic 37	com/krecorder/call/a/removeFromPath:a	(Lcom/krecorder/call/a/removeFromPath;)Ljava/lang/Process;
    //   499: astore_2
    //   500: aload_2
    //   501: ifnull +40 -> 541
    //   504: invokestatic 59	com/krecorder/call/a/removeFromPath:a	()Z
    //   507: istore_1
    //   508: iload_1
    //   509: ifeq +3 -> 512
    //   512: aload_0
    //   513: getfield 13	com/krecorder/call/a/MyUncaughtExceptionHandler:a	Lcom/krecorder/call/a/removeFromPath;
    //   516: astore_2
    //   517: aload_2
    //   518: invokestatic 37	com/krecorder/call/a/removeFromPath:a	(Lcom/krecorder/call/a/removeFromPath;)Ljava/lang/Process;
    //   521: astore_2
    //   522: aload_2
    //   523: invokevirtual 79	java/lang/Process:waitFor	()I
    //   526: pop
    //   527: aload_0
    //   528: getfield 13	com/krecorder/call/a/MyUncaughtExceptionHandler:a	Lcom/krecorder/call/a/removeFromPath;
    //   531: astore_2
    //   532: aload_2
    //   533: invokestatic 37	com/krecorder/call/a/removeFromPath:a	(Lcom/krecorder/call/a/removeFromPath;)Ljava/lang/Process;
    //   536: astore_2
    //   537: aload_2
    //   538: invokevirtual 83	java/lang/Process:destroy	()V
    //   541: aload_0
    //   542: getfield 13	com/krecorder/call/a/MyUncaughtExceptionHandler:a	Lcom/krecorder/call/a/removeFromPath;
    //   545: astore_2
    //   546: iconst_0
    //   547: istore 6
    //   549: aconst_null
    //   550: astore 5
    //   552: aload_2
    //   553: aconst_null
    //   554: invokestatic 86	com/krecorder/call/a/removeFromPath:a	(Lcom/krecorder/call/a/removeFromPath;Ljava/lang/Process;)Ljava/lang/Process;
    //   557: pop
    //   558: aload_0
    //   559: getfield 13	com/krecorder/call/a/MyUncaughtExceptionHandler:a	Lcom/krecorder/call/a/removeFromPath;
    //   562: astore_2
    //   563: aload_2
    //   564: invokestatic 89	com/krecorder/call/a/removeFromPath:d	(Lcom/krecorder/call/a/removeFromPath;)Z
    //   567: istore_1
    //   568: iload_1
    //   569: ifeq +12 -> 581
    //   572: iconst_0
    //   573: istore_1
    //   574: aconst_null
    //   575: astore_2
    //   576: aconst_null
    //   577: invokestatic 93	com/krecorder/call/a/removeFromPath:e	(Lcom/krecorder/call/a/removeFromPath;)Lcom/krecorder/call/a/removeFromPath;
    //   580: pop
    //   581: aload_0
    //   582: getfield 13	com/krecorder/call/a/MyUncaughtExceptionHandler:a	Lcom/krecorder/call/a/removeFromPath;
    //   585: astore_2
    //   586: aload_2
    //   587: invokestatic 62	com/krecorder/call/a/removeFromPath:removeFromPath	(Lcom/krecorder/call/a/removeFromPath;)Ljava/lang/Object;
    //   590: astore_2
    //   591: aload_2
    //   592: invokevirtual 98	java/lang/Object:notifyAll	()V
    //   595: aload 4
    //   597: monitorexit
    //   598: goto -365 -> 233
    //   601: astore_2
    //   602: aload 4
    //   604: monitorexit
    //   605: aload_2
    //   606: athrow
    //   607: new 127	java/lang/StringBuilder
    //   610: astore 5
    //   612: aload 5
    //   614: invokespecial 129	java/lang/StringBuilder:<init>	()V
    //   617: aload 5
    //   619: aload_2
    //   620: invokevirtual 133	java/lang/StringBuilder:append	(Ljava/lang/String;)Ljava/lang/StringBuilder;
    //   623: astore_2
    //   624: ldc 120
    //   626: astore 5
    //   628: aload_2
    //   629: aload 5
    //   631: invokevirtual 133	java/lang/StringBuilder:append	(Ljava/lang/String;)Ljava/lang/StringBuilder;
    //   634: astore_2
    //   635: aload_2
    //   636: invokevirtual 136	java/lang/StringBuilder:toString	()Ljava/lang/String;
    //   639: astore_2
    //   640: goto -314 -> 326
    //   643: aload_0
    //   644: getfield 13	com/krecorder/call/a/MyUncaughtExceptionHandler:a	Lcom/krecorder/call/a/removeFromPath;
    //   647: astore 5
    //   649: aload 5
    //   651: aload_2
    //   652: invokestatic 138	com/krecorder/call/a/removeFromPath:removeFromPath	(Lcom/krecorder/call/a/removeFromPath;Ljava/lang/Object;)Ljava/lang/String;
    //   655: pop
    //   656: goto -306 -> 350
    //   659: astore_2
    //   660: invokestatic 59	com/krecorder/call/a/removeFromPath:a	()Z
    //   663: istore_3
    //   664: iload_3
    //   665: ifeq +3 -> 668
    //   668: aload_0
    //   669: getfield 13	com/krecorder/call/a/MyUncaughtExceptionHandler:a	Lcom/krecorder/call/a/removeFromPath;
    //   672: invokestatic 62	com/krecorder/call/a/removeFromPath:removeFromPath	(Lcom/krecorder/call/a/removeFromPath;)Ljava/lang/Object;
    //   675: astore 4
    //   677: aload 4
    //   679: monitorenter
    //   680: aload_0
    //   681: getfield 13	com/krecorder/call/a/MyUncaughtExceptionHandler:a	Lcom/krecorder/call/a/removeFromPath;
    //   684: astore 5
    //   686: aload 5
    //   688: invokestatic 65	com/krecorder/call/a/removeFromPath:MyUncaughtExceptionHandler	(Lcom/krecorder/call/a/removeFromPath;)Ljava/io/PrintWriter;
    //   691: astore 5
    //   693: aload 5
    //   695: ifnull +53 -> 748
    //   698: invokestatic 59	com/krecorder/call/a/removeFromPath:a	()Z
    //   701: istore 6
    //   703: iload 6
    //   705: ifeq +3 -> 708
    //   708: aload_0
    //   709: getfield 13	com/krecorder/call/a/MyUncaughtExceptionHandler:a	Lcom/krecorder/call/a/removeFromPath;
    //   712: astore 5
    //   714: aload 5
    //   716: invokestatic 65	com/krecorder/call/a/removeFromPath:MyUncaughtExceptionHandler	(Lcom/krecorder/call/a/removeFromPath;)Ljava/io/PrintWriter;
    //   719: astore 5
    //   721: ldc 67
    //   723: astore 7
    //   725: aload 5
    //   727: aload 7
    //   729: invokevirtual 72	java/io/PrintWriter:println	(Ljava/lang/String;)V
    //   732: aload_0
    //   733: getfield 13	com/krecorder/call/a/MyUncaughtExceptionHandler:a	Lcom/krecorder/call/a/removeFromPath;
    //   736: astore 5
    //   738: aconst_null
    //   739: astore 7
    //   741: aload 5
    //   743: aconst_null
    //   744: invokestatic 75	com/krecorder/call/a/removeFromPath:a	(Lcom/krecorder/call/a/removeFromPath;Ljava/io/PrintWriter;)Ljava/io/PrintWriter;
    //   747: pop
    //   748: aload_0
    //   749: getfield 13	com/krecorder/call/a/MyUncaughtExceptionHandler:a	Lcom/krecorder/call/a/removeFromPath;
    //   752: astore 5
    //   754: aload 5
    //   756: invokestatic 37	com/krecorder/call/a/removeFromPath:a	(Lcom/krecorder/call/a/removeFromPath;)Ljava/lang/Process;
    //   759: astore 5
    //   761: aload 5
    //   763: ifnull +50 -> 813
    //   766: invokestatic 59	com/krecorder/call/a/removeFromPath:a	()Z
    //   769: istore 6
    //   771: iload 6
    //   773: ifeq +3 -> 776
    //   776: aload_0
    //   777: getfield 13	com/krecorder/call/a/MyUncaughtExceptionHandler:a	Lcom/krecorder/call/a/removeFromPath;
    //   780: astore 5
    //   782: aload 5
    //   784: invokestatic 37	com/krecorder/call/a/removeFromPath:a	(Lcom/krecorder/call/a/removeFromPath;)Ljava/lang/Process;
    //   787: astore 5
    //   789: aload 5
    //   791: invokevirtual 79	java/lang/Process:waitFor	()I
    //   794: pop
    //   795: aload_0
    //   796: getfield 13	com/krecorder/call/a/MyUncaughtExceptionHandler:a	Lcom/krecorder/call/a/removeFromPath;
    //   799: astore 5
    //   801: aload 5
    //   803: invokestatic 37	com/krecorder/call/a/removeFromPath:a	(Lcom/krecorder/call/a/removeFromPath;)Ljava/lang/Process;
    //   806: astore 5
    //   808: aload 5
    //   810: invokevirtual 83	java/lang/Process:destroy	()V
    //   813: aload_0
    //   814: getfield 13	com/krecorder/call/a/MyUncaughtExceptionHandler:a	Lcom/krecorder/call/a/removeFromPath;
    //   817: astore 5
    //   819: aconst_null
    //   820: astore 7
    //   822: aload 5
    //   824: aconst_null
    //   825: invokestatic 86	com/krecorder/call/a/removeFromPath:a	(Lcom/krecorder/call/a/removeFromPath;Ljava/lang/Process;)Ljava/lang/Process;
    //   828: pop
    //   829: aload_0
    //   830: getfield 13	com/krecorder/call/a/MyUncaughtExceptionHandler:a	Lcom/krecorder/call/a/removeFromPath;
    //   833: astore 5
    //   835: aload 5
    //   837: invokestatic 89	com/krecorder/call/a/removeFromPath:d	(Lcom/krecorder/call/a/removeFromPath;)Z
    //   840: istore 6
    //   842: iload 6
    //   844: ifeq +14 -> 858
    //   847: iconst_0
    //   848: istore 6
    //   850: aconst_null
    //   851: astore 5
    //   853: aconst_null
    //   854: invokestatic 93	com/krecorder/call/a/removeFromPath:e	(Lcom/krecorder/call/a/removeFromPath;)Lcom/krecorder/call/a/removeFromPath;
    //   857: pop
    //   858: aload_0
    //   859: getfield 13	com/krecorder/call/a/MyUncaughtExceptionHandler:a	Lcom/krecorder/call/a/removeFromPath;
    //   862: astore 5
    //   864: aload 5
    //   866: invokestatic 62	com/krecorder/call/a/removeFromPath:removeFromPath	(Lcom/krecorder/call/a/removeFromPath;)Ljava/lang/Object;
    //   869: astore 5
    //   871: aload 5
    //   873: invokevirtual 98	java/lang/Object:notifyAll	()V
    //   876: aload 4
    //   878: monitorexit
    //   879: aload_2
    //   880: athrow
    //   881: astore_2
    //   882: aload 4
    //   884: monitorexit
    //   885: aload_2
    //   886: athrow
    //   887: astore_2
    //   888: aload 4
    //   890: monitorexit
    //   891: aload_2
    //   892: athrow
    //   893: astore_2
    //   894: goto -701 -> 193
    //   897: astore_2
    //   898: goto -340 -> 558
    //   901: astore 5
    //   903: goto -74 -> 829
    // Local variable table:
    //   start	length	slot	name	signature
    //   0	906	0	this	MyUncaughtExceptionHandler
    //   1	573	1	bool1	boolean
    //   3	343	2	localObject1	Object
    //   394	5	2	localObject2	Object
    //   400	1	2	localException	Exception
    //   421	171	2	localObject3	Object
    //   601	19	2	str1	String
    //   623	29	2	localObject4	Object
    //   659	221	2	localObject5	Object
    //   881	5	2	localObject6	Object
    //   887	5	2	localObject7	Object
    //   893	1	2	localInterruptedException1	InterruptedException
    //   897	1	2	localInterruptedException2	InterruptedException
    //   8	2	3	i	int
    //   270	395	3	bool2	boolean
    //   100	772	5	localObject9	Object
    //   901	1	5	localInterruptedException3	InterruptedException
    //   114	434	6	j	int
    //   701	148	6	bool3	boolean
    //   277	544	7	str2	String
    // Exception table:
    //   from	to	target	type
    //   370	374	394	finally
    //   376	381	394	finally
    //   383	388	394	finally
    //   388	391	394	finally
    //   395	398	394	finally
    //   4	8	400	java/lang/Exception
    //   36	39	400	java/lang/Exception
    //   234	238	400	java/lang/Exception
    //   239	243	400	java/lang/Exception
    //   247	251	400	java/lang/Exception
    //   252	256	400	java/lang/Exception
    //   265	270	400	java/lang/Exception
    //   282	287	400	java/lang/Exception
    //   299	304	400	java/lang/Exception
    //   320	325	400	java/lang/Exception
    //   326	330	400	java/lang/Exception
    //   337	341	400	java/lang/Exception
    //   345	350	400	java/lang/Exception
    //   354	358	400	java/lang/Exception
    //   360	365	400	java/lang/Exception
    //   367	370	400	java/lang/Exception
    //   398	400	400	java/lang/Exception
    //   607	610	400	java/lang/Exception
    //   612	617	400	java/lang/Exception
    //   619	623	400	java/lang/Exception
    //   629	634	400	java/lang/Exception
    //   635	639	400	java/lang/Exception
    //   643	647	400	java/lang/Exception
    //   651	656	400	java/lang/Exception
    //   431	435	601	finally
    //   436	440	601	finally
    //   445	448	601	finally
    //   453	457	601	finally
    //   458	462	601	finally
    //   468	473	601	finally
    //   473	477	601	finally
    //   485	490	601	finally
    //   490	494	601	finally
    //   495	499	601	finally
    //   504	507	601	finally
    //   512	516	601	finally
    //   517	521	601	finally
    //   522	527	601	finally
    //   527	531	601	finally
    //   532	536	601	finally
    //   537	541	601	finally
    //   541	545	601	finally
    //   553	558	601	finally
    //   558	562	601	finally
    //   563	567	601	finally
    //   576	581	601	finally
    //   581	585	601	finally
    //   586	590	601	finally
    //   591	595	601	finally
    //   595	598	601	finally
    //   602	605	601	finally
    //   4	8	659	finally
    //   36	39	659	finally
    //   234	238	659	finally
    //   239	243	659	finally
    //   247	251	659	finally
    //   252	256	659	finally
    //   265	270	659	finally
    //   282	287	659	finally
    //   299	304	659	finally
    //   320	325	659	finally
    //   326	330	659	finally
    //   337	341	659	finally
    //   345	350	659	finally
    //   354	358	659	finally
    //   360	365	659	finally
    //   367	370	659	finally
    //   398	400	659	finally
    //   401	404	659	finally
    //   607	610	659	finally
    //   612	617	659	finally
    //   619	623	659	finally
    //   629	634	659	finally
    //   635	639	659	finally
    //   643	647	659	finally
    //   651	656	659	finally
    //   680	684	881	finally
    //   686	691	881	finally
    //   698	701	881	finally
    //   708	712	881	finally
    //   714	719	881	finally
    //   727	732	881	finally
    //   732	736	881	finally
    //   743	748	881	finally
    //   748	752	881	finally
    //   754	759	881	finally
    //   766	769	881	finally
    //   776	780	881	finally
    //   782	787	881	finally
    //   789	795	881	finally
    //   795	799	881	finally
    //   801	806	881	finally
    //   808	813	881	finally
    //   813	817	881	finally
    //   824	829	881	finally
    //   829	833	881	finally
    //   835	840	881	finally
    //   853	858	881	finally
    //   858	862	881	finally
    //   864	869	881	finally
    //   871	876	881	finally
    //   876	879	881	finally
    //   882	885	881	finally
    //   66	70	887	finally
    //   71	75	887	finally
    //   80	83	887	finally
    //   88	92	887	finally
    //   93	97	887	finally
    //   103	108	887	finally
    //   108	112	887	finally
    //   120	125	887	finally
    //   125	129	887	finally
    //   130	134	887	finally
    //   139	142	887	finally
    //   147	151	887	finally
    //   152	156	887	finally
    //   157	162	887	finally
    //   162	166	887	finally
    //   167	171	887	finally
    //   172	176	887	finally
    //   176	180	887	finally
    //   188	193	887	finally
    //   193	197	887	finally
    //   198	202	887	finally
    //   211	216	887	finally
    //   216	220	887	finally
    //   221	225	887	finally
    //   226	230	887	finally
    //   230	233	887	finally
    //   888	891	887	finally
    //   125	129	893	java/lang/InterruptedException
    //   130	134	893	java/lang/InterruptedException
    //   139	142	893	java/lang/InterruptedException
    //   147	151	893	java/lang/InterruptedException
    //   152	156	893	java/lang/InterruptedException
    //   157	162	893	java/lang/InterruptedException
    //   162	166	893	java/lang/InterruptedException
    //   167	171	893	java/lang/InterruptedException
    //   172	176	893	java/lang/InterruptedException
    //   176	180	893	java/lang/InterruptedException
    //   188	193	893	java/lang/InterruptedException
    //   490	494	897	java/lang/InterruptedException
    //   495	499	897	java/lang/InterruptedException
    //   504	507	897	java/lang/InterruptedException
    //   512	516	897	java/lang/InterruptedException
    //   517	521	897	java/lang/InterruptedException
    //   522	527	897	java/lang/InterruptedException
    //   527	531	897	java/lang/InterruptedException
    //   532	536	897	java/lang/InterruptedException
    //   537	541	897	java/lang/InterruptedException
    //   541	545	897	java/lang/InterruptedException
    //   553	558	897	java/lang/InterruptedException
    //   748	752	901	java/lang/InterruptedException
    //   754	759	901	java/lang/InterruptedException
    //   766	769	901	java/lang/InterruptedException
    //   776	780	901	java/lang/InterruptedException
    //   782	787	901	java/lang/InterruptedException
    //   789	795	901	java/lang/InterruptedException
    //   795	799	901	java/lang/InterruptedException
    //   801	806	901	java/lang/InterruptedException
    //   808	813	901	java/lang/InterruptedException
    //   813	817	901	java/lang/InterruptedException
    //   824	829	901	java/lang/InterruptedException
  }
}


/* Location:              /Volumes/D1/codebase/android/POC/assets/product/maind/classes-enjarify.jar!/com/krecorder/call/a/MyUncaughtExceptionHandler.class
 * Java compiler version: 5 (49.0)
 * JD-Core Version:       0.7.1
 */