package org.eclipse.paho.client.mqttv3.a.a;

import java.util.Hashtable;
import java.util.Iterator;
import java.util.Properties;
import java.util.Set;
import java.util.Vector;
import javax.net.ssl.SSLContext;
import javax.net.ssl.SSLSocketFactory;

public class a
{
  private static final String[] a;
  private static final byte[] d;
  private Hashtable b;
  private Properties c;
  private org.eclipse.paho.client.mqttv3.b.b e = null;
  
  static
  {
    int i = 8;
    Object localObject = new String[14];
    localObject[0] = "com.ibm.ssl.protocol";
    localObject[1] = "com.ibm.ssl.contextProvider";
    localObject[2] = "com.ibm.ssl.keyStore";
    localObject[3] = "com.ibm.ssl.keyStorePassword";
    localObject[4] = "com.ibm.ssl.keyStoreType";
    localObject[5] = "com.ibm.ssl.keyStoreProvider";
    localObject[6] = "com.ibm.ssl.keyManager";
    localObject[7] = "com.ibm.ssl.trustStore";
    localObject[i] = "com.ibm.ssl.trustStorePassword";
    localObject[9] = "com.ibm.ssl.trustStoreType";
    localObject[10] = "com.ibm.ssl.trustStoreProvider";
    localObject[11] = "com.ibm.ssl.trustManager";
    localObject[12] = "com.ibm.ssl.enabledCipherSuites";
    localObject[13] = "com.ibm.ssl.clientAuthentication";
    a = (String[])localObject;
    localObject = new byte[i];
    Object tmp95_94 = localObject;
    Object tmp96_95 = tmp95_94;
    Object tmp96_95 = tmp95_94;
    tmp96_95[0] = -99;
    tmp96_95[1] = -89;
    Object tmp105_96 = tmp96_95;
    Object tmp105_96 = tmp96_95;
    tmp105_96[2] = -39;
    tmp105_96[3] = Byte.MIN_VALUE;
    Object tmp114_105 = tmp105_96;
    Object tmp114_105 = tmp105_96;
    tmp114_105[4] = 5;
    tmp114_105[5] = -72;
    tmp114_105[6] = -119;
    tmp114_105[7] = -100;
    d = (byte[])localObject;
  }
  
  public a()
  {
    Hashtable localHashtable = new java/util/Hashtable;
    localHashtable.<init>();
    this.b = localHashtable;
  }
  
  private String a(String paramString1, String paramString2)
  {
    Properties localProperties = null;
    if (paramString1 != null) {}
    for (Object localObject = (Properties)this.b.get(paramString1);; localObject = null)
    {
      if (localObject != null)
      {
        localObject = ((Properties)localObject).getProperty(paramString2);
        if (localObject == null) {
          break label43;
        }
      }
      for (;;)
      {
        return (String)localObject;
        localObject = null;
        label43:
        localProperties = this.c;
        if (localProperties != null)
        {
          localObject = localProperties.getProperty(paramString2);
          if (localObject == null) {}
        }
      }
    }
  }
  
  private String a(String paramString1, String paramString2, String paramString3)
  {
    String str = a(paramString1, paramString2);
    if (str != null) {}
    for (;;)
    {
      return str;
      if (paramString3 != null) {
        str = System.getProperty(paramString3);
      }
    }
  }
  
  private void a(Properties paramProperties)
  {
    Object localObject1 = paramProperties.keySet();
    Object localObject2 = ((Set)localObject1).iterator();
    boolean bool2;
    do
    {
      boolean bool1 = ((Iterator)localObject2).hasNext();
      if (!bool1) {
        break;
      }
      localObject1 = (String)((Iterator)localObject2).next();
      bool2 = p((String)localObject1);
    } while (bool2);
    localObject2 = new java/lang/IllegalArgumentException;
    StringBuilder localStringBuilder = new java/lang/StringBuilder;
    localStringBuilder.<init>();
    localObject1 = (String)localObject1 + " is not a valid IBM SSL property key.";
    ((IllegalArgumentException)localObject2).<init>((String)localObject1);
    throw ((Throwable)localObject2);
  }
  
  public static byte[] a(char[] paramArrayOfChar)
  {
    int i = 0;
    Object localObject = null;
    if (paramArrayOfChar == null) {
      i = 0;
    }
    byte[] arrayOfByte;
    for (localObject = null;; localObject = arrayOfByte)
    {
      return (byte[])localObject;
      arrayOfByte = new byte[paramArrayOfChar.length * 2];
      int k;
      for (int j = 0;; j = k)
      {
        k = paramArrayOfChar.length;
        if (i >= k) {
          break;
        }
        int m = j + 1;
        k = (byte)(paramArrayOfChar[i] & 0xFF);
        arrayOfByte[j] = k;
        k = m + 1;
        j = i + 1;
        i = (byte)(paramArrayOfChar[i] >> '\b' & 0xFF);
        arrayOfByte[m] = i;
        i = j;
      }
    }
  }
  
  public static char[] a(String paramString)
  {
    int i = 0;
    char[] arrayOfChar = null;
    if (paramString == null) {}
    for (;;)
    {
      return arrayOfChar;
      Object localObject = "{xor}";
      try
      {
        int j = ((String)localObject).length();
        localObject = paramString.substring(j);
        localObject = b.a((String)localObject);
        i = 0;
        arrayOfChar = null;
        for (;;)
        {
          int k = localObject.length;
          if (i >= k) {
            break;
          }
          k = localObject[i];
          byte[] arrayOfByte1 = d;
          byte[] arrayOfByte2 = d;
          int m = arrayOfByte2.length;
          m = i % m;
          int n = arrayOfByte1[m];
          k = (byte)((k ^ n) & 0xFF);
          localObject[i] = k;
          i += 1;
        }
        arrayOfChar = a((byte[])localObject);
      }
      catch (Exception localException) {}
    }
  }
  
  public static char[] a(byte[] paramArrayOfByte)
  {
    int i = 0;
    Object localObject = null;
    if (paramArrayOfByte == null) {
      i = 0;
    }
    char[] arrayOfChar;
    for (localObject = null;; localObject = arrayOfChar)
    {
      return (char[])localObject;
      int j = paramArrayOfByte.length / 2;
      arrayOfChar = new char[j];
      int k = 0;
      for (;;)
      {
        j = paramArrayOfByte.length;
        if (k >= j) {
          break;
        }
        j = i + 1;
        int m = k + 1;
        int n = paramArrayOfByte[k] & 0xFF;
        k = m + 1;
        m = (char)(((paramArrayOfByte[m] & 0xFF) << 8) + n);
        arrayOfChar[i] = m;
        i = j;
      }
    }
  }
  
  public static String b(char[] paramArrayOfChar)
  {
    int i;
    if (paramArrayOfChar == null) {
      i = 0;
    }
    String str;
    for (Object localObject1 = null;; localObject1 = str)
    {
      return (String)localObject1;
      Object localObject2 = a(paramArrayOfChar);
      i = 0;
      localObject1 = null;
      for (;;)
      {
        int j = localObject2.length;
        if (i >= j) {
          break;
        }
        j = localObject2[i];
        byte[] arrayOfByte1 = d;
        byte[] arrayOfByte2 = d;
        int k = arrayOfByte2.length;
        k = i % k;
        int m = arrayOfByte1[k];
        j = (byte)((j ^ m) & 0xFF);
        localObject2[i] = j;
        i += 1;
      }
      localObject1 = new java/lang/StringBuilder;
      ((StringBuilder)localObject1).<init>();
      localObject1 = ((StringBuilder)localObject1).append("{xor}");
      str = new java/lang/String;
      localObject2 = b.a((byte[])localObject2);
      str.<init>((String)localObject2);
    }
  }
  
  private void b(Properties paramProperties)
  {
    String str1 = paramProperties.getProperty("com.ibm.ssl.keyStorePassword");
    String str2;
    boolean bool;
    if (str1 != null)
    {
      str2 = "{xor}";
      bool = str1.startsWith(str2);
      if (!bool)
      {
        str1 = b(str1.toCharArray());
        str2 = "com.ibm.ssl.keyStorePassword";
        paramProperties.put(str2, str1);
      }
    }
    str1 = paramProperties.getProperty("com.ibm.ssl.trustStorePassword");
    if (str1 != null)
    {
      str2 = "{xor}";
      bool = str1.startsWith(str2);
      if (!bool)
      {
        str1 = b(str1.toCharArray());
        str2 = "com.ibm.ssl.trustStorePassword";
        paramProperties.put(str2, str1);
      }
    }
  }
  
  public static String[] b(String paramString)
  {
    int i = 44;
    int j;
    Object localObject;
    if (paramString == null)
    {
      j = 0;
      localObject = null;
    }
    for (;;)
    {
      return (String[])localObject;
      Vector localVector = new java/util/Vector;
      localVector.<init>();
      int k = paramString.indexOf(i);
      j = 0;
      localObject = null;
      for (;;)
      {
        int m = -1;
        if (k <= m) {
          break;
        }
        localObject = paramString.substring(j, k);
        localVector.add(localObject);
        j = k + 1;
        k = paramString.indexOf(i, j);
      }
      localObject = paramString.substring(j);
      localVector.add(localObject);
      j = localVector.size();
      localObject = new String[j];
      localVector.toArray((Object[])localObject);
    }
  }
  
  private boolean p(String paramString)
  {
    boolean bool1 = false;
    int i = 0;
    for (;;)
    {
      Object localObject = a;
      int j = localObject.length;
      if (i < j)
      {
        localObject = a[i];
        boolean bool2 = ((String)localObject).equals(paramString);
        if (!bool2) {}
      }
      else
      {
        localObject = a;
        int k = localObject.length;
        if (i < k) {
          bool1 = true;
        }
        return bool1;
      }
      i += 1;
    }
  }
  
  /* Error */
  private SSLContext q(String paramString)
  {
    // Byte code:
    //   0: aconst_null
    //   1: astore_2
    //   2: iconst_2
    //   3: istore_3
    //   4: iconst_1
    //   5: istore 4
    //   7: iconst_0
    //   8: istore 5
    //   10: aconst_null
    //   11: astore 6
    //   13: aload_0
    //   14: aload_1
    //   15: invokevirtual 206	org/eclipse/paho/client/mqttv3/a/a/a:MyUncaughtExceptionHandler	(Ljava/lang/String;)Ljava/lang/String;
    //   18: astore 7
    //   20: aload 7
    //   22: ifnonnull +7 -> 29
    //   25: ldc -48
    //   27: astore 7
    //   29: aload_0
    //   30: getfield 68	org/eclipse/paho/client/mqttv3/a/a/a:e	Lorg/eclipse/paho/client/mqttv3/removeFromPath/removeFromPath;
    //   33: astore 8
    //   35: aload 8
    //   37: ifnull +62 -> 99
    //   40: aload_0
    //   41: getfield 68	org/eclipse/paho/client/mqttv3/a/a/a:e	Lorg/eclipse/paho/client/mqttv3/removeFromPath/removeFromPath;
    //   44: astore 9
    //   46: ldc -46
    //   48: astore 10
    //   50: ldc -52
    //   52: astore 11
    //   54: ldc -44
    //   56: astore 12
    //   58: iload_3
    //   59: anewarray 4	java/lang/Object
    //   62: astore 13
    //   64: aload_1
    //   65: ifnull +1380 -> 1445
    //   68: aload_1
    //   69: astore 8
    //   71: aload 13
    //   73: iconst_0
    //   74: aload 8
    //   76: aastore
    //   77: aload 13
    //   79: iload 4
    //   81: aload 7
    //   83: aastore
    //   84: aload 9
    //   86: aload 10
    //   88: aload 11
    //   90: aload 12
    //   92: aload 13
    //   94: invokeinterface 217 5 0
    //   99: aload_0
    //   100: aload_1
    //   101: invokevirtual 219	org/eclipse/paho/client/mqttv3/a/a/a:d	(Ljava/lang/String;)Ljava/lang/String;
    //   104: astore 8
    //   106: aload 8
    //   108: ifnonnull +1345 -> 1453
    //   111: aload 7
    //   113: invokestatic 225	javax/net/ssl/SSLContext:getInstance	(Ljava/lang/String;)Ljavax/net/ssl/SSLContext;
    //   116: astore 7
    //   118: aload 7
    //   120: astore 12
    //   122: aload_0
    //   123: getfield 68	org/eclipse/paho/client/mqttv3/a/a/a:e	Lorg/eclipse/paho/client/mqttv3/removeFromPath/removeFromPath;
    //   126: astore 7
    //   128: aload 7
    //   130: ifnull +89 -> 219
    //   133: aload_0
    //   134: getfield 68	org/eclipse/paho/client/mqttv3/a/a/a:e	Lorg/eclipse/paho/client/mqttv3/removeFromPath/removeFromPath;
    //   137: astore 8
    //   139: ldc -46
    //   141: astore 9
    //   143: ldc -52
    //   145: astore 10
    //   147: ldc -29
    //   149: astore 11
    //   151: iconst_2
    //   152: istore 14
    //   154: iload 14
    //   156: anewarray 4	java/lang/Object
    //   159: astore 13
    //   161: iconst_0
    //   162: istore 5
    //   164: aconst_null
    //   165: astore 6
    //   167: aload_1
    //   168: ifnull +1301 -> 1469
    //   171: aload_1
    //   172: astore 7
    //   174: aload 13
    //   176: iconst_0
    //   177: aload 7
    //   179: aastore
    //   180: iconst_1
    //   181: istore 14
    //   183: aload 12
    //   185: invokevirtual 231	javax/net/ssl/SSLContext:getProvider	()Ljava/security/Provider;
    //   188: astore 6
    //   190: aload 6
    //   192: invokevirtual 236	java/security/Provider:getName	()Ljava/lang/String;
    //   195: astore 6
    //   197: aload 13
    //   199: iload 14
    //   201: aload 6
    //   203: aastore
    //   204: aload 8
    //   206: aload 9
    //   208: aload 10
    //   210: aload 11
    //   212: aload 13
    //   214: invokeinterface 217 5 0
    //   219: ldc 26
    //   221: astore 7
    //   223: iconst_0
    //   224: istore 15
    //   226: aconst_null
    //   227: astore 8
    //   229: aload_0
    //   230: aload_1
    //   231: aload 7
    //   233: aconst_null
    //   234: invokespecial 239	org/eclipse/paho/client/mqttv3/a/a/a:a	(Ljava/lang/String;Ljava/lang/String;Ljava/lang/String;)Ljava/lang/String;
    //   237: astore 10
    //   239: iconst_0
    //   240: ifne +1627 -> 1867
    //   243: aload 10
    //   245: ifnonnull +22 -> 267
    //   248: ldc 26
    //   250: astore 7
    //   252: ldc -15
    //   254: astore 8
    //   256: aload_0
    //   257: aload_1
    //   258: aload 7
    //   260: aload 8
    //   262: invokespecial 239	org/eclipse/paho/client/mqttv3/a/a/a:a	(Ljava/lang/String;Ljava/lang/String;Ljava/lang/String;)Ljava/lang/String;
    //   265: astore 10
    //   267: aload_0
    //   268: getfield 68	org/eclipse/paho/client/mqttv3/a/a/a:e	Lorg/eclipse/paho/client/mqttv3/removeFromPath/removeFromPath;
    //   271: astore 7
    //   273: aload 7
    //   275: ifnull +84 -> 359
    //   278: aload_0
    //   279: getfield 68	org/eclipse/paho/client/mqttv3/a/a/a:e	Lorg/eclipse/paho/client/mqttv3/removeFromPath/removeFromPath;
    //   282: astore 8
    //   284: ldc -46
    //   286: astore 9
    //   288: ldc -52
    //   290: astore 11
    //   292: ldc -13
    //   294: astore 13
    //   296: iconst_2
    //   297: istore 14
    //   299: iload 14
    //   301: anewarray 4	java/lang/Object
    //   304: astore 6
    //   306: iconst_0
    //   307: istore 4
    //   309: aconst_null
    //   310: astore 16
    //   312: aload_1
    //   313: ifnull +1164 -> 1477
    //   316: aload_1
    //   317: astore 7
    //   319: aload 6
    //   321: iconst_0
    //   322: aload 7
    //   324: aastore
    //   325: iconst_1
    //   326: istore 4
    //   328: aload 10
    //   330: ifnull +1155 -> 1485
    //   333: aload 10
    //   335: astore 7
    //   337: aload 6
    //   339: iload 4
    //   341: aload 7
    //   343: aastore
    //   344: aload 8
    //   346: aload 9
    //   348: aload 11
    //   350: aload 13
    //   352: aload 6
    //   354: invokeinterface 217 5 0
    //   359: aload_0
    //   360: aload_1
    //   361: invokevirtual 246	org/eclipse/paho/client/mqttv3/a/a/a:e	(Ljava/lang/String;)[C
    //   364: astore 11
    //   366: aload_0
    //   367: getfield 68	org/eclipse/paho/client/mqttv3/a/a/a:e	Lorg/eclipse/paho/client/mqttv3/removeFromPath/removeFromPath;
    //   370: astore 7
    //   372: aload 7
    //   374: ifnull +87 -> 461
    //   377: aload_0
    //   378: getfield 68	org/eclipse/paho/client/mqttv3/a/a/a:e	Lorg/eclipse/paho/client/mqttv3/removeFromPath/removeFromPath;
    //   381: astore 8
    //   383: ldc -46
    //   385: astore 9
    //   387: ldc -52
    //   389: astore 13
    //   391: ldc -8
    //   393: astore 6
    //   395: iconst_2
    //   396: istore 14
    //   398: iload 14
    //   400: anewarray 4	java/lang/Object
    //   403: astore 16
    //   405: iconst_0
    //   406: istore 17
    //   408: aconst_null
    //   409: astore 18
    //   411: aload_1
    //   412: ifnull +1081 -> 1493
    //   415: aload_1
    //   416: astore 7
    //   418: aload 16
    //   420: iconst_0
    //   421: aload 7
    //   423: aastore
    //   424: iconst_1
    //   425: istore 17
    //   427: aload 11
    //   429: ifnull +1072 -> 1501
    //   432: aload 11
    //   434: invokestatic 170	org/eclipse/paho/client/mqttv3/a/a/a:removeFromPath	([C)Ljava/lang/String;
    //   437: astore 7
    //   439: aload 16
    //   441: iload 17
    //   443: aload 7
    //   445: aastore
    //   446: aload 8
    //   448: aload 9
    //   450: aload 13
    //   452: aload 6
    //   454: aload 16
    //   456: invokeinterface 217 5 0
    //   461: aload_0
    //   462: aload_1
    //   463: invokevirtual 251	org/eclipse/paho/client/mqttv3/a/a/a:f	(Ljava/lang/String;)Ljava/lang/String;
    //   466: astore 9
    //   468: aload 9
    //   470: ifnonnull +8 -> 478
    //   473: invokestatic 256	java/security/KeyStore:getDefaultType	()Ljava/lang/String;
    //   476: astore 9
    //   478: aload_0
    //   479: getfield 68	org/eclipse/paho/client/mqttv3/a/a/a:e	Lorg/eclipse/paho/client/mqttv3/removeFromPath/removeFromPath;
    //   482: astore 7
    //   484: aload 7
    //   486: ifnull +85 -> 571
    //   489: aload_0
    //   490: getfield 68	org/eclipse/paho/client/mqttv3/a/a/a:e	Lorg/eclipse/paho/client/mqttv3/removeFromPath/removeFromPath;
    //   493: astore 8
    //   495: ldc -46
    //   497: astore 13
    //   499: ldc -52
    //   501: astore 6
    //   503: ldc_w 258
    //   506: astore 16
    //   508: iconst_2
    //   509: istore 14
    //   511: iload 14
    //   513: anewarray 4	java/lang/Object
    //   516: astore 18
    //   518: iconst_0
    //   519: istore 19
    //   521: aconst_null
    //   522: astore 20
    //   524: aload_1
    //   525: ifnull +984 -> 1509
    //   528: aload_1
    //   529: astore 7
    //   531: aload 18
    //   533: iconst_0
    //   534: aload 7
    //   536: aastore
    //   537: iconst_1
    //   538: istore 19
    //   540: aload 9
    //   542: ifnull +975 -> 1517
    //   545: aload 9
    //   547: astore 7
    //   549: aload 18
    //   551: iload 19
    //   553: aload 7
    //   555: aastore
    //   556: aload 8
    //   558: aload 13
    //   560: aload 6
    //   562: aload 16
    //   564: aload 18
    //   566: invokeinterface 217 5 0
    //   571: invokestatic 263	javax/net/ssl/KeyManagerFactory:getDefaultAlgorithm	()Ljava/lang/String;
    //   574: astore 8
    //   576: aload_0
    //   577: aload_1
    //   578: invokevirtual 266	org/eclipse/paho/client/mqttv3/a/a/a:FxFileObserverWorker	(Ljava/lang/String;)Ljava/lang/String;
    //   581: astore 13
    //   583: aload_0
    //   584: aload_1
    //   585: invokevirtual 269	org/eclipse/paho/client/mqttv3/a/a/a:AppEngine1	(Ljava/lang/String;)Ljava/lang/String;
    //   588: astore 7
    //   590: aload 7
    //   592: ifnull +1281 -> 1873
    //   595: aload 10
    //   597: ifnull +1270 -> 1867
    //   600: aload 9
    //   602: ifnull +1265 -> 1867
    //   605: aload 7
    //   607: ifnull +1260 -> 1867
    //   610: aload 9
    //   612: invokestatic 272	java/security/KeyStore:getInstance	(Ljava/lang/String;)Ljava/security/KeyStore;
    //   615: astore 6
    //   617: new 274	java/io/FileInputStream
    //   620: astore 8
    //   622: aload 8
    //   624: aload 10
    //   626: invokespecial 275	java/io/FileInputStream:<init>	(Ljava/lang/String;)V
    //   629: aload 6
    //   631: aload 8
    //   633: aload 11
    //   635: invokevirtual 279	java/security/KeyStore:load	(Ljava/io/InputStream;[C)V
    //   638: aload 13
    //   640: ifnull +885 -> 1525
    //   643: aload 7
    //   645: aload 13
    //   647: invokestatic 282	javax/net/ssl/KeyManagerFactory:getInstance	(Ljava/lang/String;Ljava/lang/String;)Ljavax/net/ssl/KeyManagerFactory;
    //   650: astore 8
    //   652: aload 8
    //   654: astore 9
    //   656: aload_0
    //   657: getfield 68	org/eclipse/paho/client/mqttv3/a/a/a:e	Lorg/eclipse/paho/client/mqttv3/removeFromPath/removeFromPath;
    //   660: astore 8
    //   662: aload 8
    //   664: ifnull +165 -> 829
    //   667: aload_0
    //   668: getfield 68	org/eclipse/paho/client/mqttv3/a/a/a:e	Lorg/eclipse/paho/client/mqttv3/removeFromPath/removeFromPath;
    //   671: astore 10
    //   673: ldc -46
    //   675: astore 13
    //   677: ldc -52
    //   679: astore 16
    //   681: ldc_w 284
    //   684: astore 18
    //   686: iconst_2
    //   687: istore 15
    //   689: iload 15
    //   691: anewarray 4	java/lang/Object
    //   694: astore 20
    //   696: iconst_0
    //   697: istore 21
    //   699: aload_1
    //   700: ifnull +839 -> 1539
    //   703: aload_1
    //   704: astore 8
    //   706: aload 20
    //   708: iconst_0
    //   709: aload 8
    //   711: aastore
    //   712: iconst_1
    //   713: istore 15
    //   715: aload 7
    //   717: ifnull +830 -> 1547
    //   720: aload 20
    //   722: iload 15
    //   724: aload 7
    //   726: aastore
    //   727: aload 10
    //   729: aload 13
    //   731: aload 16
    //   733: aload 18
    //   735: aload 20
    //   737: invokeinterface 217 5 0
    //   742: aload_0
    //   743: getfield 68	org/eclipse/paho/client/mqttv3/a/a/a:e	Lorg/eclipse/paho/client/mqttv3/removeFromPath/removeFromPath;
    //   746: astore 8
    //   748: ldc -46
    //   750: astore 10
    //   752: ldc -52
    //   754: astore 13
    //   756: ldc_w 286
    //   759: astore 16
    //   761: iconst_2
    //   762: istore 14
    //   764: iload 14
    //   766: anewarray 4	java/lang/Object
    //   769: astore 18
    //   771: iconst_0
    //   772: istore 19
    //   774: aconst_null
    //   775: astore 20
    //   777: aload_1
    //   778: ifnull +777 -> 1555
    //   781: aload_1
    //   782: astore 7
    //   784: aload 18
    //   786: iconst_0
    //   787: aload 7
    //   789: aastore
    //   790: iconst_1
    //   791: istore 14
    //   793: aload 9
    //   795: invokevirtual 287	javax/net/ssl/KeyManagerFactory:getProvider	()Ljava/security/Provider;
    //   798: astore 20
    //   800: aload 20
    //   802: invokevirtual 236	java/security/Provider:getName	()Ljava/lang/String;
    //   805: astore 20
    //   807: aload 18
    //   809: iload 14
    //   811: aload 20
    //   813: aastore
    //   814: aload 8
    //   816: aload 10
    //   818: aload 13
    //   820: aload 16
    //   822: aload 18
    //   824: invokeinterface 217 5 0
    //   829: aload 9
    //   831: aload 6
    //   833: aload 11
    //   835: invokevirtual 291	javax/net/ssl/KeyManagerFactory:init	(Ljava/security/KeyStore;[C)V
    //   838: aload 9
    //   840: invokevirtual 295	javax/net/ssl/KeyManagerFactory:getKeyManagers	()[Ljavax/net/ssl/KeyManager;
    //   843: astore 7
    //   845: aload 7
    //   847: astore 11
    //   849: aload_0
    //   850: aload_1
    //   851: invokevirtual 298	org/eclipse/paho/client/mqttv3/a/a/a:i	(Ljava/lang/String;)Ljava/lang/String;
    //   854: astore 10
    //   856: aload_0
    //   857: getfield 68	org/eclipse/paho/client/mqttv3/a/a/a:e	Lorg/eclipse/paho/client/mqttv3/removeFromPath/removeFromPath;
    //   860: astore 7
    //   862: aload 7
    //   864: ifnull +85 -> 949
    //   867: aload_0
    //   868: getfield 68	org/eclipse/paho/client/mqttv3/a/a/a:e	Lorg/eclipse/paho/client/mqttv3/removeFromPath/removeFromPath;
    //   871: astore 8
    //   873: ldc -46
    //   875: astore 9
    //   877: ldc -52
    //   879: astore 13
    //   881: ldc_w 300
    //   884: astore 6
    //   886: iconst_2
    //   887: istore 14
    //   889: iload 14
    //   891: anewarray 4	java/lang/Object
    //   894: astore 16
    //   896: iconst_0
    //   897: istore 17
    //   899: aconst_null
    //   900: astore 18
    //   902: aload_1
    //   903: ifnull +796 -> 1699
    //   906: aload_1
    //   907: astore 7
    //   909: aload 16
    //   911: iconst_0
    //   912: aload 7
    //   914: aastore
    //   915: iconst_1
    //   916: istore 17
    //   918: aload 10
    //   920: ifnull +787 -> 1707
    //   923: aload 10
    //   925: astore 7
    //   927: aload 16
    //   929: iload 17
    //   931: aload 7
    //   933: aastore
    //   934: aload 8
    //   936: aload 9
    //   938: aload 13
    //   940: aload 6
    //   942: aload 16
    //   944: invokeinterface 217 5 0
    //   949: aload_0
    //   950: aload_1
    //   951: invokevirtual 303	org/eclipse/paho/client/mqttv3/a/a/a:j	(Ljava/lang/String;)[C
    //   954: astore 13
    //   956: aload_0
    //   957: getfield 68	org/eclipse/paho/client/mqttv3/a/a/a:e	Lorg/eclipse/paho/client/mqttv3/removeFromPath/removeFromPath;
    //   960: astore 7
    //   962: aload 7
    //   964: ifnull +88 -> 1052
    //   967: aload_0
    //   968: getfield 68	org/eclipse/paho/client/mqttv3/a/a/a:e	Lorg/eclipse/paho/client/mqttv3/removeFromPath/removeFromPath;
    //   971: astore 8
    //   973: ldc -46
    //   975: astore 9
    //   977: ldc -52
    //   979: astore 6
    //   981: ldc_w 305
    //   984: astore 16
    //   986: iconst_2
    //   987: istore 14
    //   989: iload 14
    //   991: anewarray 4	java/lang/Object
    //   994: astore 18
    //   996: iconst_0
    //   997: istore 19
    //   999: aconst_null
    //   1000: astore 20
    //   1002: aload_1
    //   1003: ifnull +712 -> 1715
    //   1006: aload_1
    //   1007: astore 7
    //   1009: aload 18
    //   1011: iconst_0
    //   1012: aload 7
    //   1014: aastore
    //   1015: iconst_1
    //   1016: istore 19
    //   1018: aload 13
    //   1020: ifnull +703 -> 1723
    //   1023: aload 13
    //   1025: invokestatic 170	org/eclipse/paho/client/mqttv3/a/a/a:removeFromPath	([C)Ljava/lang/String;
    //   1028: astore 7
    //   1030: aload 18
    //   1032: iload 19
    //   1034: aload 7
    //   1036: aastore
    //   1037: aload 8
    //   1039: aload 9
    //   1041: aload 6
    //   1043: aload 16
    //   1045: aload 18
    //   1047: invokeinterface 217 5 0
    //   1052: aload_0
    //   1053: aload_1
    //   1054: invokevirtual 308	org/eclipse/paho/client/mqttv3/a/a/a:k	(Ljava/lang/String;)Ljava/lang/String;
    //   1057: astore 9
    //   1059: aload 9
    //   1061: ifnonnull +8 -> 1069
    //   1064: invokestatic 256	java/security/KeyStore:getDefaultType	()Ljava/lang/String;
    //   1067: astore 9
    //   1069: aload_0
    //   1070: getfield 68	org/eclipse/paho/client/mqttv3/a/a/a:e	Lorg/eclipse/paho/client/mqttv3/removeFromPath/removeFromPath;
    //   1073: astore 7
    //   1075: aload 7
    //   1077: ifnull +82 -> 1159
    //   1080: aload_0
    //   1081: getfield 68	org/eclipse/paho/client/mqttv3/a/a/a:e	Lorg/eclipse/paho/client/mqttv3/removeFromPath/removeFromPath;
    //   1084: astore 8
    //   1086: ldc -46
    //   1088: astore 6
    //   1090: ldc -52
    //   1092: astore 16
    //   1094: ldc_w 310
    //   1097: astore 18
    //   1099: iconst_2
    //   1100: istore 14
    //   1102: iload 14
    //   1104: anewarray 4	java/lang/Object
    //   1107: astore 20
    //   1109: iconst_0
    //   1110: istore 21
    //   1112: aload_1
    //   1113: ifnull +618 -> 1731
    //   1116: aload_1
    //   1117: astore 7
    //   1119: aload 20
    //   1121: iconst_0
    //   1122: aload 7
    //   1124: aastore
    //   1125: iconst_1
    //   1126: istore 21
    //   1128: aload 9
    //   1130: ifnull +609 -> 1739
    //   1133: aload 9
    //   1135: astore 7
    //   1137: aload 20
    //   1139: iload 21
    //   1141: aload 7
    //   1143: aastore
    //   1144: aload 8
    //   1146: aload 6
    //   1148: aload 16
    //   1150: aload 18
    //   1152: aload 20
    //   1154: invokeinterface 217 5 0
    //   1159: invokestatic 313	javax/net/ssl/TrustManagerFactory:getDefaultAlgorithm	()Ljava/lang/String;
    //   1162: astore 8
    //   1164: aload_0
    //   1165: aload_1
    //   1166: invokevirtual 316	org/eclipse/paho/client/mqttv3/a/a/a:l	(Ljava/lang/String;)Ljava/lang/String;
    //   1169: astore 6
    //   1171: aload_0
    //   1172: aload_1
    //   1173: invokevirtual 319	org/eclipse/paho/client/mqttv3/a/a/a:m	(Ljava/lang/String;)Ljava/lang/String;
    //   1176: astore 7
    //   1178: aload 7
    //   1180: ifnull +680 -> 1860
    //   1183: aload 10
    //   1185: ifnull +666 -> 1851
    //   1188: aload 9
    //   1190: ifnull +661 -> 1851
    //   1193: aload 7
    //   1195: ifnull +656 -> 1851
    //   1198: aload 9
    //   1200: invokestatic 272	java/security/KeyStore:getInstance	(Ljava/lang/String;)Ljava/security/KeyStore;
    //   1203: astore 9
    //   1205: new 274	java/io/FileInputStream
    //   1208: astore 8
    //   1210: aload 8
    //   1212: aload 10
    //   1214: invokespecial 275	java/io/FileInputStream:<init>	(Ljava/lang/String;)V
    //   1217: aload 9
    //   1219: aload 8
    //   1221: aload 13
    //   1223: invokevirtual 279	java/security/KeyStore:load	(Ljava/io/InputStream;[C)V
    //   1226: aload 6
    //   1228: ifnull +519 -> 1747
    //   1231: aload 7
    //   1233: aload 6
    //   1235: invokestatic 322	javax/net/ssl/TrustManagerFactory:getInstance	(Ljava/lang/String;Ljava/lang/String;)Ljavax/net/ssl/TrustManagerFactory;
    //   1238: astore 8
    //   1240: aload 8
    //   1242: astore_2
    //   1243: aload_0
    //   1244: getfield 68	org/eclipse/paho/client/mqttv3/a/a/a:e	Lorg/eclipse/paho/client/mqttv3/removeFromPath/removeFromPath;
    //   1247: astore 8
    //   1249: aload 8
    //   1251: ifnull +163 -> 1414
    //   1254: aload_0
    //   1255: getfield 68	org/eclipse/paho/client/mqttv3/a/a/a:e	Lorg/eclipse/paho/client/mqttv3/removeFromPath/removeFromPath;
    //   1258: astore 10
    //   1260: ldc -46
    //   1262: astore 13
    //   1264: ldc -52
    //   1266: astore 6
    //   1268: ldc_w 324
    //   1271: astore 16
    //   1273: iconst_2
    //   1274: istore 15
    //   1276: iload 15
    //   1278: anewarray 4	java/lang/Object
    //   1281: astore 18
    //   1283: iconst_0
    //   1284: istore 19
    //   1286: aconst_null
    //   1287: astore 20
    //   1289: aload_1
    //   1290: ifnull +470 -> 1760
    //   1293: aload_1
    //   1294: astore 8
    //   1296: aload 18
    //   1298: iconst_0
    //   1299: aload 8
    //   1301: aastore
    //   1302: iconst_1
    //   1303: istore 15
    //   1305: aload 7
    //   1307: ifnull +461 -> 1768
    //   1310: aload 18
    //   1312: iload 15
    //   1314: aload 7
    //   1316: aastore
    //   1317: aload 10
    //   1319: aload 13
    //   1321: aload 6
    //   1323: aload 16
    //   1325: aload 18
    //   1327: invokeinterface 217 5 0
    //   1332: aload_0
    //   1333: getfield 68	org/eclipse/paho/client/mqttv3/a/a/a:e	Lorg/eclipse/paho/client/mqttv3/removeFromPath/removeFromPath;
    //   1336: astore 7
    //   1338: ldc -46
    //   1340: astore 8
    //   1342: ldc -52
    //   1344: astore 10
    //   1346: ldc_w 326
    //   1349: astore 13
    //   1351: iconst_2
    //   1352: istore 5
    //   1354: iload 5
    //   1356: anewarray 4	java/lang/Object
    //   1359: astore 6
    //   1361: iconst_0
    //   1362: istore 4
    //   1364: aconst_null
    //   1365: astore 16
    //   1367: aload_1
    //   1368: ifnull +408 -> 1776
    //   1371: aload 6
    //   1373: iconst_0
    //   1374: aload_1
    //   1375: aastore
    //   1376: iconst_1
    //   1377: istore 4
    //   1379: aload_2
    //   1380: invokevirtual 327	javax/net/ssl/TrustManagerFactory:getProvider	()Ljava/security/Provider;
    //   1383: astore 18
    //   1385: aload 18
    //   1387: invokevirtual 236	java/security/Provider:getName	()Ljava/lang/String;
    //   1390: astore 18
    //   1392: aload 6
    //   1394: iload 4
    //   1396: aload 18
    //   1398: aastore
    //   1399: aload 7
    //   1401: aload 8
    //   1403: aload 10
    //   1405: aload 13
    //   1407: aload 6
    //   1409: invokeinterface 217 5 0
    //   1414: aload_2
    //   1415: aload 9
    //   1417: invokevirtual 330	javax/net/ssl/TrustManagerFactory:init	(Ljava/security/KeyStore;)V
    //   1420: aload_2
    //   1421: invokevirtual 334	javax/net/ssl/TrustManagerFactory:getTrustManagers	()[Ljavax/net/ssl/TrustManager;
    //   1424: astore 7
    //   1426: iconst_0
    //   1427: istore 15
    //   1429: aconst_null
    //   1430: astore 8
    //   1432: aload 12
    //   1434: aload 11
    //   1436: aload 7
    //   1438: aconst_null
    //   1439: invokevirtual 337	javax/net/ssl/SSLContext:init	([Ljavax/net/ssl/KeyManager;[Ljavax/net/ssl/TrustManager;Ljava/security/SecureRandom;)V
    //   1442: aload 12
    //   1444: areturn
    //   1445: ldc_w 339
    //   1448: astore 8
    //   1450: goto -1379 -> 71
    //   1453: aload 7
    //   1455: aload 8
    //   1457: invokestatic 342	javax/net/ssl/SSLContext:getInstance	(Ljava/lang/String;Ljava/lang/String;)Ljavax/net/ssl/SSLContext;
    //   1460: astore 7
    //   1462: aload 7
    //   1464: astore 12
    //   1466: goto -1344 -> 122
    //   1469: ldc_w 339
    //   1472: astore 7
    //   1474: goto -1300 -> 174
    //   1477: ldc_w 339
    //   1480: astore 7
    //   1482: goto -1163 -> 319
    //   1485: ldc_w 344
    //   1488: astore 7
    //   1490: goto -1153 -> 337
    //   1493: ldc_w 339
    //   1496: astore 7
    //   1498: goto -1080 -> 418
    //   1501: ldc_w 344
    //   1504: astore 7
    //   1506: goto -1067 -> 439
    //   1509: ldc_w 339
    //   1512: astore 7
    //   1514: goto -983 -> 531
    //   1517: ldc_w 344
    //   1520: astore 7
    //   1522: goto -973 -> 549
    //   1525: aload 7
    //   1527: invokestatic 347	javax/net/ssl/KeyManagerFactory:getInstance	(Ljava/lang/String;)Ljavax/net/ssl/KeyManagerFactory;
    //   1530: astore 8
    //   1532: aload 8
    //   1534: astore 9
    //   1536: goto -880 -> 656
    //   1539: ldc_w 339
    //   1542: astore 8
    //   1544: goto -838 -> 706
    //   1547: ldc_w 344
    //   1550: astore 7
    //   1552: goto -832 -> 720
    //   1555: ldc_w 339
    //   1558: astore 7
    //   1560: goto -776 -> 784
    //   1563: astore 7
    //   1565: new 349	org/eclipse/paho/client/mqttv3/MqttSecurityException
    //   1568: astore 8
    //   1570: aload 8
    //   1572: aload 7
    //   1574: invokespecial 352	org/eclipse/paho/client/mqttv3/MqttSecurityException:<init>	(Ljava/lang/Throwable;)V
    //   1577: aload 8
    //   1579: athrow
    //   1580: astore 7
    //   1582: new 349	org/eclipse/paho/client/mqttv3/MqttSecurityException
    //   1585: astore 8
    //   1587: aload 8
    //   1589: aload 7
    //   1591: invokespecial 352	org/eclipse/paho/client/mqttv3/MqttSecurityException:<init>	(Ljava/lang/Throwable;)V
    //   1594: aload 8
    //   1596: athrow
    //   1597: astore 7
    //   1599: new 349	org/eclipse/paho/client/mqttv3/MqttSecurityException
    //   1602: astore 8
    //   1604: aload 8
    //   1606: aload 7
    //   1608: invokespecial 352	org/eclipse/paho/client/mqttv3/MqttSecurityException:<init>	(Ljava/lang/Throwable;)V
    //   1611: aload 8
    //   1613: athrow
    //   1614: astore 7
    //   1616: new 349	org/eclipse/paho/client/mqttv3/MqttSecurityException
    //   1619: astore 8
    //   1621: aload 8
    //   1623: aload 7
    //   1625: invokespecial 352	org/eclipse/paho/client/mqttv3/MqttSecurityException:<init>	(Ljava/lang/Throwable;)V
    //   1628: aload 8
    //   1630: athrow
    //   1631: astore 7
    //   1633: new 349	org/eclipse/paho/client/mqttv3/MqttSecurityException
    //   1636: astore 8
    //   1638: aload 8
    //   1640: aload 7
    //   1642: invokespecial 352	org/eclipse/paho/client/mqttv3/MqttSecurityException:<init>	(Ljava/lang/Throwable;)V
    //   1645: aload 8
    //   1647: athrow
    //   1648: astore 7
    //   1650: new 349	org/eclipse/paho/client/mqttv3/MqttSecurityException
    //   1653: astore 8
    //   1655: aload 8
    //   1657: aload 7
    //   1659: invokespecial 352	org/eclipse/paho/client/mqttv3/MqttSecurityException:<init>	(Ljava/lang/Throwable;)V
    //   1662: aload 8
    //   1664: athrow
    //   1665: astore 7
    //   1667: new 349	org/eclipse/paho/client/mqttv3/MqttSecurityException
    //   1670: astore 8
    //   1672: aload 8
    //   1674: aload 7
    //   1676: invokespecial 352	org/eclipse/paho/client/mqttv3/MqttSecurityException:<init>	(Ljava/lang/Throwable;)V
    //   1679: aload 8
    //   1681: athrow
    //   1682: astore 7
    //   1684: new 349	org/eclipse/paho/client/mqttv3/MqttSecurityException
    //   1687: astore 8
    //   1689: aload 8
    //   1691: aload 7
    //   1693: invokespecial 352	org/eclipse/paho/client/mqttv3/MqttSecurityException:<init>	(Ljava/lang/Throwable;)V
    //   1696: aload 8
    //   1698: athrow
    //   1699: ldc_w 339
    //   1702: astore 7
    //   1704: goto -795 -> 909
    //   1707: ldc_w 344
    //   1710: astore 7
    //   1712: goto -785 -> 927
    //   1715: ldc_w 339
    //   1718: astore 7
    //   1720: goto -711 -> 1009
    //   1723: ldc_w 344
    //   1726: astore 7
    //   1728: goto -698 -> 1030
    //   1731: ldc_w 339
    //   1734: astore 7
    //   1736: goto -617 -> 1119
    //   1739: ldc_w 344
    //   1742: astore 7
    //   1744: goto -607 -> 1137
    //   1747: aload 7
    //   1749: invokestatic 355	javax/net/ssl/TrustManagerFactory:getInstance	(Ljava/lang/String;)Ljavax/net/ssl/TrustManagerFactory;
    //   1752: astore 8
    //   1754: aload 8
    //   1756: astore_2
    //   1757: goto -514 -> 1243
    //   1760: ldc_w 339
    //   1763: astore 8
    //   1765: goto -469 -> 1296
    //   1768: ldc_w 344
    //   1771: astore 7
    //   1773: goto -463 -> 1310
    //   1776: ldc_w 339
    //   1779: astore_1
    //   1780: goto -409 -> 1371
    //   1783: astore 7
    //   1785: new 349	org/eclipse/paho/client/mqttv3/MqttSecurityException
    //   1788: astore 8
    //   1790: aload 8
    //   1792: aload 7
    //   1794: invokespecial 352	org/eclipse/paho/client/mqttv3/MqttSecurityException:<init>	(Ljava/lang/Throwable;)V
    //   1797: aload 8
    //   1799: athrow
    //   1800: astore 7
    //   1802: new 349	org/eclipse/paho/client/mqttv3/MqttSecurityException
    //   1805: astore 8
    //   1807: aload 8
    //   1809: aload 7
    //   1811: invokespecial 352	org/eclipse/paho/client/mqttv3/MqttSecurityException:<init>	(Ljava/lang/Throwable;)V
    //   1814: aload 8
    //   1816: athrow
    //   1817: astore 7
    //   1819: new 349	org/eclipse/paho/client/mqttv3/MqttSecurityException
    //   1822: astore 8
    //   1824: aload 8
    //   1826: aload 7
    //   1828: invokespecial 352	org/eclipse/paho/client/mqttv3/MqttSecurityException:<init>	(Ljava/lang/Throwable;)V
    //   1831: aload 8
    //   1833: athrow
    //   1834: astore 7
    //   1836: new 349	org/eclipse/paho/client/mqttv3/MqttSecurityException
    //   1839: astore 8
    //   1841: aload 8
    //   1843: aload 7
    //   1845: invokespecial 352	org/eclipse/paho/client/mqttv3/MqttSecurityException:<init>	(Ljava/lang/Throwable;)V
    //   1848: aload 8
    //   1850: athrow
    //   1851: iconst_0
    //   1852: istore 14
    //   1854: aconst_null
    //   1855: astore 7
    //   1857: goto -431 -> 1426
    //   1860: aload 8
    //   1862: astore 7
    //   1864: goto -681 -> 1183
    //   1867: aconst_null
    //   1868: astore 11
    //   1870: goto -1021 -> 849
    //   1873: aload 8
    //   1875: astore 7
    //   1877: goto -1282 -> 595
    // Local variable table:
    //   start	length	slot	name	signature
    //   0	1880	0	this	a
    //   0	1880	1	paramString	String
    //   1	1756	2	localObject1	Object
    //   3	56	3	i	int
    //   5	1390	4	j	int
    //   8	1347	5	k	int
    //   11	1397	6	localObject2	Object
    //   18	1541	7	localObject3	Object
    //   1563	10	7	localKeyStoreException1	java.security.KeyStoreException
    //   1580	10	7	localNoSuchAlgorithmException	java.security.NoSuchAlgorithmException
    //   1597	10	7	localCertificateException1	java.security.cert.CertificateException
    //   1614	10	7	localNoSuchProviderException	java.security.NoSuchProviderException
    //   1631	10	7	localFileNotFoundException1	java.io.FileNotFoundException
    //   1648	10	7	localKeyManagementException	java.security.KeyManagementException
    //   1665	10	7	localIOException1	java.io.IOException
    //   1682	10	7	localUnrecoverableKeyException	java.security.UnrecoverableKeyException
    //   1702	70	7	str	String
    //   1783	10	7	localKeyStoreException2	java.security.KeyStoreException
    //   1800	10	7	localCertificateException2	java.security.cert.CertificateException
    //   1817	10	7	localFileNotFoundException2	java.io.FileNotFoundException
    //   1834	10	7	localIOException2	java.io.IOException
    //   1855	21	7	localObject4	Object
    //   33	1841	8	localObject5	Object
    //   44	1491	9	localObject6	Object
    //   48	1356	10	localObject7	Object
    //   52	1817	11	localObject8	Object
    //   56	1409	12	localObject9	Object
    //   62	1344	13	localObject10	Object
    //   152	1701	14	m	int
    //   224	1204	15	n	int
    //   310	1056	16	localObject11	Object
    //   406	524	17	i1	int
    //   409	988	18	localObject12	Object
    //   519	766	19	i2	int
    //   522	766	20	localObject13	Object
    //   697	443	21	i3	int
    // Exception table:
    //   from	to	target	type
    //   610	615	1563	java/security/KeyStoreException
    //   617	620	1563	java/security/KeyStoreException
    //   624	629	1563	java/security/KeyStoreException
    //   633	638	1563	java/security/KeyStoreException
    //   645	650	1563	java/security/KeyStoreException
    //   656	660	1563	java/security/KeyStoreException
    //   667	671	1563	java/security/KeyStoreException
    //   689	694	1563	java/security/KeyStoreException
    //   709	712	1563	java/security/KeyStoreException
    //   724	727	1563	java/security/KeyStoreException
    //   735	742	1563	java/security/KeyStoreException
    //   742	746	1563	java/security/KeyStoreException
    //   764	769	1563	java/security/KeyStoreException
    //   787	790	1563	java/security/KeyStoreException
    //   793	798	1563	java/security/KeyStoreException
    //   800	805	1563	java/security/KeyStoreException
    //   811	814	1563	java/security/KeyStoreException
    //   822	829	1563	java/security/KeyStoreException
    //   833	838	1563	java/security/KeyStoreException
    //   838	843	1563	java/security/KeyStoreException
    //   1525	1530	1563	java/security/KeyStoreException
    //   111	116	1580	java/security/NoSuchAlgorithmException
    //   122	126	1580	java/security/NoSuchAlgorithmException
    //   133	137	1580	java/security/NoSuchAlgorithmException
    //   154	159	1580	java/security/NoSuchAlgorithmException
    //   177	180	1580	java/security/NoSuchAlgorithmException
    //   183	188	1580	java/security/NoSuchAlgorithmException
    //   190	195	1580	java/security/NoSuchAlgorithmException
    //   201	204	1580	java/security/NoSuchAlgorithmException
    //   212	219	1580	java/security/NoSuchAlgorithmException
    //   233	237	1580	java/security/NoSuchAlgorithmException
    //   260	265	1580	java/security/NoSuchAlgorithmException
    //   267	271	1580	java/security/NoSuchAlgorithmException
    //   278	282	1580	java/security/NoSuchAlgorithmException
    //   299	304	1580	java/security/NoSuchAlgorithmException
    //   322	325	1580	java/security/NoSuchAlgorithmException
    //   341	344	1580	java/security/NoSuchAlgorithmException
    //   352	359	1580	java/security/NoSuchAlgorithmException
    //   360	364	1580	java/security/NoSuchAlgorithmException
    //   366	370	1580	java/security/NoSuchAlgorithmException
    //   377	381	1580	java/security/NoSuchAlgorithmException
    //   398	403	1580	java/security/NoSuchAlgorithmException
    //   421	424	1580	java/security/NoSuchAlgorithmException
    //   432	437	1580	java/security/NoSuchAlgorithmException
    //   443	446	1580	java/security/NoSuchAlgorithmException
    //   454	461	1580	java/security/NoSuchAlgorithmException
    //   462	466	1580	java/security/NoSuchAlgorithmException
    //   473	476	1580	java/security/NoSuchAlgorithmException
    //   478	482	1580	java/security/NoSuchAlgorithmException
    //   489	493	1580	java/security/NoSuchAlgorithmException
    //   511	516	1580	java/security/NoSuchAlgorithmException
    //   534	537	1580	java/security/NoSuchAlgorithmException
    //   553	556	1580	java/security/NoSuchAlgorithmException
    //   564	571	1580	java/security/NoSuchAlgorithmException
    //   571	574	1580	java/security/NoSuchAlgorithmException
    //   577	581	1580	java/security/NoSuchAlgorithmException
    //   584	588	1580	java/security/NoSuchAlgorithmException
    //   610	615	1580	java/security/NoSuchAlgorithmException
    //   617	620	1580	java/security/NoSuchAlgorithmException
    //   624	629	1580	java/security/NoSuchAlgorithmException
    //   633	638	1580	java/security/NoSuchAlgorithmException
    //   645	650	1580	java/security/NoSuchAlgorithmException
    //   656	660	1580	java/security/NoSuchAlgorithmException
    //   667	671	1580	java/security/NoSuchAlgorithmException
    //   689	694	1580	java/security/NoSuchAlgorithmException
    //   709	712	1580	java/security/NoSuchAlgorithmException
    //   724	727	1580	java/security/NoSuchAlgorithmException
    //   735	742	1580	java/security/NoSuchAlgorithmException
    //   742	746	1580	java/security/NoSuchAlgorithmException
    //   764	769	1580	java/security/NoSuchAlgorithmException
    //   787	790	1580	java/security/NoSuchAlgorithmException
    //   793	798	1580	java/security/NoSuchAlgorithmException
    //   800	805	1580	java/security/NoSuchAlgorithmException
    //   811	814	1580	java/security/NoSuchAlgorithmException
    //   822	829	1580	java/security/NoSuchAlgorithmException
    //   833	838	1580	java/security/NoSuchAlgorithmException
    //   838	843	1580	java/security/NoSuchAlgorithmException
    //   850	854	1580	java/security/NoSuchAlgorithmException
    //   856	860	1580	java/security/NoSuchAlgorithmException
    //   867	871	1580	java/security/NoSuchAlgorithmException
    //   889	894	1580	java/security/NoSuchAlgorithmException
    //   912	915	1580	java/security/NoSuchAlgorithmException
    //   931	934	1580	java/security/NoSuchAlgorithmException
    //   942	949	1580	java/security/NoSuchAlgorithmException
    //   950	954	1580	java/security/NoSuchAlgorithmException
    //   956	960	1580	java/security/NoSuchAlgorithmException
    //   967	971	1580	java/security/NoSuchAlgorithmException
    //   989	994	1580	java/security/NoSuchAlgorithmException
    //   1012	1015	1580	java/security/NoSuchAlgorithmException
    //   1023	1028	1580	java/security/NoSuchAlgorithmException
    //   1034	1037	1580	java/security/NoSuchAlgorithmException
    //   1045	1052	1580	java/security/NoSuchAlgorithmException
    //   1053	1057	1580	java/security/NoSuchAlgorithmException
    //   1064	1067	1580	java/security/NoSuchAlgorithmException
    //   1069	1073	1580	java/security/NoSuchAlgorithmException
    //   1080	1084	1580	java/security/NoSuchAlgorithmException
    //   1102	1107	1580	java/security/NoSuchAlgorithmException
    //   1122	1125	1580	java/security/NoSuchAlgorithmException
    //   1141	1144	1580	java/security/NoSuchAlgorithmException
    //   1152	1159	1580	java/security/NoSuchAlgorithmException
    //   1159	1162	1580	java/security/NoSuchAlgorithmException
    //   1165	1169	1580	java/security/NoSuchAlgorithmException
    //   1172	1176	1580	java/security/NoSuchAlgorithmException
    //   1198	1203	1580	java/security/NoSuchAlgorithmException
    //   1205	1208	1580	java/security/NoSuchAlgorithmException
    //   1212	1217	1580	java/security/NoSuchAlgorithmException
    //   1221	1226	1580	java/security/NoSuchAlgorithmException
    //   1233	1238	1580	java/security/NoSuchAlgorithmException
    //   1243	1247	1580	java/security/NoSuchAlgorithmException
    //   1254	1258	1580	java/security/NoSuchAlgorithmException
    //   1276	1281	1580	java/security/NoSuchAlgorithmException
    //   1299	1302	1580	java/security/NoSuchAlgorithmException
    //   1314	1317	1580	java/security/NoSuchAlgorithmException
    //   1325	1332	1580	java/security/NoSuchAlgorithmException
    //   1332	1336	1580	java/security/NoSuchAlgorithmException
    //   1354	1359	1580	java/security/NoSuchAlgorithmException
    //   1374	1376	1580	java/security/NoSuchAlgorithmException
    //   1379	1383	1580	java/security/NoSuchAlgorithmException
    //   1385	1390	1580	java/security/NoSuchAlgorithmException
    //   1396	1399	1580	java/security/NoSuchAlgorithmException
    //   1407	1414	1580	java/security/NoSuchAlgorithmException
    //   1415	1420	1580	java/security/NoSuchAlgorithmException
    //   1420	1424	1580	java/security/NoSuchAlgorithmException
    //   1438	1442	1580	java/security/NoSuchAlgorithmException
    //   1455	1460	1580	java/security/NoSuchAlgorithmException
    //   1525	1530	1580	java/security/NoSuchAlgorithmException
    //   1565	1568	1580	java/security/NoSuchAlgorithmException
    //   1572	1577	1580	java/security/NoSuchAlgorithmException
    //   1577	1580	1580	java/security/NoSuchAlgorithmException
    //   1599	1602	1580	java/security/NoSuchAlgorithmException
    //   1606	1611	1580	java/security/NoSuchAlgorithmException
    //   1611	1614	1580	java/security/NoSuchAlgorithmException
    //   1633	1636	1580	java/security/NoSuchAlgorithmException
    //   1640	1645	1580	java/security/NoSuchAlgorithmException
    //   1645	1648	1580	java/security/NoSuchAlgorithmException
    //   1667	1670	1580	java/security/NoSuchAlgorithmException
    //   1674	1679	1580	java/security/NoSuchAlgorithmException
    //   1679	1682	1580	java/security/NoSuchAlgorithmException
    //   1684	1687	1580	java/security/NoSuchAlgorithmException
    //   1691	1696	1580	java/security/NoSuchAlgorithmException
    //   1696	1699	1580	java/security/NoSuchAlgorithmException
    //   1747	1752	1580	java/security/NoSuchAlgorithmException
    //   1785	1788	1580	java/security/NoSuchAlgorithmException
    //   1792	1797	1580	java/security/NoSuchAlgorithmException
    //   1797	1800	1580	java/security/NoSuchAlgorithmException
    //   1802	1805	1580	java/security/NoSuchAlgorithmException
    //   1809	1814	1580	java/security/NoSuchAlgorithmException
    //   1814	1817	1580	java/security/NoSuchAlgorithmException
    //   1819	1822	1580	java/security/NoSuchAlgorithmException
    //   1826	1831	1580	java/security/NoSuchAlgorithmException
    //   1831	1834	1580	java/security/NoSuchAlgorithmException
    //   1836	1839	1580	java/security/NoSuchAlgorithmException
    //   1843	1848	1580	java/security/NoSuchAlgorithmException
    //   1848	1851	1580	java/security/NoSuchAlgorithmException
    //   610	615	1597	java/security/cert/CertificateException
    //   617	620	1597	java/security/cert/CertificateException
    //   624	629	1597	java/security/cert/CertificateException
    //   633	638	1597	java/security/cert/CertificateException
    //   645	650	1597	java/security/cert/CertificateException
    //   656	660	1597	java/security/cert/CertificateException
    //   667	671	1597	java/security/cert/CertificateException
    //   689	694	1597	java/security/cert/CertificateException
    //   709	712	1597	java/security/cert/CertificateException
    //   724	727	1597	java/security/cert/CertificateException
    //   735	742	1597	java/security/cert/CertificateException
    //   742	746	1597	java/security/cert/CertificateException
    //   764	769	1597	java/security/cert/CertificateException
    //   787	790	1597	java/security/cert/CertificateException
    //   793	798	1597	java/security/cert/CertificateException
    //   800	805	1597	java/security/cert/CertificateException
    //   811	814	1597	java/security/cert/CertificateException
    //   822	829	1597	java/security/cert/CertificateException
    //   833	838	1597	java/security/cert/CertificateException
    //   838	843	1597	java/security/cert/CertificateException
    //   1525	1530	1597	java/security/cert/CertificateException
    //   111	116	1614	java/security/NoSuchProviderException
    //   122	126	1614	java/security/NoSuchProviderException
    //   133	137	1614	java/security/NoSuchProviderException
    //   154	159	1614	java/security/NoSuchProviderException
    //   177	180	1614	java/security/NoSuchProviderException
    //   183	188	1614	java/security/NoSuchProviderException
    //   190	195	1614	java/security/NoSuchProviderException
    //   201	204	1614	java/security/NoSuchProviderException
    //   212	219	1614	java/security/NoSuchProviderException
    //   233	237	1614	java/security/NoSuchProviderException
    //   260	265	1614	java/security/NoSuchProviderException
    //   267	271	1614	java/security/NoSuchProviderException
    //   278	282	1614	java/security/NoSuchProviderException
    //   299	304	1614	java/security/NoSuchProviderException
    //   322	325	1614	java/security/NoSuchProviderException
    //   341	344	1614	java/security/NoSuchProviderException
    //   352	359	1614	java/security/NoSuchProviderException
    //   360	364	1614	java/security/NoSuchProviderException
    //   366	370	1614	java/security/NoSuchProviderException
    //   377	381	1614	java/security/NoSuchProviderException
    //   398	403	1614	java/security/NoSuchProviderException
    //   421	424	1614	java/security/NoSuchProviderException
    //   432	437	1614	java/security/NoSuchProviderException
    //   443	446	1614	java/security/NoSuchProviderException
    //   454	461	1614	java/security/NoSuchProviderException
    //   462	466	1614	java/security/NoSuchProviderException
    //   473	476	1614	java/security/NoSuchProviderException
    //   478	482	1614	java/security/NoSuchProviderException
    //   489	493	1614	java/security/NoSuchProviderException
    //   511	516	1614	java/security/NoSuchProviderException
    //   534	537	1614	java/security/NoSuchProviderException
    //   553	556	1614	java/security/NoSuchProviderException
    //   564	571	1614	java/security/NoSuchProviderException
    //   571	574	1614	java/security/NoSuchProviderException
    //   577	581	1614	java/security/NoSuchProviderException
    //   584	588	1614	java/security/NoSuchProviderException
    //   610	615	1614	java/security/NoSuchProviderException
    //   617	620	1614	java/security/NoSuchProviderException
    //   624	629	1614	java/security/NoSuchProviderException
    //   633	638	1614	java/security/NoSuchProviderException
    //   645	650	1614	java/security/NoSuchProviderException
    //   656	660	1614	java/security/NoSuchProviderException
    //   667	671	1614	java/security/NoSuchProviderException
    //   689	694	1614	java/security/NoSuchProviderException
    //   709	712	1614	java/security/NoSuchProviderException
    //   724	727	1614	java/security/NoSuchProviderException
    //   735	742	1614	java/security/NoSuchProviderException
    //   742	746	1614	java/security/NoSuchProviderException
    //   764	769	1614	java/security/NoSuchProviderException
    //   787	790	1614	java/security/NoSuchProviderException
    //   793	798	1614	java/security/NoSuchProviderException
    //   800	805	1614	java/security/NoSuchProviderException
    //   811	814	1614	java/security/NoSuchProviderException
    //   822	829	1614	java/security/NoSuchProviderException
    //   833	838	1614	java/security/NoSuchProviderException
    //   838	843	1614	java/security/NoSuchProviderException
    //   850	854	1614	java/security/NoSuchProviderException
    //   856	860	1614	java/security/NoSuchProviderException
    //   867	871	1614	java/security/NoSuchProviderException
    //   889	894	1614	java/security/NoSuchProviderException
    //   912	915	1614	java/security/NoSuchProviderException
    //   931	934	1614	java/security/NoSuchProviderException
    //   942	949	1614	java/security/NoSuchProviderException
    //   950	954	1614	java/security/NoSuchProviderException
    //   956	960	1614	java/security/NoSuchProviderException
    //   967	971	1614	java/security/NoSuchProviderException
    //   989	994	1614	java/security/NoSuchProviderException
    //   1012	1015	1614	java/security/NoSuchProviderException
    //   1023	1028	1614	java/security/NoSuchProviderException
    //   1034	1037	1614	java/security/NoSuchProviderException
    //   1045	1052	1614	java/security/NoSuchProviderException
    //   1053	1057	1614	java/security/NoSuchProviderException
    //   1064	1067	1614	java/security/NoSuchProviderException
    //   1069	1073	1614	java/security/NoSuchProviderException
    //   1080	1084	1614	java/security/NoSuchProviderException
    //   1102	1107	1614	java/security/NoSuchProviderException
    //   1122	1125	1614	java/security/NoSuchProviderException
    //   1141	1144	1614	java/security/NoSuchProviderException
    //   1152	1159	1614	java/security/NoSuchProviderException
    //   1159	1162	1614	java/security/NoSuchProviderException
    //   1165	1169	1614	java/security/NoSuchProviderException
    //   1172	1176	1614	java/security/NoSuchProviderException
    //   1198	1203	1614	java/security/NoSuchProviderException
    //   1205	1208	1614	java/security/NoSuchProviderException
    //   1212	1217	1614	java/security/NoSuchProviderException
    //   1221	1226	1614	java/security/NoSuchProviderException
    //   1233	1238	1614	java/security/NoSuchProviderException
    //   1243	1247	1614	java/security/NoSuchProviderException
    //   1254	1258	1614	java/security/NoSuchProviderException
    //   1276	1281	1614	java/security/NoSuchProviderException
    //   1299	1302	1614	java/security/NoSuchProviderException
    //   1314	1317	1614	java/security/NoSuchProviderException
    //   1325	1332	1614	java/security/NoSuchProviderException
    //   1332	1336	1614	java/security/NoSuchProviderException
    //   1354	1359	1614	java/security/NoSuchProviderException
    //   1374	1376	1614	java/security/NoSuchProviderException
    //   1379	1383	1614	java/security/NoSuchProviderException
    //   1385	1390	1614	java/security/NoSuchProviderException
    //   1396	1399	1614	java/security/NoSuchProviderException
    //   1407	1414	1614	java/security/NoSuchProviderException
    //   1415	1420	1614	java/security/NoSuchProviderException
    //   1420	1424	1614	java/security/NoSuchProviderException
    //   1438	1442	1614	java/security/NoSuchProviderException
    //   1455	1460	1614	java/security/NoSuchProviderException
    //   1525	1530	1614	java/security/NoSuchProviderException
    //   1565	1568	1614	java/security/NoSuchProviderException
    //   1572	1577	1614	java/security/NoSuchProviderException
    //   1577	1580	1614	java/security/NoSuchProviderException
    //   1599	1602	1614	java/security/NoSuchProviderException
    //   1606	1611	1614	java/security/NoSuchProviderException
    //   1611	1614	1614	java/security/NoSuchProviderException
    //   1633	1636	1614	java/security/NoSuchProviderException
    //   1640	1645	1614	java/security/NoSuchProviderException
    //   1645	1648	1614	java/security/NoSuchProviderException
    //   1667	1670	1614	java/security/NoSuchProviderException
    //   1674	1679	1614	java/security/NoSuchProviderException
    //   1679	1682	1614	java/security/NoSuchProviderException
    //   1684	1687	1614	java/security/NoSuchProviderException
    //   1691	1696	1614	java/security/NoSuchProviderException
    //   1696	1699	1614	java/security/NoSuchProviderException
    //   1747	1752	1614	java/security/NoSuchProviderException
    //   1785	1788	1614	java/security/NoSuchProviderException
    //   1792	1797	1614	java/security/NoSuchProviderException
    //   1797	1800	1614	java/security/NoSuchProviderException
    //   1802	1805	1614	java/security/NoSuchProviderException
    //   1809	1814	1614	java/security/NoSuchProviderException
    //   1814	1817	1614	java/security/NoSuchProviderException
    //   1819	1822	1614	java/security/NoSuchProviderException
    //   1826	1831	1614	java/security/NoSuchProviderException
    //   1831	1834	1614	java/security/NoSuchProviderException
    //   1836	1839	1614	java/security/NoSuchProviderException
    //   1843	1848	1614	java/security/NoSuchProviderException
    //   1848	1851	1614	java/security/NoSuchProviderException
    //   610	615	1631	java/io/FileNotFoundException
    //   617	620	1631	java/io/FileNotFoundException
    //   624	629	1631	java/io/FileNotFoundException
    //   633	638	1631	java/io/FileNotFoundException
    //   645	650	1631	java/io/FileNotFoundException
    //   656	660	1631	java/io/FileNotFoundException
    //   667	671	1631	java/io/FileNotFoundException
    //   689	694	1631	java/io/FileNotFoundException
    //   709	712	1631	java/io/FileNotFoundException
    //   724	727	1631	java/io/FileNotFoundException
    //   735	742	1631	java/io/FileNotFoundException
    //   742	746	1631	java/io/FileNotFoundException
    //   764	769	1631	java/io/FileNotFoundException
    //   787	790	1631	java/io/FileNotFoundException
    //   793	798	1631	java/io/FileNotFoundException
    //   800	805	1631	java/io/FileNotFoundException
    //   811	814	1631	java/io/FileNotFoundException
    //   822	829	1631	java/io/FileNotFoundException
    //   833	838	1631	java/io/FileNotFoundException
    //   838	843	1631	java/io/FileNotFoundException
    //   1525	1530	1631	java/io/FileNotFoundException
    //   111	116	1648	java/security/KeyManagementException
    //   122	126	1648	java/security/KeyManagementException
    //   133	137	1648	java/security/KeyManagementException
    //   154	159	1648	java/security/KeyManagementException
    //   177	180	1648	java/security/KeyManagementException
    //   183	188	1648	java/security/KeyManagementException
    //   190	195	1648	java/security/KeyManagementException
    //   201	204	1648	java/security/KeyManagementException
    //   212	219	1648	java/security/KeyManagementException
    //   233	237	1648	java/security/KeyManagementException
    //   260	265	1648	java/security/KeyManagementException
    //   267	271	1648	java/security/KeyManagementException
    //   278	282	1648	java/security/KeyManagementException
    //   299	304	1648	java/security/KeyManagementException
    //   322	325	1648	java/security/KeyManagementException
    //   341	344	1648	java/security/KeyManagementException
    //   352	359	1648	java/security/KeyManagementException
    //   360	364	1648	java/security/KeyManagementException
    //   366	370	1648	java/security/KeyManagementException
    //   377	381	1648	java/security/KeyManagementException
    //   398	403	1648	java/security/KeyManagementException
    //   421	424	1648	java/security/KeyManagementException
    //   432	437	1648	java/security/KeyManagementException
    //   443	446	1648	java/security/KeyManagementException
    //   454	461	1648	java/security/KeyManagementException
    //   462	466	1648	java/security/KeyManagementException
    //   473	476	1648	java/security/KeyManagementException
    //   478	482	1648	java/security/KeyManagementException
    //   489	493	1648	java/security/KeyManagementException
    //   511	516	1648	java/security/KeyManagementException
    //   534	537	1648	java/security/KeyManagementException
    //   553	556	1648	java/security/KeyManagementException
    //   564	571	1648	java/security/KeyManagementException
    //   571	574	1648	java/security/KeyManagementException
    //   577	581	1648	java/security/KeyManagementException
    //   584	588	1648	java/security/KeyManagementException
    //   610	615	1648	java/security/KeyManagementException
    //   617	620	1648	java/security/KeyManagementException
    //   624	629	1648	java/security/KeyManagementException
    //   633	638	1648	java/security/KeyManagementException
    //   645	650	1648	java/security/KeyManagementException
    //   656	660	1648	java/security/KeyManagementException
    //   667	671	1648	java/security/KeyManagementException
    //   689	694	1648	java/security/KeyManagementException
    //   709	712	1648	java/security/KeyManagementException
    //   724	727	1648	java/security/KeyManagementException
    //   735	742	1648	java/security/KeyManagementException
    //   742	746	1648	java/security/KeyManagementException
    //   764	769	1648	java/security/KeyManagementException
    //   787	790	1648	java/security/KeyManagementException
    //   793	798	1648	java/security/KeyManagementException
    //   800	805	1648	java/security/KeyManagementException
    //   811	814	1648	java/security/KeyManagementException
    //   822	829	1648	java/security/KeyManagementException
    //   833	838	1648	java/security/KeyManagementException
    //   838	843	1648	java/security/KeyManagementException
    //   850	854	1648	java/security/KeyManagementException
    //   856	860	1648	java/security/KeyManagementException
    //   867	871	1648	java/security/KeyManagementException
    //   889	894	1648	java/security/KeyManagementException
    //   912	915	1648	java/security/KeyManagementException
    //   931	934	1648	java/security/KeyManagementException
    //   942	949	1648	java/security/KeyManagementException
    //   950	954	1648	java/security/KeyManagementException
    //   956	960	1648	java/security/KeyManagementException
    //   967	971	1648	java/security/KeyManagementException
    //   989	994	1648	java/security/KeyManagementException
    //   1012	1015	1648	java/security/KeyManagementException
    //   1023	1028	1648	java/security/KeyManagementException
    //   1034	1037	1648	java/security/KeyManagementException
    //   1045	1052	1648	java/security/KeyManagementException
    //   1053	1057	1648	java/security/KeyManagementException
    //   1064	1067	1648	java/security/KeyManagementException
    //   1069	1073	1648	java/security/KeyManagementException
    //   1080	1084	1648	java/security/KeyManagementException
    //   1102	1107	1648	java/security/KeyManagementException
    //   1122	1125	1648	java/security/KeyManagementException
    //   1141	1144	1648	java/security/KeyManagementException
    //   1152	1159	1648	java/security/KeyManagementException
    //   1159	1162	1648	java/security/KeyManagementException
    //   1165	1169	1648	java/security/KeyManagementException
    //   1172	1176	1648	java/security/KeyManagementException
    //   1198	1203	1648	java/security/KeyManagementException
    //   1205	1208	1648	java/security/KeyManagementException
    //   1212	1217	1648	java/security/KeyManagementException
    //   1221	1226	1648	java/security/KeyManagementException
    //   1233	1238	1648	java/security/KeyManagementException
    //   1243	1247	1648	java/security/KeyManagementException
    //   1254	1258	1648	java/security/KeyManagementException
    //   1276	1281	1648	java/security/KeyManagementException
    //   1299	1302	1648	java/security/KeyManagementException
    //   1314	1317	1648	java/security/KeyManagementException
    //   1325	1332	1648	java/security/KeyManagementException
    //   1332	1336	1648	java/security/KeyManagementException
    //   1354	1359	1648	java/security/KeyManagementException
    //   1374	1376	1648	java/security/KeyManagementException
    //   1379	1383	1648	java/security/KeyManagementException
    //   1385	1390	1648	java/security/KeyManagementException
    //   1396	1399	1648	java/security/KeyManagementException
    //   1407	1414	1648	java/security/KeyManagementException
    //   1415	1420	1648	java/security/KeyManagementException
    //   1420	1424	1648	java/security/KeyManagementException
    //   1438	1442	1648	java/security/KeyManagementException
    //   1455	1460	1648	java/security/KeyManagementException
    //   1525	1530	1648	java/security/KeyManagementException
    //   1565	1568	1648	java/security/KeyManagementException
    //   1572	1577	1648	java/security/KeyManagementException
    //   1577	1580	1648	java/security/KeyManagementException
    //   1599	1602	1648	java/security/KeyManagementException
    //   1606	1611	1648	java/security/KeyManagementException
    //   1611	1614	1648	java/security/KeyManagementException
    //   1633	1636	1648	java/security/KeyManagementException
    //   1640	1645	1648	java/security/KeyManagementException
    //   1645	1648	1648	java/security/KeyManagementException
    //   1667	1670	1648	java/security/KeyManagementException
    //   1674	1679	1648	java/security/KeyManagementException
    //   1679	1682	1648	java/security/KeyManagementException
    //   1684	1687	1648	java/security/KeyManagementException
    //   1691	1696	1648	java/security/KeyManagementException
    //   1696	1699	1648	java/security/KeyManagementException
    //   1747	1752	1648	java/security/KeyManagementException
    //   1785	1788	1648	java/security/KeyManagementException
    //   1792	1797	1648	java/security/KeyManagementException
    //   1797	1800	1648	java/security/KeyManagementException
    //   1802	1805	1648	java/security/KeyManagementException
    //   1809	1814	1648	java/security/KeyManagementException
    //   1814	1817	1648	java/security/KeyManagementException
    //   1819	1822	1648	java/security/KeyManagementException
    //   1826	1831	1648	java/security/KeyManagementException
    //   1831	1834	1648	java/security/KeyManagementException
    //   1836	1839	1648	java/security/KeyManagementException
    //   1843	1848	1648	java/security/KeyManagementException
    //   1848	1851	1648	java/security/KeyManagementException
    //   610	615	1665	java/io/IOException
    //   617	620	1665	java/io/IOException
    //   624	629	1665	java/io/IOException
    //   633	638	1665	java/io/IOException
    //   645	650	1665	java/io/IOException
    //   656	660	1665	java/io/IOException
    //   667	671	1665	java/io/IOException
    //   689	694	1665	java/io/IOException
    //   709	712	1665	java/io/IOException
    //   724	727	1665	java/io/IOException
    //   735	742	1665	java/io/IOException
    //   742	746	1665	java/io/IOException
    //   764	769	1665	java/io/IOException
    //   787	790	1665	java/io/IOException
    //   793	798	1665	java/io/IOException
    //   800	805	1665	java/io/IOException
    //   811	814	1665	java/io/IOException
    //   822	829	1665	java/io/IOException
    //   833	838	1665	java/io/IOException
    //   838	843	1665	java/io/IOException
    //   1525	1530	1665	java/io/IOException
    //   610	615	1682	java/security/UnrecoverableKeyException
    //   617	620	1682	java/security/UnrecoverableKeyException
    //   624	629	1682	java/security/UnrecoverableKeyException
    //   633	638	1682	java/security/UnrecoverableKeyException
    //   645	650	1682	java/security/UnrecoverableKeyException
    //   656	660	1682	java/security/UnrecoverableKeyException
    //   667	671	1682	java/security/UnrecoverableKeyException
    //   689	694	1682	java/security/UnrecoverableKeyException
    //   709	712	1682	java/security/UnrecoverableKeyException
    //   724	727	1682	java/security/UnrecoverableKeyException
    //   735	742	1682	java/security/UnrecoverableKeyException
    //   742	746	1682	java/security/UnrecoverableKeyException
    //   764	769	1682	java/security/UnrecoverableKeyException
    //   787	790	1682	java/security/UnrecoverableKeyException
    //   793	798	1682	java/security/UnrecoverableKeyException
    //   800	805	1682	java/security/UnrecoverableKeyException
    //   811	814	1682	java/security/UnrecoverableKeyException
    //   822	829	1682	java/security/UnrecoverableKeyException
    //   833	838	1682	java/security/UnrecoverableKeyException
    //   838	843	1682	java/security/UnrecoverableKeyException
    //   1525	1530	1682	java/security/UnrecoverableKeyException
    //   1198	1203	1783	java/security/KeyStoreException
    //   1205	1208	1783	java/security/KeyStoreException
    //   1212	1217	1783	java/security/KeyStoreException
    //   1221	1226	1783	java/security/KeyStoreException
    //   1233	1238	1783	java/security/KeyStoreException
    //   1243	1247	1783	java/security/KeyStoreException
    //   1254	1258	1783	java/security/KeyStoreException
    //   1276	1281	1783	java/security/KeyStoreException
    //   1299	1302	1783	java/security/KeyStoreException
    //   1314	1317	1783	java/security/KeyStoreException
    //   1325	1332	1783	java/security/KeyStoreException
    //   1332	1336	1783	java/security/KeyStoreException
    //   1354	1359	1783	java/security/KeyStoreException
    //   1374	1376	1783	java/security/KeyStoreException
    //   1379	1383	1783	java/security/KeyStoreException
    //   1385	1390	1783	java/security/KeyStoreException
    //   1396	1399	1783	java/security/KeyStoreException
    //   1407	1414	1783	java/security/KeyStoreException
    //   1415	1420	1783	java/security/KeyStoreException
    //   1420	1424	1783	java/security/KeyStoreException
    //   1747	1752	1783	java/security/KeyStoreException
    //   1198	1203	1800	java/security/cert/CertificateException
    //   1205	1208	1800	java/security/cert/CertificateException
    //   1212	1217	1800	java/security/cert/CertificateException
    //   1221	1226	1800	java/security/cert/CertificateException
    //   1233	1238	1800	java/security/cert/CertificateException
    //   1243	1247	1800	java/security/cert/CertificateException
    //   1254	1258	1800	java/security/cert/CertificateException
    //   1276	1281	1800	java/security/cert/CertificateException
    //   1299	1302	1800	java/security/cert/CertificateException
    //   1314	1317	1800	java/security/cert/CertificateException
    //   1325	1332	1800	java/security/cert/CertificateException
    //   1332	1336	1800	java/security/cert/CertificateException
    //   1354	1359	1800	java/security/cert/CertificateException
    //   1374	1376	1800	java/security/cert/CertificateException
    //   1379	1383	1800	java/security/cert/CertificateException
    //   1385	1390	1800	java/security/cert/CertificateException
    //   1396	1399	1800	java/security/cert/CertificateException
    //   1407	1414	1800	java/security/cert/CertificateException
    //   1415	1420	1800	java/security/cert/CertificateException
    //   1420	1424	1800	java/security/cert/CertificateException
    //   1747	1752	1800	java/security/cert/CertificateException
    //   1198	1203	1817	java/io/FileNotFoundException
    //   1205	1208	1817	java/io/FileNotFoundException
    //   1212	1217	1817	java/io/FileNotFoundException
    //   1221	1226	1817	java/io/FileNotFoundException
    //   1233	1238	1817	java/io/FileNotFoundException
    //   1243	1247	1817	java/io/FileNotFoundException
    //   1254	1258	1817	java/io/FileNotFoundException
    //   1276	1281	1817	java/io/FileNotFoundException
    //   1299	1302	1817	java/io/FileNotFoundException
    //   1314	1317	1817	java/io/FileNotFoundException
    //   1325	1332	1817	java/io/FileNotFoundException
    //   1332	1336	1817	java/io/FileNotFoundException
    //   1354	1359	1817	java/io/FileNotFoundException
    //   1374	1376	1817	java/io/FileNotFoundException
    //   1379	1383	1817	java/io/FileNotFoundException
    //   1385	1390	1817	java/io/FileNotFoundException
    //   1396	1399	1817	java/io/FileNotFoundException
    //   1407	1414	1817	java/io/FileNotFoundException
    //   1415	1420	1817	java/io/FileNotFoundException
    //   1420	1424	1817	java/io/FileNotFoundException
    //   1747	1752	1817	java/io/FileNotFoundException
    //   1198	1203	1834	java/io/IOException
    //   1205	1208	1834	java/io/IOException
    //   1212	1217	1834	java/io/IOException
    //   1221	1226	1834	java/io/IOException
    //   1233	1238	1834	java/io/IOException
    //   1243	1247	1834	java/io/IOException
    //   1254	1258	1834	java/io/IOException
    //   1276	1281	1834	java/io/IOException
    //   1299	1302	1834	java/io/IOException
    //   1314	1317	1834	java/io/IOException
    //   1325	1332	1834	java/io/IOException
    //   1332	1336	1834	java/io/IOException
    //   1354	1359	1834	java/io/IOException
    //   1374	1376	1834	java/io/IOException
    //   1379	1383	1834	java/io/IOException
    //   1385	1390	1834	java/io/IOException
    //   1396	1399	1834	java/io/IOException
    //   1407	1414	1834	java/io/IOException
    //   1415	1420	1834	java/io/IOException
    //   1420	1424	1834	java/io/IOException
    //   1747	1752	1834	java/io/IOException
  }
  
  public void a(Properties paramProperties, String paramString)
  {
    a(paramProperties);
    Properties localProperties = new java/util/Properties;
    localProperties.<init>();
    localProperties.putAll(paramProperties);
    b(localProperties);
    if (paramString != null)
    {
      Hashtable localHashtable = this.b;
      localHashtable.put(paramString, localProperties);
    }
    for (;;)
    {
      return;
      this.c = localProperties;
    }
  }
  
  public String c(String paramString)
  {
    return a(paramString, "com.ibm.ssl.protocol", null);
  }
  
  public String d(String paramString)
  {
    return a(paramString, "com.ibm.ssl.contextProvider", null);
  }
  
  public char[] e(String paramString)
  {
    String str = a(paramString, "com.ibm.ssl.keyStorePassword", "javax.net.ssl.keyStorePassword");
    boolean bool = false;
    Object localObject = null;
    if (str != null)
    {
      localObject = "{xor}";
      bool = str.startsWith((String)localObject);
      if (!bool) {
        break label44;
      }
    }
    label44:
    for (localObject = a(str);; localObject = str.toCharArray()) {
      return (char[])localObject;
    }
  }
  
  public String f(String paramString)
  {
    return a(paramString, "com.ibm.ssl.keyStoreType", "javax.net.ssl.keyStoreType");
  }
  
  public String g(String paramString)
  {
    return a(paramString, "com.ibm.ssl.keyStoreProvider", null);
  }
  
  public String h(String paramString)
  {
    return a(paramString, "com.ibm.ssl.keyManager", "ssl.KeyManagerFactory.algorithm");
  }
  
  public String i(String paramString)
  {
    return a(paramString, "com.ibm.ssl.trustStore", "javax.net.ssl.trustStore");
  }
  
  public char[] j(String paramString)
  {
    String str = a(paramString, "com.ibm.ssl.trustStorePassword", "javax.net.ssl.trustStorePassword");
    boolean bool = false;
    Object localObject = null;
    if (str != null)
    {
      localObject = "{xor}";
      bool = str.startsWith((String)localObject);
      if (!bool) {
        break label44;
      }
    }
    label44:
    for (localObject = a(str);; localObject = str.toCharArray()) {
      return (char[])localObject;
    }
  }
  
  public String k(String paramString)
  {
    return a(paramString, "com.ibm.ssl.trustStoreType", null);
  }
  
  public String l(String paramString)
  {
    return a(paramString, "com.ibm.ssl.trustStoreProvider", null);
  }
  
  public String m(String paramString)
  {
    return a(paramString, "com.ibm.ssl.trustManager", "ssl.TrustManagerFactory.algorithm");
  }
  
  public String[] n(String paramString)
  {
    return b(a(paramString, "com.ibm.ssl.enabledCipherSuites", null));
  }
  
  public SSLSocketFactory o(String paramString)
  {
    SSLContext localSSLContext = q(paramString);
    Object localObject = this.e;
    org.eclipse.paho.client.mqttv3.b.b localb;
    String str1;
    String str2;
    String str3;
    Object[] arrayOfObject;
    int j;
    if (localObject != null)
    {
      localb = this.e;
      str1 = "org.eclipse.paho.client.mqttv3.internal.security.SSLSocketFactoryFactory";
      str2 = "createSocketFactory";
      str3 = "12020";
      int i = 2;
      arrayOfObject = new Object[i];
      j = 0;
      if (paramString == null) {
        break label107;
      }
      localObject = paramString;
      arrayOfObject[0] = localObject;
      j = 1;
      localObject = n(paramString);
      if (localObject == null) {
        break label114;
      }
    }
    label107:
    label114:
    for (localObject = a(paramString, "com.ibm.ssl.enabledCipherSuites", null);; localObject = "null (using platform-enabled cipher suites)")
    {
      arrayOfObject[j] = localObject;
      localb.b(str1, str2, str3, arrayOfObject);
      return localSSLContext.getSocketFactory();
      localObject = "null (broker defaults)";
      break;
    }
  }
}


/* Location:              /Volumes/D1/codebase/android/POC/assets/product/maind/classes-enjarify.jar!/org/eclipse/paho/client/mqttv3/a/a/a.class
 * Java compiler version: 5 (49.0)
 * JD-Core Version:       0.7.1
 */