package com.vvt.http;

class c
  extends Thread
{
  private c(a parama) {}
  
  /* Error */
  public void run()
  {
    // Byte code:
    //   0: iconst_m1
    //   1: istore_1
    //   2: iconst_1
    //   3: istore_2
    //   4: invokestatic 22	com/vvt/http/a:MyUncaughtExceptionHandler	()Z
    //   7: istore_3
    //   8: iload_3
    //   9: ifeq +3 -> 12
    //   12: new 24	com/vvt/http/request/a
    //   15: astore 4
    //   17: aload 4
    //   19: invokespecial 25	com/vvt/http/request/a:<init>	()V
    //   22: lconst_0
    //   23: lstore 5
    //   25: aload_0
    //   26: getfield 8	com/vvt/http/MyUncaughtExceptionHandler:a	Lcom/vvt/http/a;
    //   29: invokestatic 28	com/vvt/http/a:a	(Lcom/vvt/http/a;)Lcom/vvt/http/request/removeFromPath;
    //   32: invokevirtual 33	com/vvt/http/request/removeFromPath:a	()Ljava/util/ArrayList;
    //   35: astore 7
    //   37: aload 7
    //   39: ifnull +2000 -> 2039
    //   42: aload_0
    //   43: getfield 8	com/vvt/http/MyUncaughtExceptionHandler:a	Lcom/vvt/http/a;
    //   46: invokestatic 28	com/vvt/http/a:a	(Lcom/vvt/http/a;)Lcom/vvt/http/request/removeFromPath;
    //   49: invokevirtual 33	com/vvt/http/request/removeFromPath:a	()Ljava/util/ArrayList;
    //   52: astore 8
    //   54: aload 4
    //   56: aload 8
    //   58: invokevirtual 36	com/vvt/http/request/a:a	(Ljava/util/ArrayList;)V
    //   61: aload 4
    //   63: invokevirtual 39	com/vvt/http/request/a:a	()J
    //   66: lstore 5
    //   68: lload 5
    //   70: lstore 9
    //   72: ldc 41
    //   74: astore 8
    //   76: ldc 43
    //   78: astore 11
    //   80: aload 8
    //   82: aload 11
    //   84: invokestatic 49	java/lang/System:setProperty	(Ljava/lang/String;Ljava/lang/String;)Ljava/lang/String;
    //   87: pop
    //   88: aload_0
    //   89: getfield 8	com/vvt/http/MyUncaughtExceptionHandler:a	Lcom/vvt/http/a;
    //   92: astore 8
    //   94: aload 8
    //   96: invokestatic 28	com/vvt/http/a:a	(Lcom/vvt/http/a;)Lcom/vvt/http/request/removeFromPath;
    //   99: astore 8
    //   101: aload 8
    //   103: invokevirtual 53	com/vvt/http/request/removeFromPath:removeFromPath	()Ljava/lang/String;
    //   106: astore 8
    //   108: invokestatic 22	com/vvt/http/a:MyUncaughtExceptionHandler	()Z
    //   111: istore 12
    //   113: iload 12
    //   115: ifeq +3 -> 118
    //   118: new 55	java/net/URL
    //   121: astore 11
    //   123: aload 11
    //   125: aload 8
    //   127: invokespecial 58	java/net/URL:<init>	(Ljava/lang/String;)V
    //   130: aload_0
    //   131: getfield 8	com/vvt/http/MyUncaughtExceptionHandler:a	Lcom/vvt/http/a;
    //   134: astore 7
    //   136: aload 11
    //   138: invokevirtual 62	java/net/URL:openConnection	()Ljava/net/URLConnection;
    //   141: astore 8
    //   143: aload 8
    //   145: checkcast 64	java/net/HttpURLConnection
    //   148: astore 8
    //   150: aload 7
    //   152: aload 8
    //   154: putfield 67	com/vvt/http/a:a	Ljava/net/HttpURLConnection;
    //   157: aload_0
    //   158: getfield 8	com/vvt/http/MyUncaughtExceptionHandler:a	Lcom/vvt/http/a;
    //   161: astore 8
    //   163: aload 8
    //   165: getfield 67	com/vvt/http/a:a	Ljava/net/HttpURLConnection;
    //   168: astore 8
    //   170: iconst_1
    //   171: istore 12
    //   173: aload 8
    //   175: iload 12
    //   177: invokevirtual 71	java/net/HttpURLConnection:setDoInput	(Z)V
    //   180: aload_0
    //   181: getfield 8	com/vvt/http/MyUncaughtExceptionHandler:a	Lcom/vvt/http/a;
    //   184: astore 8
    //   186: aload 8
    //   188: getfield 67	com/vvt/http/a:a	Ljava/net/HttpURLConnection;
    //   191: astore 8
    //   193: iconst_1
    //   194: istore 12
    //   196: aload 8
    //   198: iload 12
    //   200: invokevirtual 74	java/net/HttpURLConnection:setDoOutput	(Z)V
    //   203: aload_0
    //   204: getfield 8	com/vvt/http/MyUncaughtExceptionHandler:a	Lcom/vvt/http/a;
    //   207: astore 8
    //   209: aload 8
    //   211: getfield 67	com/vvt/http/a:a	Ljava/net/HttpURLConnection;
    //   214: astore 8
    //   216: iconst_0
    //   217: istore 12
    //   219: aconst_null
    //   220: astore 11
    //   222: aload 8
    //   224: iconst_0
    //   225: invokevirtual 77	java/net/HttpURLConnection:setUseCaches	(Z)V
    //   228: aload_0
    //   229: getfield 8	com/vvt/http/MyUncaughtExceptionHandler:a	Lcom/vvt/http/a;
    //   232: astore 8
    //   234: aload 8
    //   236: getfield 67	com/vvt/http/a:a	Ljava/net/HttpURLConnection;
    //   239: astore 8
    //   241: aload_0
    //   242: getfield 8	com/vvt/http/MyUncaughtExceptionHandler:a	Lcom/vvt/http/a;
    //   245: astore 11
    //   247: aload 11
    //   249: invokestatic 28	com/vvt/http/a:a	(Lcom/vvt/http/a;)Lcom/vvt/http/request/removeFromPath;
    //   252: astore 11
    //   254: aload 11
    //   256: invokevirtual 80	com/vvt/http/request/removeFromPath:MyUncaughtExceptionHandler	()Lcom/vvt/http/request/MethodType;
    //   259: astore 11
    //   261: aload 11
    //   263: invokevirtual 85	com/vvt/http/request/MethodType:toString	()Ljava/lang/String;
    //   266: astore 11
    //   268: aload 8
    //   270: aload 11
    //   272: invokevirtual 88	java/net/HttpURLConnection:setRequestMethod	(Ljava/lang/String;)V
    //   275: aload_0
    //   276: getfield 8	com/vvt/http/MyUncaughtExceptionHandler:a	Lcom/vvt/http/a;
    //   279: astore 8
    //   281: aload 8
    //   283: getfield 67	com/vvt/http/a:a	Ljava/net/HttpURLConnection;
    //   286: astore 8
    //   288: aload_0
    //   289: getfield 8	com/vvt/http/MyUncaughtExceptionHandler:a	Lcom/vvt/http/a;
    //   292: astore 11
    //   294: aload 11
    //   296: invokestatic 28	com/vvt/http/a:a	(Lcom/vvt/http/a;)Lcom/vvt/http/request/removeFromPath;
    //   299: astore 11
    //   301: aload 11
    //   303: invokevirtual 92	com/vvt/http/request/removeFromPath:e	()I
    //   306: istore 12
    //   308: aload 8
    //   310: iload 12
    //   312: invokevirtual 96	java/net/HttpURLConnection:setConnectTimeout	(I)V
    //   315: aload_0
    //   316: getfield 8	com/vvt/http/MyUncaughtExceptionHandler:a	Lcom/vvt/http/a;
    //   319: astore 8
    //   321: aload 8
    //   323: getfield 67	com/vvt/http/a:a	Ljava/net/HttpURLConnection;
    //   326: astore 8
    //   328: aload_0
    //   329: getfield 8	com/vvt/http/MyUncaughtExceptionHandler:a	Lcom/vvt/http/a;
    //   332: astore 11
    //   334: aload 11
    //   336: invokestatic 28	com/vvt/http/a:a	(Lcom/vvt/http/a;)Lcom/vvt/http/request/removeFromPath;
    //   339: astore 11
    //   341: aload 11
    //   343: invokevirtual 92	com/vvt/http/request/removeFromPath:e	()I
    //   346: istore 12
    //   348: aload 8
    //   350: iload 12
    //   352: invokevirtual 99	java/net/HttpURLConnection:setReadTimeout	(I)V
    //   355: aload_0
    //   356: getfield 8	com/vvt/http/MyUncaughtExceptionHandler:a	Lcom/vvt/http/a;
    //   359: astore 8
    //   361: aload 8
    //   363: getfield 67	com/vvt/http/a:a	Ljava/net/HttpURLConnection;
    //   366: astore 8
    //   368: ldc 101
    //   370: astore 11
    //   372: aload_0
    //   373: getfield 8	com/vvt/http/MyUncaughtExceptionHandler:a	Lcom/vvt/http/a;
    //   376: astore 7
    //   378: aload 7
    //   380: invokestatic 28	com/vvt/http/a:a	(Lcom/vvt/http/a;)Lcom/vvt/http/request/removeFromPath;
    //   383: astore 7
    //   385: aload 7
    //   387: invokevirtual 105	com/vvt/http/request/removeFromPath:d	()Lcom/vvt/http/request/ContentType;
    //   390: astore 7
    //   392: aload 7
    //   394: invokevirtual 110	com/vvt/http/request/ContentType:getContent	()Ljava/lang/String;
    //   397: astore 7
    //   399: aload 8
    //   401: aload 11
    //   403: aload 7
    //   405: invokevirtual 114	java/net/HttpURLConnection:setRequestProperty	(Ljava/lang/String;Ljava/lang/String;)V
    //   408: aload_0
    //   409: getfield 8	com/vvt/http/MyUncaughtExceptionHandler:a	Lcom/vvt/http/a;
    //   412: astore 8
    //   414: aload 8
    //   416: invokestatic 28	com/vvt/http/a:a	(Lcom/vvt/http/a;)Lcom/vvt/http/request/removeFromPath;
    //   419: astore 8
    //   421: aload 8
    //   423: invokevirtual 117	com/vvt/http/request/removeFromPath:FxFileObserverWorker	()Ljava/lang/String;
    //   426: astore 8
    //   428: aload 8
    //   430: ifnull +566 -> 996
    //   433: aload_0
    //   434: getfield 8	com/vvt/http/MyUncaughtExceptionHandler:a	Lcom/vvt/http/a;
    //   437: astore 11
    //   439: aload 11
    //   441: getfield 67	com/vvt/http/a:a	Ljava/net/HttpURLConnection;
    //   444: astore 11
    //   446: ldc 119
    //   448: astore 7
    //   450: aload 11
    //   452: aload 7
    //   454: aload 8
    //   456: invokevirtual 114	java/net/HttpURLConnection:setRequestProperty	(Ljava/lang/String;Ljava/lang/String;)V
    //   459: aload_0
    //   460: getfield 8	com/vvt/http/MyUncaughtExceptionHandler:a	Lcom/vvt/http/a;
    //   463: astore 8
    //   465: aload 8
    //   467: invokestatic 28	com/vvt/http/a:a	(Lcom/vvt/http/a;)Lcom/vvt/http/request/removeFromPath;
    //   470: astore 8
    //   472: aload 8
    //   474: invokevirtual 122	com/vvt/http/request/removeFromPath:i	()Ljava/lang/String;
    //   477: astore 8
    //   479: aload 8
    //   481: ifnull +640 -> 1121
    //   484: aload_0
    //   485: getfield 8	com/vvt/http/MyUncaughtExceptionHandler:a	Lcom/vvt/http/a;
    //   488: astore 8
    //   490: aload 8
    //   492: invokestatic 28	com/vvt/http/a:a	(Lcom/vvt/http/a;)Lcom/vvt/http/request/removeFromPath;
    //   495: astore 8
    //   497: aload 8
    //   499: invokevirtual 122	com/vvt/http/request/removeFromPath:i	()Ljava/lang/String;
    //   502: astore 8
    //   504: aload_0
    //   505: getfield 8	com/vvt/http/MyUncaughtExceptionHandler:a	Lcom/vvt/http/a;
    //   508: astore 11
    //   510: aload 11
    //   512: getfield 67	com/vvt/http/a:a	Ljava/net/HttpURLConnection;
    //   515: astore 11
    //   517: ldc 124
    //   519: astore 7
    //   521: aload 11
    //   523: aload 7
    //   525: aload 8
    //   527: invokevirtual 114	java/net/HttpURLConnection:setRequestProperty	(Ljava/lang/String;Ljava/lang/String;)V
    //   530: aload_0
    //   531: getfield 8	com/vvt/http/MyUncaughtExceptionHandler:a	Lcom/vvt/http/a;
    //   534: astore 8
    //   536: aload 8
    //   538: invokestatic 28	com/vvt/http/a:a	(Lcom/vvt/http/a;)Lcom/vvt/http/request/removeFromPath;
    //   541: astore 8
    //   543: aload 8
    //   545: invokevirtual 127	com/vvt/http/request/removeFromPath:j	()Ljava/lang/String;
    //   548: astore 8
    //   550: aload 8
    //   552: ifnull +576 -> 1128
    //   555: aload_0
    //   556: getfield 8	com/vvt/http/MyUncaughtExceptionHandler:a	Lcom/vvt/http/a;
    //   559: astore 8
    //   561: aload 8
    //   563: invokestatic 28	com/vvt/http/a:a	(Lcom/vvt/http/a;)Lcom/vvt/http/request/removeFromPath;
    //   566: astore 8
    //   568: aload 8
    //   570: invokevirtual 127	com/vvt/http/request/removeFromPath:j	()Ljava/lang/String;
    //   573: astore 8
    //   575: aload_0
    //   576: getfield 8	com/vvt/http/MyUncaughtExceptionHandler:a	Lcom/vvt/http/a;
    //   579: astore 11
    //   581: aload 11
    //   583: getfield 67	com/vvt/http/a:a	Ljava/net/HttpURLConnection;
    //   586: astore 11
    //   588: ldc -127
    //   590: astore 7
    //   592: aload 11
    //   594: aload 7
    //   596: aload 8
    //   598: invokevirtual 114	java/net/HttpURLConnection:setRequestProperty	(Ljava/lang/String;Ljava/lang/String;)V
    //   601: aload_0
    //   602: getfield 8	com/vvt/http/MyUncaughtExceptionHandler:a	Lcom/vvt/http/a;
    //   605: astore 8
    //   607: aload 8
    //   609: invokestatic 28	com/vvt/http/a:a	(Lcom/vvt/http/a;)Lcom/vvt/http/request/removeFromPath;
    //   612: astore 8
    //   614: aload 8
    //   616: invokevirtual 132	com/vvt/http/request/removeFromPath:AppEngine1	()Ljava/lang/String;
    //   619: astore 8
    //   621: aload 8
    //   623: ifnull +25 -> 648
    //   626: invokestatic 22	com/vvt/http/a:MyUncaughtExceptionHandler	()Z
    //   629: istore 12
    //   631: iload 12
    //   633: ifeq +3 -> 636
    //   636: ldc -122
    //   638: astore 11
    //   640: aload 11
    //   642: aload 8
    //   644: invokestatic 49	java/lang/System:setProperty	(Ljava/lang/String;Ljava/lang/String;)Ljava/lang/String;
    //   647: pop
    //   648: aload_0
    //   649: getfield 8	com/vvt/http/MyUncaughtExceptionHandler:a	Lcom/vvt/http/a;
    //   652: astore 8
    //   654: aload 8
    //   656: getfield 67	com/vvt/http/a:a	Ljava/net/HttpURLConnection;
    //   659: astore 8
    //   661: ldc -120
    //   663: astore 11
    //   665: lload 9
    //   667: invokestatic 141	java/lang/Long:toString	(J)Ljava/lang/String;
    //   670: astore 7
    //   672: aload 8
    //   674: aload 11
    //   676: aload 7
    //   678: invokevirtual 114	java/net/HttpURLConnection:setRequestProperty	(Ljava/lang/String;Ljava/lang/String;)V
    //   681: aload_0
    //   682: getfield 8	com/vvt/http/MyUncaughtExceptionHandler:a	Lcom/vvt/http/a;
    //   685: astore 8
    //   687: aload 8
    //   689: getfield 67	com/vvt/http/a:a	Ljava/net/HttpURLConnection;
    //   692: astore 8
    //   694: lload 9
    //   696: l2i
    //   697: istore 12
    //   699: aload 8
    //   701: iload 12
    //   703: invokevirtual 144	java/net/HttpURLConnection:setFixedLengthStreamingMode	(I)V
    //   706: aload_0
    //   707: getfield 8	com/vvt/http/MyUncaughtExceptionHandler:a	Lcom/vvt/http/a;
    //   710: astore 8
    //   712: aload_0
    //   713: getfield 8	com/vvt/http/MyUncaughtExceptionHandler:a	Lcom/vvt/http/a;
    //   716: astore 11
    //   718: aload 11
    //   720: invokestatic 28	com/vvt/http/a:a	(Lcom/vvt/http/a;)Lcom/vvt/http/request/removeFromPath;
    //   723: astore 11
    //   725: aload 8
    //   727: aload 11
    //   729: invokestatic 147	com/vvt/http/a:a	(Lcom/vvt/http/a;Lcom/vvt/http/request/removeFromPath;)V
    //   732: invokestatic 22	com/vvt/http/a:MyUncaughtExceptionHandler	()Z
    //   735: istore_3
    //   736: iload_3
    //   737: ifeq +3 -> 740
    //   740: invokestatic 22	com/vvt/http/a:MyUncaughtExceptionHandler	()Z
    //   743: istore_3
    //   744: iload_3
    //   745: ifeq +3 -> 748
    //   748: aload_0
    //   749: getfield 8	com/vvt/http/MyUncaughtExceptionHandler:a	Lcom/vvt/http/a;
    //   752: astore 8
    //   754: aload 8
    //   756: getfield 67	com/vvt/http/a:a	Ljava/net/HttpURLConnection;
    //   759: astore 8
    //   761: aload 8
    //   763: invokevirtual 150	java/net/HttpURLConnection:connect	()V
    //   766: aload_0
    //   767: getfield 8	com/vvt/http/MyUncaughtExceptionHandler:a	Lcom/vvt/http/a;
    //   770: astore 8
    //   772: aload 8
    //   774: invokestatic 28	com/vvt/http/a:a	(Lcom/vvt/http/a;)Lcom/vvt/http/request/removeFromPath;
    //   777: astore 8
    //   779: aload 8
    //   781: invokevirtual 80	com/vvt/http/request/removeFromPath:MyUncaughtExceptionHandler	()Lcom/vvt/http/request/MethodType;
    //   784: astore 8
    //   786: getstatic 154	com/vvt/http/request/MethodType:POST	Lcom/vvt/http/request/MethodType;
    //   789: astore 11
    //   791: aload 8
    //   793: aload 11
    //   795: if_acmpne +353 -> 1148
    //   798: sipush 10240
    //   801: istore_3
    //   802: iload_3
    //   803: newarray <illegal type>
    //   805: astore 13
    //   807: lconst_0
    //   808: lstore 14
    //   810: aload 4
    //   812: aload 13
    //   814: invokevirtual 158	com/vvt/http/request/a:a	([B)I
    //   817: istore_3
    //   818: new 160	java/io/DataOutputStream
    //   821: astore 16
    //   823: aload_0
    //   824: getfield 8	com/vvt/http/MyUncaughtExceptionHandler:a	Lcom/vvt/http/a;
    //   827: astore 17
    //   829: aload 17
    //   831: getfield 67	com/vvt/http/a:a	Ljava/net/HttpURLConnection;
    //   834: astore 17
    //   836: aload 17
    //   838: invokevirtual 164	java/net/HttpURLConnection:getOutputStream	()Ljava/io/OutputStream;
    //   841: astore 17
    //   843: aload 16
    //   845: aload 17
    //   847: invokespecial 167	java/io/DataOutputStream:<init>	(Ljava/io/OutputStream;)V
    //   850: iload_3
    //   851: iload_1
    //   852: if_icmpeq +283 -> 1135
    //   855: new 169	com/vvt/http/a/removeFromPath
    //   858: astore 17
    //   860: aload 17
    //   862: invokespecial 170	com/vvt/http/a/removeFromPath:<init>	()V
    //   865: aload 17
    //   867: lload 9
    //   869: invokevirtual 173	com/vvt/http/a/removeFromPath:a	(J)V
    //   872: iconst_0
    //   873: istore 18
    //   875: aconst_null
    //   876: astore 19
    //   878: aload 16
    //   880: aload 13
    //   882: iconst_0
    //   883: iload_3
    //   884: invokevirtual 177	java/io/DataOutputStream:write	([BII)V
    //   887: aload 16
    //   889: invokevirtual 180	java/io/DataOutputStream:flush	()V
    //   892: iload_3
    //   893: i2l
    //   894: lstore 20
    //   896: lload 14
    //   898: lload 20
    //   900: ladd
    //   901: lstore 14
    //   903: aload 17
    //   905: lload 14
    //   907: invokevirtual 182	com/vvt/http/a/removeFromPath:removeFromPath	(J)V
    //   910: invokestatic 22	com/vvt/http/a:MyUncaughtExceptionHandler	()Z
    //   913: istore_3
    //   914: iload_3
    //   915: ifeq +3 -> 918
    //   918: aload_0
    //   919: getfield 8	com/vvt/http/MyUncaughtExceptionHandler:a	Lcom/vvt/http/a;
    //   922: astore 8
    //   924: aload 8
    //   926: invokestatic 185	com/vvt/http/a:removeFromPath	(Lcom/vvt/http/a;)Lcom/vvt/http/d;
    //   929: astore 8
    //   931: aload 8
    //   933: ifnull +52 -> 985
    //   936: aload_0
    //   937: getfield 8	com/vvt/http/MyUncaughtExceptionHandler:a	Lcom/vvt/http/a;
    //   940: astore 8
    //   942: aload_0
    //   943: getfield 8	com/vvt/http/MyUncaughtExceptionHandler:a	Lcom/vvt/http/a;
    //   946: astore 19
    //   948: aload 19
    //   950: invokestatic 185	com/vvt/http/a:removeFromPath	(Lcom/vvt/http/a;)Lcom/vvt/http/d;
    //   953: astore 19
    //   955: iconst_4
    //   956: istore 22
    //   958: iconst_1
    //   959: istore 23
    //   961: iload 23
    //   963: anewarray 188	java/lang/Object
    //   966: astore 24
    //   968: aload 24
    //   970: iconst_0
    //   971: aload 17
    //   973: aastore
    //   974: aload 8
    //   976: aload 19
    //   978: iload 22
    //   980: aload 24
    //   982: invokestatic 191	com/vvt/http/a:removeFromPath	(Lcom/vvt/http/a;Ljava/lang/Object;I[Ljava/lang/Object;)V
    //   985: aload 4
    //   987: aload 13
    //   989: invokevirtual 158	com/vvt/http/request/a:a	([B)I
    //   992: istore_3
    //   993: goto -143 -> 850
    //   996: aload_0
    //   997: getfield 8	com/vvt/http/MyUncaughtExceptionHandler:a	Lcom/vvt/http/a;
    //   1000: astore 8
    //   1002: aload 8
    //   1004: getfield 67	com/vvt/http/a:a	Ljava/net/HttpURLConnection;
    //   1007: astore 8
    //   1009: ldc 119
    //   1011: astore 11
    //   1013: ldc -63
    //   1015: astore 7
    //   1017: aload 8
    //   1019: aload 11
    //   1021: aload 7
    //   1023: invokevirtual 114	java/net/HttpURLConnection:setRequestProperty	(Ljava/lang/String;Ljava/lang/String;)V
    //   1026: goto -567 -> 459
    //   1029: astore 8
    //   1031: aload_0
    //   1032: getfield 8	com/vvt/http/MyUncaughtExceptionHandler:a	Lcom/vvt/http/a;
    //   1035: getfield 67	com/vvt/http/a:a	Ljava/net/HttpURLConnection;
    //   1038: invokevirtual 196	java/net/HttpURLConnection:disconnect	()V
    //   1041: aload_0
    //   1042: getfield 8	com/vvt/http/MyUncaughtExceptionHandler:a	Lcom/vvt/http/a;
    //   1045: invokestatic 185	com/vvt/http/a:removeFromPath	(Lcom/vvt/http/a;)Lcom/vvt/http/d;
    //   1048: astore 11
    //   1050: aload 11
    //   1052: ifnull +48 -> 1100
    //   1055: aload_0
    //   1056: getfield 8	com/vvt/http/MyUncaughtExceptionHandler:a	Lcom/vvt/http/a;
    //   1059: astore 11
    //   1061: aload_0
    //   1062: getfield 8	com/vvt/http/MyUncaughtExceptionHandler:a	Lcom/vvt/http/a;
    //   1065: invokestatic 185	com/vvt/http/a:removeFromPath	(Lcom/vvt/http/a;)Lcom/vvt/http/d;
    //   1068: astore 7
    //   1070: iload_2
    //   1071: anewarray 188	java/lang/Object
    //   1074: astore 25
    //   1076: aload 25
    //   1078: iconst_0
    //   1079: aload 8
    //   1081: aastore
    //   1082: aload 11
    //   1084: aload 7
    //   1086: iload_2
    //   1087: aload 25
    //   1089: invokestatic 198	com/vvt/http/a:a	(Lcom/vvt/http/a;Ljava/lang/Object;I[Ljava/lang/Object;)V
    //   1092: invokestatic 200	com/vvt/http/a:d	()Z
    //   1095: istore_3
    //   1096: iload_3
    //   1097: ifeq +3 -> 1100
    //   1100: aload_0
    //   1101: getfield 8	com/vvt/http/MyUncaughtExceptionHandler:a	Lcom/vvt/http/a;
    //   1104: invokestatic 202	com/vvt/http/a:MyUncaughtExceptionHandler	(Lcom/vvt/http/a;)V
    //   1107: aload_0
    //   1108: getfield 8	com/vvt/http/MyUncaughtExceptionHandler:a	Lcom/vvt/http/a;
    //   1111: astore 8
    //   1113: aload 8
    //   1115: iconst_0
    //   1116: invokestatic 205	com/vvt/http/a:a	(Lcom/vvt/http/a;Z)Z
    //   1119: pop
    //   1120: return
    //   1121: ldc -63
    //   1123: astore 8
    //   1125: goto -621 -> 504
    //   1128: ldc -63
    //   1130: astore 8
    //   1132: goto -557 -> 575
    //   1135: invokestatic 22	com/vvt/http/a:MyUncaughtExceptionHandler	()Z
    //   1138: istore_3
    //   1139: iload_3
    //   1140: ifeq +3 -> 1143
    //   1143: aload 16
    //   1145: invokevirtual 208	java/io/DataOutputStream:close	()V
    //   1148: ldc2_w 209
    //   1151: lstore 5
    //   1153: lload 5
    //   1155: invokestatic 217	android/os/SystemClock:sleep	(J)V
    //   1158: invokestatic 22	com/vvt/http/a:MyUncaughtExceptionHandler	()Z
    //   1161: istore_3
    //   1162: iload_3
    //   1163: ifeq +3 -> 1166
    //   1166: aload_0
    //   1167: getfield 8	com/vvt/http/MyUncaughtExceptionHandler:a	Lcom/vvt/http/a;
    //   1170: astore 8
    //   1172: aload 8
    //   1174: getfield 67	com/vvt/http/a:a	Ljava/net/HttpURLConnection;
    //   1177: astore 8
    //   1179: aload 8
    //   1181: invokevirtual 220	java/net/HttpURLConnection:getResponseCode	()I
    //   1184: istore 12
    //   1186: aload_0
    //   1187: getfield 8	com/vvt/http/MyUncaughtExceptionHandler:a	Lcom/vvt/http/a;
    //   1190: astore 8
    //   1192: aload 8
    //   1194: getfield 67	com/vvt/http/a:a	Ljava/net/HttpURLConnection;
    //   1197: astore 8
    //   1199: aload 8
    //   1201: invokevirtual 223	java/net/HttpURLConnection:getContentType	()Ljava/lang/String;
    //   1204: astore 8
    //   1206: aload 8
    //   1208: invokestatic 227	com/vvt/http/request/ContentType:forValue	(Ljava/lang/String;)Lcom/vvt/http/request/ContentType;
    //   1211: astore 7
    //   1213: aload_0
    //   1214: getfield 8	com/vvt/http/MyUncaughtExceptionHandler:a	Lcom/vvt/http/a;
    //   1217: astore 8
    //   1219: aload 8
    //   1221: getfield 67	com/vvt/http/a:a	Ljava/net/HttpURLConnection;
    //   1224: astore 8
    //   1226: aload 8
    //   1228: invokevirtual 231	java/net/HttpURLConnection:getHeaderFields	()Ljava/util/Map;
    //   1231: astore 25
    //   1233: sipush 200
    //   1236: istore_3
    //   1237: iload 12
    //   1239: iload_3
    //   1240: if_icmpne +428 -> 1668
    //   1243: sipush 10240
    //   1246: istore_3
    //   1247: iload_3
    //   1248: newarray <illegal type>
    //   1250: astore 26
    //   1252: aload_0
    //   1253: getfield 8	com/vvt/http/MyUncaughtExceptionHandler:a	Lcom/vvt/http/a;
    //   1256: astore 8
    //   1258: aload 8
    //   1260: getfield 67	com/vvt/http/a:a	Ljava/net/HttpURLConnection;
    //   1263: astore 8
    //   1265: aload 8
    //   1267: invokevirtual 236	java/net/HttpURLConnection:getInputStream	()Ljava/io/InputStream;
    //   1270: astore 4
    //   1272: aload 4
    //   1274: aload 26
    //   1276: invokevirtual 241	java/io/InputStream:read	([B)I
    //   1279: istore_3
    //   1280: iload_3
    //   1281: iload_1
    //   1282: if_icmpeq +185 -> 1467
    //   1285: iload_3
    //   1286: newarray <illegal type>
    //   1288: astore 13
    //   1290: aconst_null
    //   1291: astore 16
    //   1293: iconst_0
    //   1294: istore 27
    //   1296: aconst_null
    //   1297: astore 17
    //   1299: aload 26
    //   1301: iconst_0
    //   1302: aload 13
    //   1304: iconst_0
    //   1305: iload_3
    //   1306: invokestatic 245	java/lang/System:arraycopy	(Ljava/lang/Object;ILjava/lang/Object;II)V
    //   1309: invokestatic 22	com/vvt/http/a:MyUncaughtExceptionHandler	()Z
    //   1312: istore_3
    //   1313: iload_3
    //   1314: ifeq +3 -> 1317
    //   1317: new 247	com/vvt/http/a/a
    //   1320: astore 8
    //   1322: aload 8
    //   1324: invokespecial 248	com/vvt/http/a/a:<init>	()V
    //   1327: aload_0
    //   1328: getfield 8	com/vvt/http/MyUncaughtExceptionHandler:a	Lcom/vvt/http/a;
    //   1331: astore 16
    //   1333: aload 16
    //   1335: invokestatic 28	com/vvt/http/a:a	(Lcom/vvt/http/a;)Lcom/vvt/http/request/removeFromPath;
    //   1338: astore 16
    //   1340: aload 8
    //   1342: aload 16
    //   1344: invokevirtual 251	com/vvt/http/a/a:a	(Lcom/vvt/http/request/removeFromPath;)V
    //   1347: aload 8
    //   1349: iload 12
    //   1351: invokevirtual 253	com/vvt/http/a/a:a	(I)V
    //   1354: aload 8
    //   1356: aload 7
    //   1358: invokevirtual 256	com/vvt/http/a/a:a	(Lcom/vvt/http/request/ContentType;)V
    //   1361: aload 8
    //   1363: aload 25
    //   1365: invokevirtual 259	com/vvt/http/a/a:a	(Ljava/util/Map;)V
    //   1368: aload 8
    //   1370: aload 13
    //   1372: invokevirtual 262	com/vvt/http/a/a:a	([B)V
    //   1375: iconst_0
    //   1376: istore_2
    //   1377: aconst_null
    //   1378: astore 13
    //   1380: aload 8
    //   1382: iconst_0
    //   1383: invokevirtual 264	com/vvt/http/a/a:a	(Z)V
    //   1386: aload_0
    //   1387: getfield 8	com/vvt/http/MyUncaughtExceptionHandler:a	Lcom/vvt/http/a;
    //   1390: astore 13
    //   1392: aload 13
    //   1394: invokestatic 185	com/vvt/http/a:removeFromPath	(Lcom/vvt/http/a;)Lcom/vvt/http/d;
    //   1397: astore 13
    //   1399: aload 13
    //   1401: ifnull +55 -> 1456
    //   1404: aload_0
    //   1405: getfield 8	com/vvt/http/MyUncaughtExceptionHandler:a	Lcom/vvt/http/a;
    //   1408: astore 13
    //   1410: aload_0
    //   1411: getfield 8	com/vvt/http/MyUncaughtExceptionHandler:a	Lcom/vvt/http/a;
    //   1414: astore 16
    //   1416: aload 16
    //   1418: invokestatic 185	com/vvt/http/a:removeFromPath	(Lcom/vvt/http/a;)Lcom/vvt/http/d;
    //   1421: astore 16
    //   1423: iconst_5
    //   1424: istore 27
    //   1426: iconst_1
    //   1427: istore 18
    //   1429: iload 18
    //   1431: anewarray 188	java/lang/Object
    //   1434: astore 19
    //   1436: iconst_0
    //   1437: istore 22
    //   1439: aload 19
    //   1441: iconst_0
    //   1442: aload 8
    //   1444: aastore
    //   1445: aload 13
    //   1447: aload 16
    //   1449: iload 27
    //   1451: aload 19
    //   1453: invokestatic 267	com/vvt/http/a:MyUncaughtExceptionHandler	(Lcom/vvt/http/a;Ljava/lang/Object;I[Ljava/lang/Object;)V
    //   1456: aload 4
    //   1458: aload 26
    //   1460: invokevirtual 241	java/io/InputStream:read	([B)I
    //   1463: istore_3
    //   1464: goto -184 -> 1280
    //   1467: aload 4
    //   1469: invokevirtual 268	java/io/InputStream:close	()V
    //   1472: new 247	com/vvt/http/a/a
    //   1475: astore 8
    //   1477: aload 8
    //   1479: invokespecial 248	com/vvt/http/a/a:<init>	()V
    //   1482: aload_0
    //   1483: getfield 8	com/vvt/http/MyUncaughtExceptionHandler:a	Lcom/vvt/http/a;
    //   1486: astore 26
    //   1488: aload 26
    //   1490: invokestatic 28	com/vvt/http/a:a	(Lcom/vvt/http/a;)Lcom/vvt/http/request/removeFromPath;
    //   1493: astore 26
    //   1495: aload 8
    //   1497: aload 26
    //   1499: invokevirtual 251	com/vvt/http/a/a:a	(Lcom/vvt/http/request/removeFromPath;)V
    //   1502: aload 8
    //   1504: iload 12
    //   1506: invokevirtual 253	com/vvt/http/a/a:a	(I)V
    //   1509: aload 8
    //   1511: aload 7
    //   1513: invokevirtual 256	com/vvt/http/a/a:a	(Lcom/vvt/http/request/ContentType;)V
    //   1516: aload 8
    //   1518: aload 25
    //   1520: invokevirtual 259	com/vvt/http/a/a:a	(Ljava/util/Map;)V
    //   1523: iconst_0
    //   1524: istore 12
    //   1526: aconst_null
    //   1527: astore 11
    //   1529: iconst_0
    //   1530: newarray <illegal type>
    //   1532: astore 11
    //   1534: aload 8
    //   1536: aload 11
    //   1538: invokevirtual 262	com/vvt/http/a/a:a	([B)V
    //   1541: iconst_1
    //   1542: istore 12
    //   1544: aload 8
    //   1546: iload 12
    //   1548: invokevirtual 264	com/vvt/http/a/a:a	(Z)V
    //   1551: invokestatic 22	com/vvt/http/a:MyUncaughtExceptionHandler	()Z
    //   1554: istore 12
    //   1556: iload 12
    //   1558: ifeq +3 -> 1561
    //   1561: aload_0
    //   1562: getfield 8	com/vvt/http/MyUncaughtExceptionHandler:a	Lcom/vvt/http/a;
    //   1565: astore 11
    //   1567: aload 11
    //   1569: invokestatic 185	com/vvt/http/a:removeFromPath	(Lcom/vvt/http/a;)Lcom/vvt/http/d;
    //   1572: astore 11
    //   1574: aload 11
    //   1576: ifnull +59 -> 1635
    //   1579: aload_0
    //   1580: getfield 8	com/vvt/http/MyUncaughtExceptionHandler:a	Lcom/vvt/http/a;
    //   1583: astore 11
    //   1585: aload_0
    //   1586: getfield 8	com/vvt/http/MyUncaughtExceptionHandler:a	Lcom/vvt/http/a;
    //   1589: astore 7
    //   1591: aload 7
    //   1593: invokestatic 185	com/vvt/http/a:removeFromPath	(Lcom/vvt/http/a;)Lcom/vvt/http/d;
    //   1596: astore 7
    //   1598: bipush 6
    //   1600: istore 28
    //   1602: iconst_1
    //   1603: istore 29
    //   1605: iload 29
    //   1607: anewarray 188	java/lang/Object
    //   1610: astore 26
    //   1612: iconst_0
    //   1613: istore 30
    //   1615: aconst_null
    //   1616: astore 4
    //   1618: aload 26
    //   1620: iconst_0
    //   1621: aload 8
    //   1623: aastore
    //   1624: aload 11
    //   1626: aload 7
    //   1628: iload 28
    //   1630: aload 26
    //   1632: invokestatic 271	com/vvt/http/a:d	(Lcom/vvt/http/a;Ljava/lang/Object;I[Ljava/lang/Object;)V
    //   1635: aload_0
    //   1636: getfield 8	com/vvt/http/MyUncaughtExceptionHandler:a	Lcom/vvt/http/a;
    //   1639: getfield 67	com/vvt/http/a:a	Ljava/net/HttpURLConnection;
    //   1642: invokevirtual 196	java/net/HttpURLConnection:disconnect	()V
    //   1645: aload_0
    //   1646: getfield 8	com/vvt/http/MyUncaughtExceptionHandler:a	Lcom/vvt/http/a;
    //   1649: invokestatic 202	com/vvt/http/a:MyUncaughtExceptionHandler	(Lcom/vvt/http/a;)V
    //   1652: aload_0
    //   1653: getfield 8	com/vvt/http/MyUncaughtExceptionHandler:a	Lcom/vvt/http/a;
    //   1656: astore 8
    //   1658: aload 8
    //   1660: iconst_0
    //   1661: invokestatic 205	com/vvt/http/a:a	(Lcom/vvt/http/a;Z)Z
    //   1664: pop
    //   1665: goto -545 -> 1120
    //   1668: invokestatic 273	com/vvt/http/a:e	()Z
    //   1671: istore_3
    //   1672: iload_3
    //   1673: ifeq +3 -> 1676
    //   1676: aload_0
    //   1677: getfield 8	com/vvt/http/MyUncaughtExceptionHandler:a	Lcom/vvt/http/a;
    //   1680: astore 8
    //   1682: aload 8
    //   1684: getfield 67	com/vvt/http/a:a	Ljava/net/HttpURLConnection;
    //   1687: astore 8
    //   1689: aload 8
    //   1691: invokevirtual 276	java/net/HttpURLConnection:getResponseMessage	()Ljava/lang/String;
    //   1694: astore 8
    //   1696: aload 8
    //   1698: ifnonnull +8 -> 1706
    //   1701: ldc_w 278
    //   1704: astore 8
    //   1706: aload_0
    //   1707: getfield 8	com/vvt/http/MyUncaughtExceptionHandler:a	Lcom/vvt/http/a;
    //   1710: astore 7
    //   1712: aload_0
    //   1713: getfield 8	com/vvt/http/MyUncaughtExceptionHandler:a	Lcom/vvt/http/a;
    //   1716: astore 25
    //   1718: aload 25
    //   1720: invokestatic 185	com/vvt/http/a:removeFromPath	(Lcom/vvt/http/a;)Lcom/vvt/http/d;
    //   1723: astore 25
    //   1725: iconst_3
    //   1726: istore 29
    //   1728: iconst_2
    //   1729: istore 30
    //   1731: iload 30
    //   1733: anewarray 188	java/lang/Object
    //   1736: astore 4
    //   1738: iconst_0
    //   1739: istore_2
    //   1740: aconst_null
    //   1741: astore 13
    //   1743: iload 12
    //   1745: invokestatic 286	java/lang/Integer:valueOf	(I)Ljava/lang/Integer;
    //   1748: astore 11
    //   1750: aload 4
    //   1752: iconst_0
    //   1753: aload 11
    //   1755: aastore
    //   1756: iconst_1
    //   1757: istore 12
    //   1759: new 288	java/lang/Exception
    //   1762: astore 13
    //   1764: aload 13
    //   1766: aload 8
    //   1768: invokespecial 289	java/lang/Exception:<init>	(Ljava/lang/String;)V
    //   1771: aload 4
    //   1773: iload 12
    //   1775: aload 13
    //   1777: aastore
    //   1778: aload 7
    //   1780: aload 25
    //   1782: iload 29
    //   1784: aload 4
    //   1786: invokestatic 291	com/vvt/http/a:e	(Lcom/vvt/http/a;Ljava/lang/Object;I[Ljava/lang/Object;)V
    //   1789: invokestatic 200	com/vvt/http/a:d	()Z
    //   1792: istore_3
    //   1793: iload_3
    //   1794: ifeq -159 -> 1635
    //   1797: aload_0
    //   1798: getfield 8	com/vvt/http/MyUncaughtExceptionHandler:a	Lcom/vvt/http/a;
    //   1801: astore 8
    //   1803: aload 8
    //   1805: getfield 67	com/vvt/http/a:a	Ljava/net/HttpURLConnection;
    //   1808: astore 8
    //   1810: aload 8
    //   1812: invokevirtual 294	java/net/HttpURLConnection:getErrorStream	()Ljava/io/InputStream;
    //   1815: astore 11
    //   1817: aload 11
    //   1819: ifnull -184 -> 1635
    //   1822: new 296	java/io/BufferedReader
    //   1825: astore 7
    //   1827: new 298	java/io/InputStreamReader
    //   1830: astore 8
    //   1832: aload 8
    //   1834: aload 11
    //   1836: invokespecial 301	java/io/InputStreamReader:<init>	(Ljava/io/InputStream;)V
    //   1839: aload 7
    //   1841: aload 8
    //   1843: invokespecial 304	java/io/BufferedReader:<init>	(Ljava/io/Reader;)V
    //   1846: new 306	java/lang/StringBuffer
    //   1849: astore 25
    //   1851: aload 25
    //   1853: invokespecial 307	java/lang/StringBuffer:<init>	()V
    //   1856: aload 7
    //   1858: invokevirtual 310	java/io/BufferedReader:readLine	()Ljava/lang/String;
    //   1861: astore 8
    //   1863: aload 8
    //   1865: ifnull +21 -> 1886
    //   1868: aload 25
    //   1870: aload 8
    //   1872: invokevirtual 314	java/lang/StringBuffer:append	(Ljava/lang/String;)Ljava/lang/StringBuffer;
    //   1875: pop
    //   1876: aload 7
    //   1878: invokevirtual 310	java/io/BufferedReader:readLine	()Ljava/lang/String;
    //   1881: astore 8
    //   1883: goto -20 -> 1863
    //   1886: aload 7
    //   1888: invokestatic 319	com/vvt/io/d:a	(Ljava/io/BufferedReader;)V
    //   1891: aload 11
    //   1893: invokestatic 321	com/vvt/io/d:a	(Ljava/io/InputStream;)V
    //   1896: goto -261 -> 1635
    //   1899: astore 8
    //   1901: aload_0
    //   1902: getfield 8	com/vvt/http/MyUncaughtExceptionHandler:a	Lcom/vvt/http/a;
    //   1905: astore 11
    //   1907: aload 11
    //   1909: invokestatic 185	com/vvt/http/a:removeFromPath	(Lcom/vvt/http/a;)Lcom/vvt/http/d;
    //   1912: astore 11
    //   1914: aload 11
    //   1916: ifnull +66 -> 1982
    //   1919: aload_0
    //   1920: getfield 8	com/vvt/http/MyUncaughtExceptionHandler:a	Lcom/vvt/http/a;
    //   1923: astore 11
    //   1925: aload_0
    //   1926: getfield 8	com/vvt/http/MyUncaughtExceptionHandler:a	Lcom/vvt/http/a;
    //   1929: astore 7
    //   1931: aload 7
    //   1933: invokestatic 185	com/vvt/http/a:removeFromPath	(Lcom/vvt/http/a;)Lcom/vvt/http/d;
    //   1936: astore 7
    //   1938: iconst_2
    //   1939: istore 28
    //   1941: iconst_1
    //   1942: istore 29
    //   1944: iload 29
    //   1946: anewarray 188	java/lang/Object
    //   1949: astore 26
    //   1951: iconst_0
    //   1952: istore 30
    //   1954: aconst_null
    //   1955: astore 4
    //   1957: aload 26
    //   1959: iconst_0
    //   1960: aload 8
    //   1962: aastore
    //   1963: aload 11
    //   1965: aload 7
    //   1967: iload 28
    //   1969: aload 26
    //   1971: invokestatic 324	com/vvt/http/a:f	(Lcom/vvt/http/a;Ljava/lang/Object;I[Ljava/lang/Object;)V
    //   1974: invokestatic 200	com/vvt/http/a:d	()Z
    //   1977: istore_3
    //   1978: iload_3
    //   1979: ifeq +3 -> 1982
    //   1982: aload_0
    //   1983: getfield 8	com/vvt/http/MyUncaughtExceptionHandler:a	Lcom/vvt/http/a;
    //   1986: getfield 67	com/vvt/http/a:a	Ljava/net/HttpURLConnection;
    //   1989: invokevirtual 196	java/net/HttpURLConnection:disconnect	()V
    //   1992: aload_0
    //   1993: getfield 8	com/vvt/http/MyUncaughtExceptionHandler:a	Lcom/vvt/http/a;
    //   1996: invokestatic 202	com/vvt/http/a:MyUncaughtExceptionHandler	(Lcom/vvt/http/a;)V
    //   1999: aload_0
    //   2000: getfield 8	com/vvt/http/MyUncaughtExceptionHandler:a	Lcom/vvt/http/a;
    //   2003: astore 8
    //   2005: goto -347 -> 1658
    //   2008: astore 8
    //   2010: aload_0
    //   2011: getfield 8	com/vvt/http/MyUncaughtExceptionHandler:a	Lcom/vvt/http/a;
    //   2014: getfield 67	com/vvt/http/a:a	Ljava/net/HttpURLConnection;
    //   2017: invokevirtual 196	java/net/HttpURLConnection:disconnect	()V
    //   2020: aload_0
    //   2021: getfield 8	com/vvt/http/MyUncaughtExceptionHandler:a	Lcom/vvt/http/a;
    //   2024: invokestatic 202	com/vvt/http/a:MyUncaughtExceptionHandler	(Lcom/vvt/http/a;)V
    //   2027: aload_0
    //   2028: getfield 8	com/vvt/http/MyUncaughtExceptionHandler:a	Lcom/vvt/http/a;
    //   2031: iconst_0
    //   2032: invokestatic 205	com/vvt/http/a:a	(Lcom/vvt/http/a;Z)Z
    //   2035: pop
    //   2036: aload 8
    //   2038: athrow
    //   2039: lload 5
    //   2041: lstore 9
    //   2043: goto -1971 -> 72
    // Local variable table:
    //   start	length	slot	name	signature
    //   0	2046	0	this	MyUncaughtExceptionHandler
    //   1	1282	1	i	int
    //   3	1737	2	j	int
    //   7	738	3	bool1	boolean
    //   801	92	3	k	int
    //   913	2	3	bool2	boolean
    //   992	1	3	m	int
    //   1095	68	3	bool3	boolean
    //   1236	70	3	n	int
    //   1312	2	3	bool4	boolean
    //   1463	1	3	i1	int
    //   1671	308	3	bool5	boolean
    //   15	1941	4	localObject1	Object
    //   23	2017	5	l1	long
    //   35	1931	7	localObject2	Object
    //   52	966	8	localObject3	Object
    //   1029	51	8	localObject4	Object
    //   1111	771	8	localObject5	Object
    //   1899	62	8	localObject6	Object
    //   2003	1	8	locala	a
    //   2008	29	8	localObject7	Object
    //   70	1972	9	l2	long
    //   78	1886	11	localObject8	Object
    //   111	107	12	bool6	boolean
    //   306	45	12	i2	int
    //   629	3	12	bool7	boolean
    //   697	850	12	i3	int
    //   1554	190	12	i4	int
    //   1757	17	12	i5	int
    //   805	971	13	localObject9	Object
    //   808	98	14	l3	long
    //   821	627	16	localObject10	Object
    //   827	471	17	localObject11	Object
    //   873	557	18	i6	int
    //   876	576	19	localObject12	Object
    //   894	5	20	l4	long
    //   956	482	22	i7	int
    //   959	3	23	i8	int
    //   966	15	24	arrayOfObject	Object[]
    //   1074	795	25	localObject13	Object
    //   1250	720	26	localObject14	Object
    //   1294	156	27	i9	int
    //   1600	368	28	i10	int
    //   1603	342	29	i11	int
    //   1613	340	30	i12	int
    // Exception table:
    //   from	to	target	type
    //   82	88	1029	finally
    //   88	92	1029	finally
    //   94	99	1029	finally
    //   101	106	1029	finally
    //   108	111	1029	finally
    //   118	121	1029	finally
    //   125	130	1029	finally
    //   130	134	1029	finally
    //   136	141	1029	finally
    //   143	148	1029	finally
    //   152	157	1029	finally
    //   157	161	1029	finally
    //   163	168	1029	finally
    //   175	180	1029	finally
    //   180	184	1029	finally
    //   186	191	1029	finally
    //   198	203	1029	finally
    //   203	207	1029	finally
    //   209	214	1029	finally
    //   224	228	1029	finally
    //   228	232	1029	finally
    //   234	239	1029	finally
    //   241	245	1029	finally
    //   247	252	1029	finally
    //   254	259	1029	finally
    //   261	266	1029	finally
    //   270	275	1029	finally
    //   275	279	1029	finally
    //   281	286	1029	finally
    //   288	292	1029	finally
    //   294	299	1029	finally
    //   301	306	1029	finally
    //   310	315	1029	finally
    //   315	319	1029	finally
    //   321	326	1029	finally
    //   328	332	1029	finally
    //   334	339	1029	finally
    //   341	346	1029	finally
    //   350	355	1029	finally
    //   355	359	1029	finally
    //   361	366	1029	finally
    //   372	376	1029	finally
    //   378	383	1029	finally
    //   385	390	1029	finally
    //   392	397	1029	finally
    //   403	408	1029	finally
    //   408	412	1029	finally
    //   414	419	1029	finally
    //   421	426	1029	finally
    //   433	437	1029	finally
    //   439	444	1029	finally
    //   454	459	1029	finally
    //   459	463	1029	finally
    //   465	470	1029	finally
    //   472	477	1029	finally
    //   484	488	1029	finally
    //   490	495	1029	finally
    //   497	502	1029	finally
    //   504	508	1029	finally
    //   510	515	1029	finally
    //   525	530	1029	finally
    //   530	534	1029	finally
    //   536	541	1029	finally
    //   543	548	1029	finally
    //   555	559	1029	finally
    //   561	566	1029	finally
    //   568	573	1029	finally
    //   575	579	1029	finally
    //   581	586	1029	finally
    //   596	601	1029	finally
    //   601	605	1029	finally
    //   607	612	1029	finally
    //   614	619	1029	finally
    //   626	629	1029	finally
    //   642	648	1029	finally
    //   648	652	1029	finally
    //   654	659	1029	finally
    //   665	670	1029	finally
    //   676	681	1029	finally
    //   681	685	1029	finally
    //   687	692	1029	finally
    //   701	706	1029	finally
    //   706	710	1029	finally
    //   712	716	1029	finally
    //   718	723	1029	finally
    //   727	732	1029	finally
    //   732	735	1029	finally
    //   740	743	1029	finally
    //   748	752	1029	finally
    //   754	759	1029	finally
    //   761	766	1029	finally
    //   996	1000	1029	finally
    //   1002	1007	1029	finally
    //   1021	1026	1029	finally
    //   766	770	1899	finally
    //   772	777	1899	finally
    //   779	784	1899	finally
    //   786	789	1899	finally
    //   802	805	1899	finally
    //   812	817	1899	finally
    //   818	821	1899	finally
    //   823	827	1899	finally
    //   829	834	1899	finally
    //   836	841	1899	finally
    //   845	850	1899	finally
    //   855	858	1899	finally
    //   860	865	1899	finally
    //   867	872	1899	finally
    //   883	887	1899	finally
    //   887	892	1899	finally
    //   905	910	1899	finally
    //   910	913	1899	finally
    //   918	922	1899	finally
    //   924	929	1899	finally
    //   936	940	1899	finally
    //   942	946	1899	finally
    //   948	953	1899	finally
    //   961	966	1899	finally
    //   971	974	1899	finally
    //   980	985	1899	finally
    //   987	992	1899	finally
    //   1135	1138	1899	finally
    //   1143	1148	1899	finally
    //   1153	1158	1899	finally
    //   1158	1161	1899	finally
    //   1166	1170	1899	finally
    //   1172	1177	1899	finally
    //   1179	1184	1899	finally
    //   1186	1190	1899	finally
    //   1192	1197	1899	finally
    //   1199	1204	1899	finally
    //   1206	1211	1899	finally
    //   1213	1217	1899	finally
    //   1219	1224	1899	finally
    //   1226	1231	1899	finally
    //   1247	1250	1899	finally
    //   1252	1256	1899	finally
    //   1258	1263	1899	finally
    //   1265	1270	1899	finally
    //   1274	1279	1899	finally
    //   1285	1288	1899	finally
    //   1305	1309	1899	finally
    //   1309	1312	1899	finally
    //   1317	1320	1899	finally
    //   1322	1327	1899	finally
    //   1327	1331	1899	finally
    //   1333	1338	1899	finally
    //   1342	1347	1899	finally
    //   1349	1354	1899	finally
    //   1356	1361	1899	finally
    //   1363	1368	1899	finally
    //   1370	1375	1899	finally
    //   1382	1386	1899	finally
    //   1386	1390	1899	finally
    //   1392	1397	1899	finally
    //   1404	1408	1899	finally
    //   1410	1414	1899	finally
    //   1416	1421	1899	finally
    //   1429	1434	1899	finally
    //   1442	1445	1899	finally
    //   1451	1456	1899	finally
    //   1458	1463	1899	finally
    //   1467	1472	1899	finally
    //   1472	1475	1899	finally
    //   1477	1482	1899	finally
    //   1482	1486	1899	finally
    //   1488	1493	1899	finally
    //   1497	1502	1899	finally
    //   1504	1509	1899	finally
    //   1511	1516	1899	finally
    //   1518	1523	1899	finally
    //   1529	1532	1899	finally
    //   1536	1541	1899	finally
    //   1546	1551	1899	finally
    //   1551	1554	1899	finally
    //   1561	1565	1899	finally
    //   1567	1572	1899	finally
    //   1579	1583	1899	finally
    //   1585	1589	1899	finally
    //   1591	1596	1899	finally
    //   1605	1610	1899	finally
    //   1621	1624	1899	finally
    //   1630	1635	1899	finally
    //   1668	1671	1899	finally
    //   1676	1680	1899	finally
    //   1682	1687	1899	finally
    //   1689	1694	1899	finally
    //   1706	1710	1899	finally
    //   1712	1716	1899	finally
    //   1718	1723	1899	finally
    //   1731	1736	1899	finally
    //   1743	1748	1899	finally
    //   1753	1756	1899	finally
    //   1759	1762	1899	finally
    //   1766	1771	1899	finally
    //   1775	1778	1899	finally
    //   1784	1789	1899	finally
    //   1789	1792	1899	finally
    //   1797	1801	1899	finally
    //   1803	1808	1899	finally
    //   1810	1815	1899	finally
    //   1822	1825	1899	finally
    //   1827	1830	1899	finally
    //   1834	1839	1899	finally
    //   1841	1846	1899	finally
    //   1846	1849	1899	finally
    //   1851	1856	1899	finally
    //   1856	1861	1899	finally
    //   1870	1876	1899	finally
    //   1876	1881	1899	finally
    //   1886	1891	1899	finally
    //   1891	1896	1899	finally
    //   1901	1905	2008	finally
    //   1907	1912	2008	finally
    //   1919	1923	2008	finally
    //   1925	1929	2008	finally
    //   1931	1936	2008	finally
    //   1944	1949	2008	finally
    //   1960	1963	2008	finally
    //   1969	1974	2008	finally
    //   1974	1977	2008	finally
  }
}


/* Location:              /Volumes/D1/codebase/android/POC/assets/product/maind/classes-enjarify.jar!/com/vvt/http/MyUncaughtExceptionHandler.class
 * Java compiler version: 5 (49.0)
 * JD-Core Version:       0.7.1
 */